Workbook
Name \__: #REF!
Name \0: #REF!
Name \0: #REF!
Name \0: #N/A
Name \1: "#REF!"
Name \3671: #REF!
Name \A: #REF!
Name \AA: #REF!
Name \ab: #REF!
Name \B: #REF!
Name \b: #N/A
Name \BA: "#REF!"
Name \c: #N/A
Name \C: #REF!
Name \C: #REF!
Name \CALCS: "#REF!"
Name \CC: #REF!
Name \D: #REF!
Name \DATA: "#REF!"
Name \E: #REF!
Name \F: #REF!
Name \G: #REF!
Name \gvfbd: #REF!
Name \gzfbhxcn: #REF!
Name \h: #REF!
Name \I: #REF!
Name \i: #N/A
Name \INSERT: "#REF!"
Name \j: #REF!
Name \k: #REF!
Name \l: #REF!
Name \LA: "#REF!"
Name \LP: "#REF!"
Name \LPS: "#REF!"
Name \m: #REF!
Name \MENU: "#REF!"
Name \n: #REF!
Name \o: #REF!
Name \OO: #REF!
Name \p: #N/A
Name \p: #REF!
Name \PRIME: "#REF!"
Name \PRINT: "#REF!"
Name \Q: #REF!
Name \q: #N/A
Name \r: #REF!
Name \s: #N/A
Name \SORT: "#REF!"
Name \t: #REF!
Name \U: #REF!
Name \V: #REF!
Name \v1: #REF!
Name \w: "#REF!"
Name \X: #REF!
Name \X: #REF!
Name \Y: #REF!
Name \z: #REF!
Name \Z: #REF!
Name \Z: #REF!
Name \z: #N/A

Sheet Building
C3: Scope | D3: (Multiple Items)
C5: Sum of Element Rate | D5: Column Labels
C6: Row Labels | D6: PROJECT 1 Low Rise | E6: PROJECT 3 Mid Rise | F6: PROJECT 5 High Rise | G6: PROJECT 6 High Rise | H6: PROJECT 2 Low Rise | I6: PROJECT 4A Mid Rise | J6: PROJECT 4B Mid Rise
C7: Substructure | D7: 589.9803 | E7: 594.86581 | F7: 617.31212 | G7: 545.08 | H7: 601.71625 | I7: 650 | J7: 572.0189
C8: Superstructure | D8: 1001.3 | E8: 1191.8597 | F8: 1447.4739 | G8: 1736.9687 | H8: 1441.417 | I8: 750 | J8: 1062.0403
C9: Building External Envelope | D9: 1156.329 | E9: 1141.4016 | F9: 1014.5703 | G9: 995.62244 | H9: 1126.4742 | I9: 393.55793 | J9: 1141.4016
C10: Internal Walls and Doors | D10: 189.45266 | E10: 140.2757 | F10: 153.63058 | G10: 397.404 | H10: 229.36243 | I10: 143.80656 | J10: 241.0282
C11: Internal Finishes | D11: 364.90458 | E11: 546.59152 | F11: 507.13993 | G11: 601.25067 | H11: 474.30868 | I11: 200.56366 | J11: 373.57759
C12: FF&E | D12: 32.948289 | E12: 98.128713 | F12: 110.68981 | G12: 170 | H12: 53.839147 | I12: 82.957606 | J12: 129.85718
C13: Sanitary Fittings | D13: 47.363165 | E13: 9.6741862 | F13: 108.919 | G13: 116.28 | H13: 36.10156 | I13: 81.630449 | J13: 83.368326
C14: Services Equipment | D14: 10.29634 | E14: 20.960737 | F14: 46.700281 | G14: 45 | H14: 16.919026 | I14: 10.817758 | J14: 19.5
C15: Mechanical | D15: 875.6979 | E15: 1035.1379 | F15: 1086.0617 | G15: 1252.86 | H15: 822.55123 | I15: 806.47367 | J15: 785.48212
C16: Electrical | D16: 745.45503 | E16: 1181.8631 | F16: 1219.1509 | G16: 1568.184 | H16: 816.76494 | I16: 714.46314 | J16: 870.11785
C17: Conveying Systems | D17: 94.41744 | E17: 227.0209 | F17: 209.91109 | G17: 152.76 | H17: 44.454315 | I17: 106.80776 | J17: 169.13155
C18: External Works | D18: 499.47547 | E18: 588.42368 | F18: 418.18821 | G18: 943.10328 | H18: 637.71753 | I18: 403.01749 | J18: 436.53237
... C20: Grand Total | D20: 5607.6202 | E20: 6776.2036 | F20: 6939.7479 | G20: 8524.5131 | H20: 6301.6264 | I20: 4344.096 | J20: 5884.056
C46: Scope | D46: 02- Multi Family
C48: Sum of Element Rate | D48: Column Labels
C49: Row Labels | D49: MF PROJECT 1 | E49: MF PROJECT 2 | F49: MF PROJECT 3 | G49: MF PROJECT 4 | H49: MF PROJECT 5 | I49: MF PROJECT 6
C50: General Requirements | D50: 0 | E50: 0 | F50: 0 | G50: 0 | H50: 0 | I50: 0
C51: Substructure | D51: 373 | E51: 452 | F51: 456 | G51: 314 | H51: 286 | I51: 294
C52: Superstructure | D52: 892 | E52: 927 | F52: 922 | G52: 891.8 | H52: 951 | I52: 767
C53: Building External Envelope | D53: 409 | E53: 415 | F53: 683.8 | G53: 954 | H53: 663 | I53: 978
C54: Internal Walls and Doors | D54: 317 | E54: 540 | F54: 238 | G54: 590 | H54: 196 | I54: 440
C55: Internal Finishes | D55: 675 | E55: 605 | F55: 1010 | G55: 1138 | H55: 549 | I55: 1172
C56: FF&E | D56: 413 | E56: 394 | F56: 232 | G56: 359 | H56: 307 | I56: 481
C57: Sanitary Fittings | D57: 85 | E57: 117 | F57: 88 | G57: 181 | H57: 68 | I57: 155
C58: Services Equipment | D58: 51 | E58: 56 | F58: 94 | G58: 94 | H58: 175 | I58: 94
C59: Mechanical | D59: 759 | E59: 781 | F59: 968 | G59: 1108 | H59: 1503 | I59: 1421
C60: Electrical | D60: 1292 | E60: 1303 | F60: 1377 | G60: 1040 | H60: 1376 | I60: 1212
C61: Conveying Systems | D61: 278 | E61: 276 | F61: 102 | G61: 160 | H61: 197 | I61: 53
... C63: Grand Total | D63: 5988 | E63: 6335 | F63: 6733.8 | G63: 7402.8 | H63: 6773 | I63: 7625

Sheet GCover

Sheet QA.QC
A1: Quality Assurance
A3: CONTROLLED DOCUMENT DISTRIBUTION
A5: VERSION | B5: date of issue | C5: method | D5: issued to
A6: Rev 00
A12: QUALITY ASSURANCE & CONTACT DETAILS
A14: QA / QC CHECK | B14: NAME | C14: CONTACT TELEPHONE | D14: E-MAIL ADDRESS
A15: Prepared By
A19: Checked By
A28: Approved By

Sheet Contents
A2: Contents
A4: Section | C4: Headings
A5: Section 1 | C5: Introduction
A6: Section 2 | C6: Executive Summary
B7: 2.2 | C7: Executive Summary Building
B8: 2.2 | C8: Executive Summary infrastructure
A9: Section 3 | C9: Dataset
A10: Section 4 | C10: Data Interrogation Charts
A11: Section 5
A12: Section 6
A13: Section 7
A14: Section 8

Sheet 1. Introduction
A2: 1. Introduction
A4: 1.1 Project Data
A6: Project/asset name | B6: RUA Al Madinah Superblock 5
A8: Building type | B8: Hotels + Residential Apartment Building + 4 Level Common Basement
A10: Fit out level | B10: Complete Building including Fit out
A12: Construction stage duration (Months) | B12: TBC
A14: Procurement stage | B14: Detail Design
A16: Gross internal area (GIA) | B16: 642637.65 | C16: m2
A18: Gross external area (GEA) | B18: 670375 | C18: m2
A26: Building Type: | B26: Hotels + Residential Apartment Building + 4 Level Common Basement (Mixed Used)
A28: Scope of works: | B28: The Superblock 5 consists of 4 and 5 star international hotels, as well as one apartment building. All the 18 no. buildings will share a common 4 level basement.
A30: Enabling works: | B30: Traditional bulk excavation of a depth of 12 meters, Shoring & Piling
A32: Substructure: | B32: Four level basements to accommodate parking and MEP services
A34: Superstructure: | B34: Construction of 18 nrs of hotel towers + residential towers which are in 3 clusters; superstructure levels varies from 12 floors to 21 floors
A36: Envelope: | B36: Aesthetic envelop consist with curtain walls and building façade
A38: Internal fitting out: | B38: All the fitting out and finishes consist with high-end
A40: Heating and cooling: | B40: Central cooling, Centralized hot and cold water system.
A42: Electrical and data: | B42: MEP services to medium specifications; Electrical main and sub main, power, lighting, fire fighting, communication systems and security systems.
A44: External works: | B44: Asphalt roads, pre-cast concrete pavers, hydraulically pressed precast kerbs, natural granite, soft scaping and irrigation system to planting, site furniture, water features
A46: Procurement Route: | B46: The Cost Plan prepared based on the traditional procurement method, designed by the employer.
A54: 1.2 Basis of Costs
A56: a) The Detail Design Cost Plan has been priced based on Q1 2024 market rates.
A57: b) The area schedules used have been prepared by De Leeuw International based on the Drawings provided.
A58: c) All areas indicated above are subject to design development and could vary as a consequence of site surveys, Planning and NOC requirements.
A59: d) At this stage of design development all quantities shown are indicative and to be refined when the design evolves
A60: e) All the quantities have been provided by Rua (via P&T design consultant). Omnium have carried out the pricing exercise for the BoQ and produced the estimate.
A61: 1.3 Assumptions
A63: General
A64: a) Excavated material can be disposed within 30km of the site location.
A65: b) The majority of building materials are available locally or within Gulf Corporation countries; international specifications are minimal.
A67: Civil/Structural/Architectural
A68: a) 4m level difference in site levels considered for pricing
... A216: - ongoing supply chain issues due to Covid pandemic

Sheet Exec Summ Buildings
B2: Residential | E2: Multi Family | H2: Commercial | K2: Retail
A3: Group Elements | B3: Villa Average | C3: Townhouse Average | D3: Duplex Average | E3: Low-rise Average | F3: Mid-rise Average | G3: High Rise Average | H3: Com-Low-rise Average | I3: Com-Mid-rise Average | J3: Com-High Rise Average | K3: Neighbourhood Centre Average | L3: District Centre (Community Mall) Average | M3: Mixed Use Retail Average | N3: Outlet Mall Average | O3: Lifestyle Retail Average | P3: Regional Mall Average
A4: Substructure | B4: =+INDEX('Building Pivot'!$B$11:$BJ$23,MATCH($A4,'Building Pivot'!$A$11:$A$23,0),MATCH(B$3,'Building Pivot'!$B$9:$BJ$9,0)) -> 316.25 | C4: =+INDEX('Building Pivot'!$B$11:$BJ$23,MATCH($A4,'Building Pivot'!$A$11:$A$23,0),MATCH(C$3,'Building Pivot'!$B$9:$BJ$9,0)) -> 230.66667 | D4: =+INDEX('Building Pivot'!$B$11:$BJ$23,MATCH(A4,'Building Pivot'!$A$11:$A$23,0),MATCH(D$3,'Building Pivot'!$B$9:$BJ$9,0)) -> 230.5 | E4: =+INDEX('Building Pivot'!$B$11:$BJ$23,MATCH($A4,'Building Pivot'!$A$11:$A$23,0),MATCH(E$3,'Building Pivot'!$B$9:$BJ$9,0)) -> 294 | F4: =+INDEX('Building Pivot'!$B$11:$BJ$23,MATCH($A4,'Building Pivot'!$A$11:$A$23,0),MATCH(F$3,'Building Pivot'!$B$9:$BJ$9,0)) -> 352 | G4: =+INDEX('Building Pivot'!$B$11:$BJ$23,MATCH($A4,'Building Pivot'!$A$11:$A$23,0),MATCH(G$3,'Building Pivot'!$B$9:$BJ$9,0)) -> 412.5 | H4: =+INDEX('Building Pivot'!$B$11:$BJ$23,MATCH($A4,'Building Pivot'!$A$11:$A$23,0),MATCH(H$3,'Building Pivot'!$B$9:$BJ$9,0)) -> 595.84827 | I4: =+INDEX('Building Pivot'!$B$11:$BJ$23,MATCH($A4,'Building Pivot'!$A$11:$A$23,0),MATCH(I$3,'Building Pivot'!$B$9:$BJ$9,0)) -> 605.62824 | J4: =+INDEX('Building Pivot'!$B$11:$BJ$23,MATCH($A4,'Building Pivot'!$A$11:$A$23,0),MATCH(J$3,'Building Pivot'!$B$9:$BJ$9,0)) -> 581.19606 | K4: =+INDEX('Building Pivot'!$B$11:$BJ$23,MATCH($A4,'Building Pivot'!$A$11:$A$23,0),MATCH(K$3,'Building Pivot'!$B$9:$BJ$9,0)) -> 660 | L4: =+INDEX('Building Pivot'!$B$11:$BJ$23,MATCH($A4,'Building Pivot'!$A$11:$A$23,0),MATCH(L$3,'Building Pivot'!$B$9:$BJ$9,0)) -> 557 | ... P4: =+INDEX('Building Pivot'!$B$11:$BJ$23,MATCH($A4,'Building Pivot'!$A$11:$A$23,0),MATCH(P$3,'Building Pivot'!$B$9:$BJ$9,0)) -> 651
A5: Superstructure | B5: =+INDEX('Building Pivot'!$B$11:$BJ$23,MATCH($A5,'Building Pivot'!$A$11:$A$23,0),MATCH(B$3,'Building Pivot'!$B$9:$BJ$9,0)) -> 554.25 | C5: =+INDEX('Building Pivot'!$B$11:$BJ$23,MATCH($A5,'Building Pivot'!$A$11:$A$23,0),MATCH(C$3,'Building Pivot'!$B$9:$BJ$9,0)) -> 435 | D5: =+INDEX('Building Pivot'!$B$11:$BJ$23,MATCH(A5,'Building Pivot'!$A$11:$A$23,0),MATCH(D$3,'Building Pivot'!$B$9:$BJ$9,0)) -> 450.5 | E5: =+INDEX('Building Pivot'!$B$11:$BJ$23,MATCH($A5,'Building Pivot'!$A$11:$A$23,0),MATCH(E$3,'Building Pivot'!$B$9:$BJ$9,0)) -> 767 | F5: =+INDEX('Building Pivot'!$B$11:$BJ$23,MATCH($A5,'Building Pivot'!$A$11:$A$23,0),MATCH(F$3,'Building Pivot'!$B$9:$BJ$9,0)) -> 921.6 | G5: =+INDEX('Building Pivot'!$B$11:$BJ$23,MATCH($A5,'Building Pivot'!$A$11:$A$23,0),MATCH(G$3,'Building Pivot'!$B$9:$BJ$9,0)) -> 909.5 | H5: =+INDEX('Building Pivot'!$B$11:$BJ$23,MATCH($A5,'Building Pivot'!$A$11:$A$23,0),MATCH(H$3,'Building Pivot'!$B$9:$BJ$9,0)) -> 1221.3585 | I5: =+INDEX('Building Pivot'!$B$11:$BJ$23,MATCH($A5,'Building Pivot'!$A$11:$A$23,0),MATCH(I$3,'Building Pivot'!$B$9:$BJ$9,0)) -> 1001.3 | J5: =+INDEX('Building Pivot'!$B$11:$BJ$23,MATCH($A5,'Building Pivot'!$A$11:$A$23,0),MATCH(J$3,'Building Pivot'!$B$9:$BJ$9,0)) -> 1592.2213 | K5: =+INDEX('Building Pivot'!$B$11:$BJ$23,MATCH($A5,'Building Pivot'!$A$11:$A$23,0),MATCH(K$3,'Building Pivot'!$B$9:$BJ$9,0)) -> 850 | L5: =+INDEX('Building Pivot'!$B$11:$BJ$23,MATCH($A5,'Building Pivot'!$A$11:$A$23,0),MATCH(L$3,'Building Pivot'!$B$9:$BJ$9,0)) -> 1463 | ... P5: =+INDEX('Building Pivot'!$B$11:$BJ$23,MATCH($A5,'Building Pivot'!$A$11:$A$23,0),MATCH(P$3,'Building Pivot'!$B$9:$BJ$9,0)) -> 1460.5
A6: Building External Envelope | B6: =+INDEX('Building Pivot'!$B$11:$BJ$23,MATCH($A6,'Building Pivot'!$A$11:$A$23,0),MATCH(B$3,'Building Pivot'!$B$9:$BJ$9,0)) -> 805.775 | C6: =+INDEX('Building Pivot'!$B$11:$BJ$23,MATCH($A6,'Building Pivot'!$A$11:$A$23,0),MATCH(C$3,'Building Pivot'!$B$9:$BJ$9,0)) -> 755.33333 | D6: =+INDEX('Building Pivot'!$B$11:$BJ$23,MATCH($A6,'Building Pivot'!$A$11:$A$23,0),MATCH(D$3,'Building Pivot'!$B$9:$BJ$9,0)) -> 896.75 | E6: =+INDEX('Building Pivot'!$B$11:$BJ$23,MATCH($A6,'Building Pivot'!$A$11:$A$23,0),MATCH(E$3,'Building Pivot'!$B$9:$BJ$9,0)) -> 978 | F6: =+INDEX('Building Pivot'!$B$11:$BJ$23,MATCH($A6,'Building Pivot'!$A$11:$A$23,0),MATCH(F$3,'Building Pivot'!$B$9:$BJ$9,0)) -> 766.93333 | G6: =+INDEX('Building Pivot'!$B$11:$BJ$23,MATCH($A6,'Building Pivot'!$A$11:$A$23,0),MATCH(G$3,'Building Pivot'!$B$9:$BJ$9,0)) -> 412 | H6: =+INDEX('Building Pivot'!$B$11:$BJ$23,MATCH($A6,'Building Pivot'!$A$11:$A$23,0),MATCH(H$3,'Building Pivot'!$B$9:$BJ$9,0)) -> 1141.4016 | I6: =+INDEX('Building Pivot'!$B$11:$BJ$23,MATCH($A6,'Building Pivot'!$A$11:$A$23,0),MATCH(I$3,'Building Pivot'!$B$9:$BJ$9,0)) -> 892.12039 | ... P6: =+INDEX('Building Pivot'!$B$11:$BJ$23,MATCH($A6,'Building Pivot'!$A$11:$A$23,0),MATCH(P$3,'Building Pivot'!$B$9:$BJ$9,0)) -> 974.9
A7: Internal Walls and Doors | B7: =+INDEX('Building Pivot'!$B$11:$BJ$23,MATCH($A7,'Building Pivot'!$A$11:$A$23,0),MATCH(B$3,'Building Pivot'!$B$9:$BJ$9,0)) -> 238 | C7: =+INDEX('Building Pivot'!$B$11:$BJ$23,MATCH($A7,'Building Pivot'!$A$11:$A$23,0),MATCH(C$3,'Building Pivot'!$B$9:$BJ$9,0)) -> 243.66667 | D7: =+INDEX('Building Pivot'!$B$11:$BJ$23,MATCH(A7,'Building Pivot'!$A$11:$A$23,0),MATCH(D$3,'Building Pivot'!$B$9:$BJ$9,0)) -> 297.5 | E7: =+INDEX('Building Pivot'!$B$11:$BJ$23,MATCH($A7,'Building Pivot'!$A$11:$A$23,0),MATCH(E$3,'Building Pivot'!$B$9:$BJ$9,0)) -> 440 | F7: =+INDEX('Building Pivot'!$B$11:$BJ$23,MATCH($A7,'Building Pivot'!$A$11:$A$23,0),MATCH(F$3,'Building Pivot'!$B$9:$BJ$9,0)) -> 341.33333 | G7: =+INDEX('Building Pivot'!$B$11:$BJ$23,MATCH($A7,'Building Pivot'!$A$11:$A$23,0),MATCH(G$3,'Building Pivot'!$B$9:$BJ$9,0)) -> 428.5 | H7: =+INDEX('Building Pivot'!$B$11:$BJ$23,MATCH($A7,'Building Pivot'!$A$11:$A$23,0),MATCH(H$3,'Building Pivot'!$B$9:$BJ$9,0)) -> 209.40754 | I7: =+INDEX('Building Pivot'!$B$11:$BJ$23,MATCH($A7,'Building Pivot'!$A$11:$A$23,0),MATCH(I$3,'Building Pivot'!$B$9:$BJ$9,0)) -> 175.03682 | J7: =+INDEX('Building Pivot'!$B$11:$BJ$23,MATCH($A7,'Building Pivot'!$A$11:$A$23,0),MATCH(J$3,'Building Pivot'!$B$9:$BJ$9,0)) -> 275.51729 | K7: =+INDEX('Building Pivot'!$B$11:$BJ$23,MATCH($A7,'Building Pivot'!$A$11:$A$23,0),MATCH(K$3,'Building Pivot'!$B$9:$BJ$9,0)) -> 45 | L7: =+INDEX('Building Pivot'!$B$11:$BJ$23,MATCH($A7,'Building Pivot'!$A$11:$A$23,0),MATCH(L$3,'Building Pivot'!$B$9:$BJ$9,0)) -> 209 | ... P7: =+INDEX('Building Pivot'!$B$11:$BJ$23,MATCH($A7,'Building Pivot'!$A$11:$A$23,0),MATCH(P$3,'Building Pivot'!$B$9:$BJ$9,0)) -> 169
A8: Internal Finishes | B8: =+INDEX('Building Pivot'!$B$11:$BJ$23,MATCH($A8,'Building Pivot'!$A$11:$A$23,0),MATCH(B$3,'Building Pivot'!$B$9:$BJ$9,0)) -> 314.5 | C8: =+INDEX('Building Pivot'!$B$11:$BJ$23,MATCH($A8,'Building Pivot'!$A$11:$A$23,0),MATCH(C$3,'Building Pivot'!$B$9:$BJ$9,0)) -> 270.66667 | D8: =+INDEX('Building Pivot'!$B$11:$BJ$23,MATCH(A8,'Building Pivot'!$A$11:$A$23,0),MATCH(D$3,'Building Pivot'!$B$9:$BJ$9,0)) -> 158 | E8: =+INDEX('Building Pivot'!$B$11:$BJ$23,MATCH($A8,'Building Pivot'!$A$11:$A$23,0),MATCH(E$3,'Building Pivot'!$B$9:$BJ$9,0)) -> 1172 | F8: =+INDEX('Building Pivot'!$B$11:$BJ$23,MATCH($A8,'Building Pivot'!$A$11:$A$23,0),MATCH(F$3,'Building Pivot'!$B$9:$BJ$9,0)) -> 899 | G8: =+INDEX('Building Pivot'!$B$11:$BJ$23,MATCH($A8,'Building Pivot'!$A$11:$A$23,0),MATCH(G$3,'Building Pivot'!$B$9:$BJ$9,0)) -> 640 | H8: =+INDEX('Building Pivot'!$B$11:$BJ$23,MATCH($A8,'Building Pivot'!$A$11:$A$23,0),MATCH(H$3,'Building Pivot'!$B$9:$BJ$9,0)) -> 419.60663 | I8: =+INDEX('Building Pivot'!$B$11:$BJ$23,MATCH($A8,'Building Pivot'!$A$11:$A$23,0),MATCH(I$3,'Building Pivot'!$B$9:$BJ$9,0)) -> 373.57759 | J8: =+INDEX('Building Pivot'!$B$11:$BJ$23,MATCH($A8,'Building Pivot'!$A$11:$A$23,0),MATCH(J$3,'Building Pivot'!$B$9:$BJ$9,0)) -> 554.1953 | K8: =+INDEX('Building Pivot'!$B$11:$BJ$23,MATCH($A8,'Building Pivot'!$A$11:$A$23,0),MATCH(K$3,'Building Pivot'!$B$9:$BJ$9,0)) -> 120 | L8: =+INDEX('Building Pivot'!$B$11:$BJ$23,MATCH($A8,'Building Pivot'!$A$11:$A$23,0),MATCH(L$3,'Building Pivot'!$B$9:$BJ$9,0)) -> 383 | ... P8: =+INDEX('Building Pivot'!$B$11:$BJ$23,MATCH($A8,'Building Pivot'!$A$11:$A$23,0),MATCH(P$3,'Building Pivot'!$B$9:$BJ$9,0)) -> 309
A9: FF&E | B9: =+INDEX('Building Pivot'!$B$11:$BJ$23,MATCH($A9,'Building Pivot'!$A$11:$A$23,0),MATCH(B$3,'Building Pivot'!$B$9:$BJ$9,0)) -> 189 | C9: =+INDEX('Building Pivot'!$B$11:$BJ$23,MATCH($A9,'Building Pivot'!$A$11:$A$23,0),MATCH(C$3,'Building Pivot'!$B$9:$BJ$9,0)) -> 161.66667 | D9: =+INDEX('Building Pivot'!$B$11:$BJ$23,MATCH(A9,'Building Pivot'!$A$11:$A$23,0),MATCH(D$3,'Building Pivot'!$B$9:$BJ$9,0)) -> 106 | E9: =+INDEX('Building Pivot'!$B$11:$BJ$23,MATCH($A9,'Building Pivot'!$A$11:$A$23,0),MATCH(E$3,'Building Pivot'!$B$9:$BJ$9,0)) -> 481 | F9: =+INDEX('Building Pivot'!$B$11:$BJ$23,MATCH($A9,'Building Pivot'!$A$11:$A$23,0),MATCH(F$3,'Building Pivot'!$B$9:$BJ$9,0)) -> 299.33333 | G9: =+INDEX('Building Pivot'!$B$11:$BJ$23,MATCH($A9,'Building Pivot'!$A$11:$A$23,0),MATCH(G$3,'Building Pivot'!$B$9:$BJ$9,0)) -> 403.5 | H9: =+INDEX('Building Pivot'!$B$11:$BJ$23,MATCH($A9,'Building Pivot'!$A$11:$A$23,0),MATCH(H$3,'Building Pivot'!$B$9:$BJ$9,0)) -> 43.393718 | I9: =+INDEX('Building Pivot'!$B$11:$BJ$23,MATCH($A9,'Building Pivot'!$A$11:$A$23,0),MATCH(I$3,'Building Pivot'!$B$9:$BJ$9,0)) -> 103.64783 | J9: =+INDEX('Building Pivot'!$B$11:$BJ$23,MATCH($A9,'Building Pivot'!$A$11:$A$23,0),MATCH(J$3,'Building Pivot'!$B$9:$BJ$9,0)) -> 140.34491 | K9: =+INDEX('Building Pivot'!$B$11:$BJ$23,MATCH($A9,'Building Pivot'!$A$11:$A$23,0),MATCH(K$3,'Building Pivot'!$B$9:$BJ$9,0)) -> 115 | L9: =+INDEX('Building Pivot'!$B$11:$BJ$23,MATCH($A9,'Building Pivot'!$A$11:$A$23,0),MATCH(L$3,'Building Pivot'!$B$9:$BJ$9,0)) -> 209 | ... P9: =+INDEX('Building Pivot'!$B$11:$BJ$23,MATCH($A9,'Building Pivot'!$A$11:$A$23,0),MATCH(P$3,'Building Pivot'!$B$9:$BJ$9,0)) -> 121.5
A10: Sanitary Fittings | B10: =+INDEX('Building Pivot'!$B$11:$BJ$23,MATCH($A10,'Building Pivot'!$A$11:$A$23,0),MATCH(B$3,'Building Pivot'!$B$9:$BJ$9,0)) -> 76.25 | C10: =+INDEX('Building Pivot'!$B$11:$BJ$23,MATCH($A10,'Building Pivot'!$A$11:$A$23,0),MATCH(C$3,'Building Pivot'!$B$9:$BJ$9,0)) -> 63.333333 | D10: =+INDEX('Building Pivot'!$B$11:$BJ$23,MATCH(A10,'Building Pivot'!$A$11:$A$23,0),MATCH(D$3,'Building Pivot'!$B$9:$BJ$9,0)) -> 66.25 | E10: =+INDEX('Building Pivot'!$B$11:$BJ$23,MATCH($A10,'Building Pivot'!$A$11:$A$23,0),MATCH(E$3,'Building Pivot'!$B$9:$BJ$9,0)) -> 155 | F10: =+INDEX('Building Pivot'!$B$11:$BJ$23,MATCH($A10,'Building Pivot'!$A$11:$A$23,0),MATCH(F$3,'Building Pivot'!$B$9:$BJ$9,0)) -> 112.33333 | G10: =+INDEX('Building Pivot'!$B$11:$BJ$23,MATCH($A10,'Building Pivot'!$A$11:$A$23,0),MATCH(G$3,'Building Pivot'!$B$9:$BJ$9,0)) -> 101 | H10: =+INDEX('Building Pivot'!$B$11:$BJ$23,MATCH($A10,'Building Pivot'!$A$11:$A$23,0),MATCH(H$3,'Building Pivot'!$B$9:$BJ$9,0)) -> 41.732363 | I10: =+INDEX('Building Pivot'!$B$11:$BJ$23,MATCH($A10,'Building Pivot'!$A$11:$A$23,0),MATCH(I$3,'Building Pivot'!$B$9:$BJ$9,0)) -> 58.22432 | J10: =+INDEX('Building Pivot'!$B$11:$BJ$23,MATCH($A10,'Building Pivot'!$A$11:$A$23,0),MATCH(J$3,'Building Pivot'!$B$9:$BJ$9,0)) -> 112.5995 | K10: =+INDEX('Building Pivot'!$B$11:$BJ$23,MATCH($A10,'Building Pivot'!$A$11:$A$23,0),MATCH(K$3,'Building Pivot'!$B$9:$BJ$9,0)) -> 25 | L10: =+INDEX('Building Pivot'!$B$11:$BJ$23,MATCH($A10,'Building Pivot'!$A$11:$A$23,0),MATCH(L$3,'Building Pivot'!$B$9:$BJ$9,0)) -> 70 | ... P10: =+INDEX('Building Pivot'!$B$11:$BJ$23,MATCH($A10,'Building Pivot'!$A$11:$A$23,0),MATCH(P$3,'Building Pivot'!$B$9:$BJ$9,0)) -> 82
A11: Services Equipment | B11: =+INDEX('Building Pivot'!$B$11:$BJ$23,MATCH($A11,'Building Pivot'!$A$11:$A$23,0),MATCH(B$3,'Building Pivot'!$B$9:$BJ$9,0)) -> 0 | C11: =+INDEX('Building Pivot'!$B$11:$BJ$23,MATCH($A11,'Building Pivot'!$A$11:$A$23,0),MATCH(C$3,'Building Pivot'!$B$9:$BJ$9,0)) -> 0 | D11: =+INDEX('Building Pivot'!$B$11:$BJ$23,MATCH(A11,'Building Pivot'!$A$11:$A$23,0),MATCH(D$3,'Building Pivot'!$B$9:$BJ$9,0)) -> 0 | E11: =+INDEX('Building Pivot'!$B$11:$BJ$23,MATCH($A11,'Building Pivot'!$A$11:$A$23,0),MATCH(E$3,'Building Pivot'!$B$9:$BJ$9,0)) -> 94 | F11: =+INDEX('Building Pivot'!$B$11:$BJ$23,MATCH($A11,'Building Pivot'!$A$11:$A$23,0),MATCH(F$3,'Building Pivot'!$B$9:$BJ$9,0)) -> 121 | G11: =+INDEX('Building Pivot'!$B$11:$BJ$23,MATCH($A11,'Building Pivot'!$A$11:$A$23,0),MATCH(G$3,'Building Pivot'!$B$9:$BJ$9,0)) -> 53.5 | H11: =+INDEX('Building Pivot'!$B$11:$BJ$23,MATCH($A11,'Building Pivot'!$A$11:$A$23,0),MATCH(H$3,'Building Pivot'!$B$9:$BJ$9,0)) -> 13.607683 | I11: =+INDEX('Building Pivot'!$B$11:$BJ$23,MATCH($A11,'Building Pivot'!$A$11:$A$23,0),MATCH(I$3,'Building Pivot'!$B$9:$BJ$9,0)) -> 17.092831 | J11: =+INDEX('Building Pivot'!$B$11:$BJ$23,MATCH($A11,'Building Pivot'!$A$11:$A$23,0),MATCH(J$3,'Building Pivot'!$B$9:$BJ$9,0)) -> 45.850141 | K11: =+INDEX('Building Pivot'!$B$11:$BJ$23,MATCH($A11,'Building Pivot'!$A$11:$A$23,0),MATCH(K$3,'Building Pivot'!$B$9:$BJ$9,0)) -> 0 | L11: =+INDEX('Building Pivot'!$B$11:$BJ$23,MATCH($A11,'Building Pivot'!$A$11:$A$23,0),MATCH(L$3,'Building Pivot'!$B$9:$BJ$9,0)) -> 0 | ... P11: =+INDEX('Building Pivot'!$B$11:$BJ$23,MATCH($A11,'Building Pivot'!$A$11:$A$23,0),MATCH(P$3,'Building Pivot'!$B$9:$BJ$9,0)) -> 53
A12: Mechanical | B12: =+INDEX('Building Pivot'!$B$11:$BJ$23,MATCH($A12,'Building Pivot'!$A$11:$A$23,0),MATCH(B$3,'Building Pivot'!$B$9:$BJ$9,0)) -> 545.75 | C12: =+INDEX('Building Pivot'!$B$11:$BJ$23,MATCH($A12,'Building Pivot'!$A$11:$A$23,0),MATCH(C$3,'Building Pivot'!$B$9:$BJ$9,0)) -> 530.95833 | D12: =+INDEX('Building Pivot'!$B$11:$BJ$23,MATCH(A12,'Building Pivot'!$A$11:$A$23,0),MATCH(D$3,'Building Pivot'!$B$9:$BJ$9,0)) -> 568 | E12: =+INDEX('Building Pivot'!$B$11:$BJ$23,MATCH($A12,'Building Pivot'!$A$11:$A$23,0),MATCH(E$3,'Building Pivot'!$B$9:$BJ$9,0)) -> 1421 | F12: =+INDEX('Building Pivot'!$B$11:$BJ$23,MATCH($A12,'Building Pivot'!$A$11:$A$23,0),MATCH(F$3,'Building Pivot'!$B$9:$BJ$9,0)) -> 1193 | G12: =+INDEX('Building Pivot'!$B$11:$BJ$23,MATCH($A12,'Building Pivot'!$A$11:$A$23,0),MATCH(G$3,'Building Pivot'!$B$9:$BJ$9,0)) -> 770 | H12: =+INDEX('Building Pivot'!$B$11:$BJ$23,MATCH($A12,'Building Pivot'!$A$11:$A$23,0),MATCH(H$3,'Building Pivot'!$B$9:$BJ$9,0)) -> 849.12457 | I12: =+INDEX('Building Pivot'!$B$11:$BJ$23,MATCH($A12,'Building Pivot'!$A$11:$A$23,0),MATCH(I$3,'Building Pivot'!$B$9:$BJ$9,0)) -> 875.6979 | J12: =+INDEX('Building Pivot'!$B$11:$BJ$23,MATCH($A12,'Building Pivot'!$A$11:$A$23,0),MATCH(J$3,'Building Pivot'!$B$9:$BJ$9,0)) -> 1169.4609 | K12: =+INDEX('Building Pivot'!$B$11:$BJ$23,MATCH($A12,'Building Pivot'!$A$11:$A$23,0),MATCH(K$3,'Building Pivot'!$B$9:$BJ$9,0)) -> 520 | L12: =+INDEX('Building Pivot'!$B$11:$BJ$23,MATCH($A12,'Building Pivot'!$A$11:$A$23,0),MATCH(L$3,'Building Pivot'!$B$9:$BJ$9,0)) -> 836 | ... P12: =+INDEX('Building Pivot'!$B$11:$BJ$23,MATCH($A12,'Building Pivot'!$A$11:$A$23,0),MATCH(P$3,'Building Pivot'!$B$9:$BJ$9,0)) -> 810.5
A13: Electrical | B13: =+INDEX('Building Pivot'!$B$11:$BJ$23,MATCH($A13,'Building Pivot'!$A$11:$A$23,0),MATCH(B$3,'Building Pivot'!$B$9:$BJ$9,0)) -> 417.25 | C13: =+INDEX('Building Pivot'!$B$11:$BJ$23,MATCH($A13,'Building Pivot'!$A$11:$A$23,0),MATCH(C$3,'Building Pivot'!$B$9:$BJ$9,0)) -> 438.20833 | D13: =+INDEX('Building Pivot'!$B$11:$BJ$23,MATCH(A13,'Building Pivot'!$A$11:$A$23,0),MATCH(D$3,'Building Pivot'!$B$9:$BJ$9,0)) -> 476 | E13: =+INDEX('Building Pivot'!$B$11:$BJ$23,MATCH($A13,'Building Pivot'!$A$11:$A$23,0),MATCH(E$3,'Building Pivot'!$B$9:$BJ$9,0)) -> 1212 | F13: =+INDEX('Building Pivot'!$B$11:$BJ$23,MATCH($A13,'Building Pivot'!$A$11:$A$23,0),MATCH(F$3,'Building Pivot'!$B$9:$BJ$9,0)) -> 1264.3333 | G13: =+INDEX('Building Pivot'!$B$11:$BJ$23,MATCH($A13,'Building Pivot'!$A$11:$A$23,0),MATCH(G$3,'Building Pivot'!$B$9:$BJ$9,0)) -> 1297.5 | H13: =+INDEX('Building Pivot'!$B$11:$BJ$23,MATCH($A13,'Building Pivot'!$A$11:$A$23,0),MATCH(H$3,'Building Pivot'!$B$9:$BJ$9,0)) -> 781.10999 | I13: =+INDEX('Building Pivot'!$B$11:$BJ$23,MATCH($A13,'Building Pivot'!$A$11:$A$23,0),MATCH(I$3,'Building Pivot'!$B$9:$BJ$9,0)) -> 922.14802 | J13: =+INDEX('Building Pivot'!$B$11:$BJ$23,MATCH($A13,'Building Pivot'!$A$11:$A$23,0),MATCH(J$3,'Building Pivot'!$B$9:$BJ$9,0)) -> 1393.6675 | K13: =+INDEX('Building Pivot'!$B$11:$BJ$23,MATCH($A13,'Building Pivot'!$A$11:$A$23,0),MATCH(K$3,'Building Pivot'!$B$9:$BJ$9,0)) -> 1110 | L13: =+INDEX('Building Pivot'!$B$11:$BJ$23,MATCH($A13,'Building Pivot'!$A$11:$A$23,0),MATCH(L$3,'Building Pivot'!$B$9:$BJ$9,0)) -> 1115 | ... P13: =+INDEX('Building Pivot'!$B$11:$BJ$23,MATCH($A13,'Building Pivot'!$A$11:$A$23,0),MATCH(P$3,'Building Pivot'!$B$9:$BJ$9,0)) -> 1314.5
A14: Conveying Systems | B14: =+INDEX('Building Pivot'!$B$11:$BJ$23,MATCH($A14,'Building Pivot'!$A$11:$A$23,0),MATCH(B$3,'Building Pivot'!$B$9:$BJ$9,0)) -> 0 | C14: =+INDEX('Building Pivot'!$B$11:$BJ$23,MATCH($A14,'Building Pivot'!$A$11:$A$23,0),MATCH(C$3,'Building Pivot'!$B$9:$BJ$9,0)) -> 0 | D14: =+INDEX('Building Pivot'!$B$11:$BJ$23,MATCH(A14,'Building Pivot'!$A$11:$A$23,0),MATCH(D$3,'Building Pivot'!$B$9:$BJ$9,0)) -> 0 | E14: =+INDEX('Building Pivot'!$B$11:$BJ$23,MATCH($A14,'Building Pivot'!$A$11:$A$23,0),MATCH(E$3,'Building Pivot'!$B$9:$BJ$9,0)) -> 53 | F14: =+INDEX('Building Pivot'!$B$11:$BJ$23,MATCH($A14,'Building Pivot'!$A$11:$A$23,0),MATCH(F$3,'Building Pivot'!$B$9:$BJ$9,0)) -> 153 | G14: =+INDEX('Building Pivot'!$B$11:$BJ$23,MATCH($A14,'Building Pivot'!$A$11:$A$23,0),MATCH(G$3,'Building Pivot'!$B$9:$BJ$9,0)) -> 277 | H14: =+INDEX('Building Pivot'!$B$11:$BJ$23,MATCH($A14,'Building Pivot'!$A$11:$A$23,0),MATCH(H$3,'Building Pivot'!$B$9:$BJ$9,0)) -> 69.435878 | I14: =+INDEX('Building Pivot'!$B$11:$BJ$23,MATCH($A14,'Building Pivot'!$A$11:$A$23,0),MATCH(I$3,'Building Pivot'!$B$9:$BJ$9,0)) -> 167.65341 | J14: =+INDEX('Building Pivot'!$B$11:$BJ$23,MATCH($A14,'Building Pivot'!$A$11:$A$23,0),MATCH(J$3,'Building Pivot'!$B$9:$BJ$9,0)) -> 181.33555 | K14: =+INDEX('Building Pivot'!$B$11:$BJ$23,MATCH($A14,'Building Pivot'!$A$11:$A$23,0),MATCH(K$3,'Building Pivot'!$B$9:$BJ$9,0)) -> 0 | L14: =+INDEX('Building Pivot'!$B$11:$BJ$23,MATCH($A14,'Building Pivot'!$A$11:$A$23,0),MATCH(L$3,'Building Pivot'!$B$9:$BJ$9,0)) -> 0 | ... P14: =+INDEX('Building Pivot'!$B$11:$BJ$23,MATCH($A14,'Building Pivot'!$A$11:$A$23,0),MATCH(P$3,'Building Pivot'!$B$9:$BJ$9,0)) -> 198.5
A15: External Works | B15: =+INDEX('Building Pivot'!$B$11:$BJ$23,MATCH($A15,'Building Pivot'!$A$11:$A$23,0),MATCH(B$3,'Building Pivot'!$B$9:$BJ$9,0)) -> 213.25 | C15: =+INDEX('Building Pivot'!$B$11:$BJ$23,MATCH($A15,'Building Pivot'!$A$11:$A$23,0),MATCH(C$3,'Building Pivot'!$B$9:$BJ$9,0)) -> 286.66667 | D15: =+INDEX('Building Pivot'!$B$11:$BJ$23,MATCH(A15,'Building Pivot'!$A$11:$A$23,0),MATCH(D$3,'Building Pivot'!$B$9:$BJ$9,0)) -> 197 | E15: =+INDEX('Building Pivot'!$B$11:$BJ$23,MATCH($A15,'Building Pivot'!$A$11:$A$23,0),MATCH(E$3,'Building Pivot'!$B$9:$BJ$9,0)) -> 558 | F15: =+INDEX('Building Pivot'!$B$11:$BJ$23,MATCH($A15,'Building Pivot'!$A$11:$A$23,0),MATCH(F$3,'Building Pivot'!$B$9:$BJ$9,0)) -> 546 | G15: =+INDEX('Building Pivot'!$B$11:$BJ$23,MATCH($A15,'Building Pivot'!$A$11:$A$23,0),MATCH(G$3,'Building Pivot'!$B$9:$BJ$9,0)) -> 456.5 | H15: =+INDEX('Building Pivot'!$B$11:$BJ$23,MATCH($A15,'Building Pivot'!$A$11:$A$23,0),MATCH(H$3,'Building Pivot'!$B$9:$BJ$9,0)) -> 568.5965 | I15: =+INDEX('Building Pivot'!$B$11:$BJ$23,MATCH($A15,'Building Pivot'!$A$11:$A$23,0),MATCH(I$3,'Building Pivot'!$B$9:$BJ$9,0)) -> 475.99118 | J15: =+INDEX('Building Pivot'!$B$11:$BJ$23,MATCH($A15,'Building Pivot'!$A$11:$A$23,0),MATCH(J$3,'Building Pivot'!$B$9:$BJ$9,0)) -> 680.64575 | K15: =+INDEX('Building Pivot'!$B$11:$BJ$23,MATCH($A15,'Building Pivot'!$A$11:$A$23,0),MATCH(K$3,'Building Pivot'!$B$9:$BJ$9,0)) -> 243 | L15: =+INDEX('Building Pivot'!$B$11:$BJ$23,MATCH($A15,'Building Pivot'!$A$11:$A$23,0),MATCH(L$3,'Building Pivot'!$B$9:$BJ$9,0)) -> 366 | ... P15: =+INDEX('Building Pivot'!$B$11:$BJ$23,MATCH($A15,'Building Pivot'!$A$11:$A$23,0),MATCH(P$3,'Building Pivot'!$B$9:$BJ$9,0)) -> 396
A16: General Requirements | B16: =+INDEX('Building Pivot'!$B$11:$BJ$23,MATCH($A16,'Building Pivot'!$A$11:$A$23,0),MATCH(B$3,'Building Pivot'!$B$9:$BJ$9,0)) -> 0 | C16: =+INDEX('Building Pivot'!$B$11:$BJ$23,MATCH($A16,'Building Pivot'!$A$11:$A$23,0),MATCH(C$3,'Building Pivot'!$B$9:$BJ$9,0)) -> 0 | D16: =+INDEX('Building Pivot'!$B$11:$BJ$23,MATCH(A16,'Building Pivot'!$A$11:$A$23,0),MATCH(D$3,'Building Pivot'!$B$9:$BJ$9,0)) -> 0 | E16: =+INDEX('Building Pivot'!$B$11:$BJ$23,MATCH($A16,'Building Pivot'!$A$11:$A$23,0),MATCH(E$3,'Building Pivot'!$B$9:$BJ$9,0)) -> 0 | F16: =+INDEX('Building Pivot'!$B$11:$BJ$23,MATCH($A16,'Building Pivot'!$A$11:$A$23,0),MATCH(F$3,'Building Pivot'!$B$9:$BJ$9,0)) -> 0 | G16: =+INDEX('Building Pivot'!$B$11:$BJ$23,MATCH($A16,'Building Pivot'!$A$11:$A$23,0),MATCH(G$3,'Building Pivot'!$B$9:$BJ$9,0)) -> 0 | H16: =+INDEX('Building Pivot'!$B$11:$BJ$23,MATCH($A16,'Building Pivot'!$A$11:$A$23,0),MATCH(H$3,'Building Pivot'!$B$9:$BJ$9,0)) -> 0 | I16: =+INDEX('Building Pivot'!$B$11:$BJ$23,MATCH($A16,'Building Pivot'!$A$11:$A$23,0),MATCH(I$3,'Building Pivot'!$B$9:$BJ$9,0)) -> 0 | J16: =+INDEX('Building Pivot'!$B$11:$BJ$23,MATCH($A16,'Building Pivot'!$A$11:$A$23,0),MATCH(J$3,'Building Pivot'!$B$9:$BJ$9,0)) -> 0 | K16: =+INDEX('Building Pivot'!$B$11:$BJ$23,MATCH($A16,'Building Pivot'!$A$11:$A$23,0),MATCH(K$3,'Building Pivot'!$B$9:$BJ$9,0)) -> 0 | L16: =+INDEX('Building Pivot'!$B$11:$BJ$23,MATCH($A16,'Building Pivot'!$A$11:$A$23,0),MATCH(L$3,'Building Pivot'!$B$9:$BJ$9,0)) -> 0 | ... P16: =+INDEX('Building Pivot'!$B$11:$BJ$23,MATCH($A16,'Building Pivot'!$A$11:$A$23,0),MATCH(P$3,'Building Pivot'!$B$9:$BJ$9,0)) -> 0
A17: Total | B17: =+SUM(B4:B16) -> 3670.275 | C17: =+SUM(C4:C16) -> 3416.1667 | D17: =+SUM(D4:D16) -> 3446.5 | E17: =+SUM(E4:E16) -> 7625 | F17: =+SUM(F4:F16) -> 6969.8667 | G17: =+SUM(G4:G16) -> 6161.5 | H17: =+SUM(H4:H16) -> 5954.6233 | I17: =+SUM(I4:I16) -> 5668.1185 | ... P17: =+SUM(P4:P16) -> 6540.4

Sheet Exec Summ Infra
AA3: Average | AB3: Max
B4: Desnsity | C4: Low to Use | D4: Mid to Use | E4: High to Use | F4: =+'[3]ROM Temp'!H$1 -> Low | G4: =+'[3]ROM Temp'!I$1 -> Low | H4: =+'[3]ROM Temp'!J$1 -> Low | I4: =+'[3]ROM Temp'!K$1 -> Low | J4: =+'[3]ROM Temp'!L$1 -> Low | K4: =+'[3]ROM Temp'!M$1 -> Low | L4: =+'[3]ROM Temp'!N$1 -> Low | M4: =+'[3]ROM Temp'!O$1 -> Low | ... W4: =+'[3]ROM Temp'!Y$1 -> Low | X4: =+'[3]ROM Temp'!AA$1 -> Low | Y4: =+'[3]ROM Temp'!AB$1 -> Low | Z4: =+'[3]ROM Temp'!AE$1 -> Low | AC4: =+'[3]ROM Temp'!AD$1 -> Mid | AD4: =+'[3]ROM Temp'!Z$1 -> Mid | AE4: =+'[3]ROM Temp'!AF$1 -> Mid | AH4: =+'[3]ROM Temp'!AC$1 -> High
B5: FAR | F5: =+'[3]ROM Temp'!H$2 -> 0.68168455 | G5: =+'[3]ROM Temp'!I$2 -> 0.65438664 | H5: =+'[3]ROM Temp'!J$2 -> 0.68351082 | I5: =+'[3]ROM Temp'!K$2 -> 0.60029375 | J5: =+'[3]ROM Temp'!L$2 -> 0.6 | K5: =+'[3]ROM Temp'!M$2 -> 0.6 | L5: =+'[3]ROM Temp'!N$2 -> 0.6 | M5: =+'[3]ROM Temp'!O$2 -> 0.65496894 | ... W5: =+'[3]ROM Temp'!Y$2 -> 0.4670758 | X5: =+'[3]ROM Temp'!AA$2 -> 0.584307 | Y5: =+'[3]ROM Temp'!AB$2 -> 0.25114043 | Z5: =+'[3]ROM Temp'!AE$2 -> 0.6 | AA5: =AVERAGEIF(F5:Z5,"<>0") -> 0.52061739 | AB5: =+MAX(F5:Z5) -> 0.68351082 | AC5: =+'[3]ROM Temp'!AD$2 -> 1.1 | AD5: =+'[3]ROM Temp'!Z$2 -> 1.0549914 | AE5: =+'[3]ROM Temp'!AF$2 -> 0.8 | AH5: =+'[3]ROM Temp'!AC$2 -> 2.9946292
B6: Projects | F6: =+'[3]ROM Temp'!H$3 -> Sidra 2 | G6: =+'[3]ROM Temp'!I$3 -> Sidra 3 | H6: =+'[3]ROM Temp'!J$3 -> Sidra 4 | I6: =+'[3]ROM Temp'!K$3 -> Sidra 5 | J6: =+'[3]ROM Temp'!L$3 -> Makkah Phase 01 | K6: =+'[3]ROM Temp'!M$3 -> Al Arous 1A & 1B | L6: =+'[3]ROM Temp'!N$3 -> Riyadh East | M6: =+'[3]ROM Temp'!O$3 -> Roshan Rate | ... W6: =+'[3]ROM Temp'!Y$3 -> PJA Fronds I to P | X6: =+'[3]ROM Temp'!AA$3 -> PJA Spine District | Y6: =+'[3]ROM Temp'!AB$3 -> Chevron Business Administration and Residential Community | Z6: =+'[3]ROM Temp'!AE$3 -> Al-Thuraya Infrastructure - Roads & Utilities TP4 | AC6: =+'[3]ROM Temp'!AD$3 -> RENAISSANCE | AD6: =+'[3]ROM Temp'!Z$3 -> Ghaf Woods | AE6: =+'[3]ROM Temp'!AF$3 -> Al-Thuraya Infrastructure - Roads & Utilities TP4 | AH6: =+'[3]ROM Temp'!AC$3 -> RUA Madinah Infrastructure (Both early works and main infra)
B7: Location | F7: KSA,Riyadh | G7: KSA,Riyadh | H7: KSA,Riyadh | I7: KSA,Riyadh | J7: KSA,Makkah | K7: KSA,Jeddah | L7: KSA,Riyadh | M7: KSA,Riyadh | N7: KSA,Riyadh | O7: KSA,Riyadh | P7: KSA,Riyadh | Q7: KSA,Riyadh | R7: KSA,Riyadh | S7: KSA,Riyadh | T7: KSA,Riyadh | U7: KSA,Riyadh | V7: KSA,Riyadh | W7: KSA,Riyadh | X7: KSA,Riyadh | Y7: KSA,Riyadh | Z7: KSA,Riyadh
B8: Average Gross FAR (RCDC Defined for Low, Mid and High)) | C8: =+(0.6+0.33)/2 -> 0.465 | D8: =+(1.5+0.6)/2 -> 1.05 | E8: =+(4+1.5)/2 -> 2.75
A9: S/No | B9: CESMM Summary | C9: Low to Use | D9: Mid to Use | E9: High to Use | F9: =+'[3]ROM Temp'!H$4 -> Project 01 | G9: =+'[3]ROM Temp'!I$4 -> Project 02 | H9: =+'[3]ROM Temp'!J$4 -> Project 03 | I9: =+'[3]ROM Temp'!K$4 -> Project 04 | J9: =+'[3]ROM Temp'!L$4 -> Project 05 | K9: =+'[3]ROM Temp'!M$4 -> Project 06 | L9: =+'[3]ROM Temp'!N$4 -> Project 07 | M9: =+'[3]ROM Temp'!O$4 -> Project 08 | ... W9: =+'[3]ROM Temp'!Y$4 -> Project 18 | X9: =+'[3]ROM Temp'!AA$4 -> Project 20 | Y9: =+'[3]ROM Temp'!AB$4 -> Project 21 | Z9: =+'[3]ROM Temp'!AE$4 -> Project 24 | AC9: =+'[3]ROM Temp'!AD$4 -> Project 23 | AD9: =+'[3]ROM Temp'!Z$4 -> Project 19 | AE9: =+'[3]ROM Temp'!AF$4 -> Project 25 | AH9: =+'[3]ROM Temp'!AC$4 -> Project 22
A11: 1 | B11: General Items | AA11: =+SUM(AA12:AA35)*0.1 -> 33.943256 | AB11: =+SUM(AB12:AB35)*0.1 -> 69.819 | AC11: =+ROUND('[3]ROM Temp'!AD6,2) -> 60.01 | AD11: =+ROUND('[3]ROM Temp'!Z6,2) -> 0 | AE11: =+ROUND('[3]ROM Temp'!AF6,2) -> 10.88 | AF11: =+SUM(AF12:AF35)*0.1 -> 46.510333 | AG11: =+SUM(AG12:AG35)*0.1 -> 59.453 | AH11: =+ROUND('[3]ROM Temp'!AC6,2) -> 0
A12: 2 | B12: Ground Investigation | C12: =+(AA12*2+AB12)/3*0+MAX(F12:Z12) -> 1.42 | D12: =+(AF12*2+AG12)/3 -> 2.0433333 | E12: =+AH12*0+MAX(F12:Z12,AC12:AE12) -> 3 | F12: =+ROUND('[3]ROM Temp'!H7,2) -> 0.43 | G12: =+ROUND('[3]ROM Temp'!I7,2) -> 0 | H12: =+ROUND('[3]ROM Temp'!J7,2) -> 0 | I12: =+ROUND('[3]ROM Temp'!K7,2) -> 0 | J12: =+ROUND('[3]ROM Temp'!L7,2) -> 0 | K12: =+ROUND('[3]ROM Temp'!M7,2) -> 1.42 | L12: =+ROUND('[3]ROM Temp'!N7,2) -> 0 | M12: =+ROUND('[3]ROM Temp'!O7,2) -> 1.06 | ... W12: =+ROUND('[3]ROM Temp'!Y7,2) -> 0 | X12: =+ROUND('[3]ROM Temp'!AA7,2) -> 0.06 | Y12: =+ROUND('[3]ROM Temp'!AB7,2) -> 0 | Z12: =+ROUND('[3]ROM Temp'!AE7,2) -> 0 | AA12: =AVERAGEIF(F12:Z12,"<>0") -> 0.7425 | AB12: =+MAX(F12:Z12) -> 1.42 | AC12: =+ROUND('[3]ROM Temp'!AD7,2) -> 3 | AD12: =+ROUND('[3]ROM Temp'!Z7,2) -> 0 | AE12: =+ROUND('[3]ROM Temp'!AF7,2) -> 0.13 | AF12: =AVERAGEIF(AC12:AE12,"<>0") -> 1.565 | AG12: =+MAX(AC12:AE12) -> 3 | AH12: =+ROUND('[3]ROM Temp'!AC7,2) -> 1.86
A13: =A12+1 -> 3 | B13: Demolition and Site Clearance | C13: =+(AA13*2+AB13)/3*0+D13 -> 4.6266667 | D13: =+(AF13*2+AG13)/3 -> 4.6266667 | E13: =+AH13 -> 4.84 | F13: =+ROUND('[3]ROM Temp'!H8,2) -> 0 | G13: =+ROUND('[3]ROM Temp'!I8,2) -> 2.51 | H13: =+ROUND('[3]ROM Temp'!J8,2) -> 2.59 | I13: =+ROUND('[3]ROM Temp'!K8,2) -> 2.6 | J13: =+ROUND('[3]ROM Temp'!L8,2) -> 3.36 | K13: =+ROUND('[3]ROM Temp'!M8,2) -> 4.15 | L13: =+ROUND('[3]ROM Temp'!N8,2) -> 0 | M13: =+ROUND('[3]ROM Temp'!O8,2) -> 3.86 | ... W13: =+ROUND('[3]ROM Temp'!Y8,2) -> 0.47 | X13: =+ROUND('[3]ROM Temp'!AA8,2) -> 0.8 | Y13: =+ROUND('[3]ROM Temp'!AB8,2) -> 8.29 | Z13: =+ROUND('[3]ROM Temp'!AE8,2) -> 3.3 | AA13: =AVERAGEIF(F13:Z13,"<>0") -> 6.7226667 | AB13: =+MAX(F13:Z13) -> 34.29 | AC13: =+ROUND('[3]ROM Temp'!AD8,2) -> 6 | AD13: =+ROUND('[3]ROM Temp'!Z8,2) -> 1.65 | AE13: =+ROUND('[3]ROM Temp'!AF8,2) -> 4.17 | AF13: =AVERAGEIF(AC13:AE13,"<>0") -> 3.94 | AG13: =+MAX(AC13:AE13) -> 6 | AH13: =+ROUND('[3]ROM Temp'!AC8,2) -> 4.84
A14: =A13+1 -> 4 | B14: Earthworks | C14: =+(AA14*2+AB14)/3*0+M14 -> 32.5 | D14: =+(AF14*2+AG14)/3*0+MAX(F14:Z14,AC14:AE14) -> 44.67 | E14: =+AH14 -> 44.67 | F14: =+ROUND('[3]ROM Temp'!H9,2) -> 4.69 | G14: =+ROUND('[3]ROM Temp'!I9,2) -> 29.62 | H14: =+ROUND('[3]ROM Temp'!J9,2) -> 28.53 | I14: =+ROUND('[3]ROM Temp'!K9,2) -> 44.67 | J14: =+ROUND('[3]ROM Temp'!L9,2) -> 14.45 | K14: =+ROUND('[3]ROM Temp'!M9,2) -> 15.98 | L14: =+ROUND('[3]ROM Temp'!N9,2) -> 18.12 | M14: =+ROUND('[3]ROM Temp'!O9,2) -> 32.5 | ... W14: =+ROUND('[3]ROM Temp'!Y9,2) -> 3.09 | X14: =+ROUND('[3]ROM Temp'!AA9,2) -> 17.62 | Y14: =+ROUND('[3]ROM Temp'!AB9,2) -> 38.59 | Z14: =+ROUND('[3]ROM Temp'!AE9,2) -> 13.2 | AA14: =AVERAGEIF(F14:Z14,"<>0") -> 18.715714 | AB14: =+MAX(F14:Z14) -> 44.67 | AC14: =+ROUND('[3]ROM Temp'!AD9,2) -> 35 | AD14: =+ROUND('[3]ROM Temp'!Z9,2) -> 14.31 | AE14: =+ROUND('[3]ROM Temp'!AF9,2) -> 13.43 | AF14: =AVERAGEIF(AC14:AE14,"<>0") -> 20.913333 | AG14: =+MAX(AC14:AE14) -> 35 | AH14: =+ROUND('[3]ROM Temp'!AC9,2) -> 44.67
A15: =A14+1 -> 5 | B15: Structural Metal Works | C15: =+(AA15*2+AB15)/3 -> 0.70444444 | D15: =+(AF15*2+AG15)/3*0+(C15+E15*2)/3 -> 0.91481481 | E15: =+AH15*0+MAX(F15:Z15,AC15:AE15) -> 1.02 | F15: =+ROUND('[3]ROM Temp'!H10,2) -> 0.02 | G15: =+ROUND('[3]ROM Temp'!I10,2) -> 0 | H15: =+ROUND('[3]ROM Temp'!J10,2) -> 0 | I15: =+ROUND('[3]ROM Temp'!K10,2) -> 0 | J15: =+ROUND('[3]ROM Temp'!L10,2) -> 0 | K15: =+ROUND('[3]ROM Temp'!M10,2) -> 1.02 | L15: =+ROUND('[3]ROM Temp'!N10,2) -> 0 | M15: =+ROUND('[3]ROM Temp'!O10,2) -> 0.6 | ... W15: =+ROUND('[3]ROM Temp'!Y10,2) -> 0 | X15: =+ROUND('[3]ROM Temp'!AA10,2) -> 0 | Y15: =+ROUND('[3]ROM Temp'!AB10,2) -> 0 | Z15: =+ROUND('[3]ROM Temp'!AE10,2) -> 0 | AA15: =AVERAGEIF(F15:Z15,"<>0") -> 0.54666667 | AB15: =+MAX(F15:Z15) -> 1.02 | AC15: =+ROUND('[3]ROM Temp'!AD10,2) -> 0 | AD15: =+ROUND('[3]ROM Temp'!Z10,2) -> 0 | AE15: =+ROUND('[3]ROM Temp'!AF10,2) -> 0 | AF15: 0 | AG15: =+MAX(AC15:AE15) -> 0 | AH15: =+ROUND('[3]ROM Temp'!AC10,2) -> 0
A16: 6 | B16: Roads and Paving's | C16: =+(AA16*2+AB16)/3 -> 48.119365 | D16: =+(AF16*2+AG16)/3*0+(C16+E16*2)/3 -> 57.566455 | E16: =+AH16*0+MAX(F16:Z16,AC16:AE16,AH16) -> 62.29 | F16: =+ROUND('[3]ROM Temp'!H11,2) -> 24.87 | G16: =+ROUND('[3]ROM Temp'!I11,2) -> 40.88 | H16: =+ROUND('[3]ROM Temp'!J11,2) -> 40.66 | I16: =+ROUND('[3]ROM Temp'!K11,2) -> 21.93 | J16: =+ROUND('[3]ROM Temp'!L11,2) -> 40.38 | K16: =+ROUND('[3]ROM Temp'!M11,2) -> 28.44 | L16: =+ROUND('[3]ROM Temp'!N11,2) -> 37.1 | M16: =+ROUND('[3]ROM Temp'!O11,2) -> 38.31 | ... W16: =+ROUND('[3]ROM Temp'!Y11,2) -> 18.76 | X16: =+ROUND('[3]ROM Temp'!AA11,2) -> 57.79 | Y16: =+ROUND('[3]ROM Temp'!AB11,2) -> 49.18 | Z16: =+ROUND('[3]ROM Temp'!AE11,2) -> 41.1 | AA16: =AVERAGEIF(F16:Z16,"<>0") -> 41.239048 | AB16: =+MAX(F16:Z16) -> 61.88 | AC16: =+ROUND('[3]ROM Temp'!AD11,2) -> 45 | AD16: =+ROUND('[3]ROM Temp'!Z11,2) -> 18.25 | AE16: =+ROUND('[3]ROM Temp'!AF11,2) -> 62.29 | AF16: =AVERAGEIF(AC16:AE16,"<>0") -> 41.846667 | AG16: =+MAX(AC16:AE16) -> 62.29 | AH16: =+ROUND('[3]ROM Temp'!AC11,2) -> 52.54
A17: =A16+1 -> 7 | B17: Potable Water Works | C17: =+(AA17*2+AB17)/3 -> 41.319048 | D17: =+(AF17*2+AG17)/3*0+(C17+E17*2)/3 -> 55.199683 | E17: =+AH17*0+MAX(F17:Z17,AC17:AE17,AH17) -> 62.14 | F17: =+ROUND('[3]ROM Temp'!H12,2) -> 20.09 | G17: =+ROUND('[3]ROM Temp'!I12,2) -> 23.18 | H17: =+ROUND('[3]ROM Temp'!J12,2) -> 28.13 | I17: =+ROUND('[3]ROM Temp'!K12,2) -> 18.63 | J17: =+ROUND('[3]ROM Temp'!L12,2) -> 18.22 | K17: =+ROUND('[3]ROM Temp'!M12,2) -> 16.62 | L17: =+ROUND('[3]ROM Temp'!N12,2) -> 35.22 | M17: =+ROUND('[3]ROM Temp'!O12,2) -> 26.23 | ... W17: =+ROUND('[3]ROM Temp'!Y12,2) -> 36.24 | X17: =+ROUND('[3]ROM Temp'!AA12,2) -> 33.58 | Y17: =+ROUND('[3]ROM Temp'!AB12,2) -> 15.28 | Z17: =+ROUND('[3]ROM Temp'!AE12,2) -> 28.6 | AA17: =AVERAGEIF(F17:Z17,"<>0") -> 30.908571 | AB17: =+MAX(F17:Z17) -> 62.14 | AC17: =+ROUND('[3]ROM Temp'!AD12,2) -> 25 | AD17: =+ROUND('[3]ROM Temp'!Z12,2) -> 14.46 | AE17: =+ROUND('[3]ROM Temp'!AF12,2) -> 57.72 | AF17: =AVERAGEIF(AC17:AE17,"<>0") -> 32.393333 | AG17: =+MAX(AC17:AE17) -> 57.72 | AH17: =+ROUND('[3]ROM Temp'!AC12,2) -> 35.49
A18: =A17+1 -> 8 | B18: TSE & Irrigation Network | C18: =+(AA18*2+AB18)/3 -> 29.080635 | D18: =+(AF18*2+AG18)/3*0+(C18+E18*2)/3 -> 33.473545 | E18: =+AH18 -> 35.67 | F18: =+ROUND('[3]ROM Temp'!H13,2) -> 6.05 | G18: =+ROUND('[3]ROM Temp'!I13,2) -> 9.26 | H18: =+ROUND('[3]ROM Temp'!J13,2) -> 10.98 | I18: =+ROUND('[3]ROM Temp'!K13,2) -> 7.45 | J18: =+ROUND('[3]ROM Temp'!L13,2) -> 8.03 | K18: =+ROUND('[3]ROM Temp'!M13,2) -> 3.61 | L18: =+ROUND('[3]ROM Temp'!N13,2) -> 9.36 | M18: =+ROUND('[3]ROM Temp'!O13,2) -> 8.39 | ... W18: =+ROUND('[3]ROM Temp'!Y13,2) -> 24.63 | X18: =+ROUND('[3]ROM Temp'!AA13,2) -> 7.57 | Y18: =+ROUND('[3]ROM Temp'!AB13,2) -> 7.81 | Z18: =+ROUND('[3]ROM Temp'!AE13,2) -> 13.2 | AA18: =AVERAGEIF(F18:Z18,"<>0") -> 18.380952 | AB18: =+MAX(F18:Z18) -> 50.48 | AC18: =+ROUND('[3]ROM Temp'!AD13,2) -> 11 | AD18: =+ROUND('[3]ROM Temp'!Z13,2) -> 6.36 | AE18: =+ROUND('[3]ROM Temp'!AF13,2) -> 18.29 | AF18: =AVERAGEIF(AC18:AE18,"<>0") -> 11.883333 | AG18: =+MAX(AC18:AE18) -> 18.29 | AH18: =+ROUND('[3]ROM Temp'!AC13,2) -> 35.67
A19: =A18+1 -> 9 | B19: Sewerage Network | C19: =+(AA19*2+AB19)/3 -> 40.862381 | D19: =AVERAGE(E19,C19) -> 49.35619 | E19: =MAX(F19:AE19) -> 57.85 | F19: =+ROUND('[3]ROM Temp'!H14,2) -> 19.59 | G19: =+ROUND('[3]ROM Temp'!I14,2) -> 22.04 | H19: =+ROUND('[3]ROM Temp'!J14,2) -> 23.7 | I19: =+ROUND('[3]ROM Temp'!K14,2) -> 18.17 | J19: =+ROUND('[3]ROM Temp'!L14,2) -> 18.61 | K19: =+ROUND('[3]ROM Temp'!M14,2) -> 41.55 | L19: =+ROUND('[3]ROM Temp'!N14,2) -> 43.04 | M19: =+ROUND('[3]ROM Temp'!O14,2) -> 33.22 | ... W19: =+ROUND('[3]ROM Temp'!Y14,2) -> 52.46 | X19: =+ROUND('[3]ROM Temp'!AA14,2) -> 44.6 | Y19: =+ROUND('[3]ROM Temp'!AB14,2) -> 7.05 | Z19: =+ROUND('[3]ROM Temp'!AE14,2) -> 17.6 | AA19: =AVERAGEIF(F19:Z19,"<>0") -> 32.368571 | AB19: =+MAX(F19:Z19) -> 57.85 | AC19: =+ROUND('[3]ROM Temp'!AD14,2) -> 22 | AD19: =+ROUND('[3]ROM Temp'!Z14,2) -> 28.35 | AE19: =+ROUND('[3]ROM Temp'!AF14,2) -> 55.32 | AF19: =AVERAGEIF(AC19:AE19,"<>0") -> 35.223333 | AG19: =+MAX(AC19:AE19) -> 55.32 | AH19: =+ROUND('[3]ROM Temp'!AC14,2) -> 63.63
A20: =A19+1 -> 10 | B20: Sewer Treatment Plant/Pumping Station (100% primary) | C20: =+(AA20*2+AB20)/3 -> 15.753333 | D20: =AVERAGE(E20,C20) -> 54.459104 | E20: =+AH20*0+C20*(E8/C8) -> 93.164875 | F20: =+ROUND('[3]ROM Temp'!H15,2) -> 0 | G20: =+ROUND('[3]ROM Temp'!I15,2) -> 0 | H20: =+ROUND('[3]ROM Temp'!J15,2) -> 0 | I20: =+ROUND('[3]ROM Temp'!K15,2) -> 0 | J20: =+ROUND('[3]ROM Temp'!L15,2) -> 21.58 | K20: =+ROUND('[3]ROM Temp'!M15,2) -> 0 | L20: =+ROUND('[3]ROM Temp'!N15,2) -> 0 | M20: =+ROUND('[3]ROM Temp'!O15,2) -> 0 | ... W20: =+ROUND('[3]ROM Temp'!Y15,2) -> 0 | X20: =+ROUND('[3]ROM Temp'!AA15,2) -> 0 | Y20: =+ROUND('[3]ROM Temp'!AB15,2) -> 0 | Z20: =+ROUND('[3]ROM Temp'!AE15,2) -> 7.2 | AA20: =AVERAGEIF(F20:Z20,"<>0") -> 12.84 | AB20: =+MAX(F20:Z20) -> 21.58 | AC20: =+ROUND('[3]ROM Temp'!AD15,2) -> 10.21 | AD20: =+ROUND('[3]ROM Temp'!Z15,2) -> 0 | AE20: =+ROUND('[3]ROM Temp'!AF15,2) -> 0 | AF20: =AVERAGEIF(AC20:AE20,"<>0") -> 10.21 | AG20: =+MAX(AC20:AE20) -> 10.21 | AH20: =+ROUND('[3]ROM Temp'!AC15,2) -> 0
A21: =A20+1 -> 11 | B21: Sewerage Lifting Station (100% primary) | C21: =+(AA21*2+AB21)/3 -> 9.5133333 | D21: =AVERAGE(E21,C21) -> 10.751667 | E21: =MAX(G21:AH21) -> 11.99 | F21: =+ROUND('[3]ROM Temp'!H16,2) -> 0 | G21: =+ROUND('[3]ROM Temp'!I16,2) -> 0 | H21: =+ROUND('[3]ROM Temp'!J16,2) -> 0 | I21: =+ROUND('[3]ROM Temp'!K16,2) -> 0 | J21: =+ROUND('[3]ROM Temp'!L16,2) -> 0 | K21: =+ROUND('[3]ROM Temp'!M16,2) -> 0 | L21: =+ROUND('[3]ROM Temp'!N16,2) -> 4.56 | M21: =+ROUND('[3]ROM Temp'!O16,2) -> 0 | ... W21: =+ROUND('[3]ROM Temp'!Y16,2) -> 0 | X21: =+ROUND('[3]ROM Temp'!AA16,2) -> 0 | Y21: =+ROUND('[3]ROM Temp'!AB16,2) -> 11.99 | Z21: =+ROUND('[3]ROM Temp'!AE16,2) -> 0 | AA21: =AVERAGEIF(F21:Z21,"<>0") -> 8.275 | AB21: =+MAX(F21:Z21) -> 11.99 | AC21: =+ROUND('[3]ROM Temp'!AD16,2) -> 1.56 | AD21: =+ROUND('[3]ROM Temp'!Z16,2) -> 0 | AE21: =+ROUND('[3]ROM Temp'!AF16,2) -> 0 | AF21: =AVERAGEIF(AC21:AE21,"<>0") -> 1.56 | AG21: =+MAX(AC21:AE21) -> 1.56 | AH21: =+ROUND('[3]ROM Temp'!AC16,2) -> 0
A22: =A21+1 -> 12 | B22: Drainage Network | C22: =+(AA22*2+AB22)/3 -> 34.748 | D22: =+(AF22*2+AG22)/3 -> 36.933333 | E22: =+AH22 -> 71.96 | F22: =+ROUND('[3]ROM Temp'!H17,2) -> 12.5 | G22: =+ROUND('[3]ROM Temp'!I17,2) -> 14.09 | H22: =+ROUND('[3]ROM Temp'!J17,2) -> 18.49 | I22: =+ROUND('[3]ROM Temp'!K17,2) -> 11.65 | J22: =+ROUND('[3]ROM Temp'!L17,2) -> 42.08 | K22: =+ROUND('[3]ROM Temp'!M17,2) -> 41.86 | L22: =+ROUND('[3]ROM Temp'!N17,2) -> 33.06 | M22: =+ROUND('[3]ROM Temp'!O17,2) -> 33.27 | ... W22: =+ROUND('[3]ROM Temp'!Y17,2) -> 0 | X22: =+ROUND('[3]ROM Temp'!AA17,2) -> 0 | Y22: =+ROUND('[3]ROM Temp'!AB17,2) -> 47.42 | Z22: =+ROUND('[3]ROM Temp'!AE17,2) -> 29.7 | AA22: =AVERAGEIF(F22:Z22,"<>0") -> 28.412 | AB22: =+MAX(F22:Z22) -> 47.42 | AC22: =+ROUND('[3]ROM Temp'!AD17,2) -> 35 | AD22: =+ROUND('[3]ROM Temp'!Z17,2) -> 0 | AE22: =+ROUND('[3]ROM Temp'!AF17,2) -> 37.9 | AF22: =AVERAGEIF(AC22:AE22,"<>0") -> 36.45 | AG22: =+MAX(AC22:AE22) -> 37.9 | AH22: =+ROUND('[3]ROM Temp'!AC17,2) -> 71.96
A23: =A22+1 -> 13 | B23: Potable Water tank & Pumping Station/tank (100% primary) | C23: =D23 -> 6.11 | D23: =+(AF23*2+AG23)/3 -> 6.11 | E23: =+AH23*0+D23*(E8/D8) -> 16.002381 | F23: =+ROUND('[3]ROM Temp'!H18,2) -> 0 | G23: =+ROUND('[3]ROM Temp'!I18,2) -> 0 | H23: =+ROUND('[3]ROM Temp'!J18,2) -> 0 | I23: =+ROUND('[3]ROM Temp'!K18,2) -> 0 | J23: =+ROUND('[3]ROM Temp'!L18,2) -> 0 | K23: =+ROUND('[3]ROM Temp'!M18,2) -> 0 | L23: =+ROUND('[3]ROM Temp'!N18,2) -> 0 | M23: =+ROUND('[3]ROM Temp'!O18,2) -> 0 | ... W23: =+ROUND('[3]ROM Temp'!Y18,2) -> 0 | X23: =+ROUND('[3]ROM Temp'!AA18,2) -> 0 | Y23: =+ROUND('[3]ROM Temp'!AB18,2) -> 0 | Z23: =+ROUND('[3]ROM Temp'!AE18,2) -> 0 | AA23: 0 | AB23: =+MAX(F23:Z23) -> 0 | AC23: =+ROUND('[3]ROM Temp'!AD18,2) -> 6.11 | AD23: =+ROUND('[3]ROM Temp'!Z18,2) -> 0 | AE23: =+ROUND('[3]ROM Temp'!AF18,2) -> 0 | AF23: =AVERAGEIF(AC23:AE23,"<>0") -> 6.11 | AG23: =+MAX(AC23:AE23) -> 6.11 | AH23: =+ROUND('[3]ROM Temp'!AC18,2) -> 0
A24: =A23+1 -> 14 | B24: Irrigation Pumping Station/Water tank (100% primary) | C24: =AC24 -> 6.52 | D24: =AVERAGE(C24,E24) -> 7.22 | E24: =AB24 -> 7.92 | F24: =+ROUND('[3]ROM Temp'!H19,2) -> 0 | G24: =+ROUND('[3]ROM Temp'!I19,2) -> 0 | H24: =+ROUND('[3]ROM Temp'!J19,2) -> 0 | I24: =+ROUND('[3]ROM Temp'!K19,2) -> 0 | J24: =+ROUND('[3]ROM Temp'!L19,2) -> 0 | K24: =+ROUND('[3]ROM Temp'!M19,2) -> 0 | L24: =+ROUND('[3]ROM Temp'!N19,2) -> 0 | M24: =+ROUND('[3]ROM Temp'!O19,2) -> 0 | ... W24: =+ROUND('[3]ROM Temp'!Y19,2) -> 0 | X24: =+ROUND('[3]ROM Temp'!AA19,2) -> 0 | Y24: =+ROUND('[3]ROM Temp'!AB19,2) -> 0 | Z24: =+ROUND('[3]ROM Temp'!AE19,2) -> 7.92 | AA24: =AVERAGEIF(F24:Z24,"<>0") -> 7.92 | AB24: =+MAX(F24:Z24) -> 7.92 | AC24: =+ROUND('[3]ROM Temp'!AD19,2) -> 6.52 | AD24: =+ROUND('[3]ROM Temp'!Z19,2) -> 0 | AE24: =+ROUND('[3]ROM Temp'!AF19,2) -> 0 | AF24: =AVERAGEIF(AC24:AE24,"<>0") -> 6.52 | AG24: =+MAX(AC24:AE24) -> 6.52 | AH24: =+ROUND('[3]ROM Temp'!AC19,2) -> 0
A25: =A24+1 -> 15 | B25: Storm Water Pumping Station (100% primary) | C25: =+(AA25*2+AB25)/3*0+D25*(C8/D8) -> 4.4285714 | D25: =+(AF25*2+AG25)/3 -> 10 | E25: =+AH25*0+D25*(E8/D8) -> 26.190476 | F25: =+ROUND('[3]ROM Temp'!H20,2) -> 0 | G25: =+ROUND('[3]ROM Temp'!I20,2) -> 0 | H25: =+ROUND('[3]ROM Temp'!J20,2) -> 0 | I25: =+ROUND('[3]ROM Temp'!K20,2) -> 0 | J25: =+ROUND('[3]ROM Temp'!L20,2) -> 0 | K25: =+ROUND('[3]ROM Temp'!M20,2) -> 0 | L25: =+ROUND('[3]ROM Temp'!N20,2) -> 0 | M25: =+ROUND('[3]ROM Temp'!O20,2) -> 0 | ... W25: =+ROUND('[3]ROM Temp'!Y20,2) -> 0 | X25: =+ROUND('[3]ROM Temp'!AA20,2) -> 0 | Y25: =+ROUND('[3]ROM Temp'!AB20,2) -> 0 | Z25: =+ROUND('[3]ROM Temp'!AE20,2) -> 0 | AA25: 0 | AB25: =+MAX(F25:Z25) -> 0 | AC25: =+ROUND('[3]ROM Temp'!AD20,2) -> 10 | AD25: =+ROUND('[3]ROM Temp'!Z20,2) -> 0 | AE25: =+ROUND('[3]ROM Temp'!AF20,2) -> 0 | AF25: =AVERAGEIF(AC25:AE25,"<>0") -> 10 | AG25: =+MAX(AC25:AE25) -> 10 | AH25: =+ROUND('[3]ROM Temp'!AC20,2) -> 0
A26: =A25+1 -> 16 | B26: Electrical Works (HV, LV, MV) | C26: =+(AA26*2+AB26)/3*0+M26 -> 48 | D26: =+(AF26*2+AG26)/3*0+(C26+E26*2)/3 -> 82.073333 | E26: =+AH26*0+MAX(F26:Z26,AD26:AE26,AH26) -> 99.11 | F26: =+ROUND('[3]ROM Temp'!H21,2) -> 28.76 | G26: =+ROUND('[3]ROM Temp'!I21,2) -> 33.49 | H26: =+ROUND('[3]ROM Temp'!J21,2) -> 31.83 | I26: =+ROUND('[3]ROM Temp'!K21,2) -> 24.27 | J26: =+ROUND('[3]ROM Temp'!L21,2) -> 27.18 | K26: =+ROUND('[3]ROM Temp'!M21,2) -> 25.37 | L26: =+ROUND('[3]ROM Temp'!N21,2) -> 55 | M26: =+ROUND('[3]ROM Temp'!O21,2) -> 48 | ... W26: =+ROUND('[3]ROM Temp'!Y21,2) -> 14.02 | X26: =+ROUND('[3]ROM Temp'!AA21,2) -> 7.18 | Y26: =+ROUND('[3]ROM Temp'!AB21,2) -> 57 | Z26: =+ROUND('[3]ROM Temp'!AE21,2) -> 26.55 | AA26: =AVERAGEIF(F26:Z26,"<>0") -> 29.886667 | AB26: =+MAX(F26:Z26) -> 59 | AC26: =+ROUND('[3]ROM Temp'!AD21,2) -> 40 | AD26: =+ROUND('[3]ROM Temp'!Z21,2) -> 13.58 | AE26: =+ROUND('[3]ROM Temp'!AF21,2) -> 54.48 | AF26: =AVERAGEIF(AC26:AE26,"<>0") -> 36.02 | AG26: =+MAX(AC26:AE26) -> 54.48 | AH26: =+ROUND('[3]ROM Temp'!AC21,2) -> 99.11
A27: =A26+1 -> 17 | B27: Street Lighting Network | C27: =+(AA27*2+AB27)/3 -> 18.240667 | D27: =+(AF27*2+AG27)/3*0+(E27+C27)/2 -> 21.555333 | E27: =+AH27 -> 24.87 | F27: =+ROUND('[3]ROM Temp'!H22,2) -> 11.76 | G27: =+ROUND('[3]ROM Temp'!I22,2) -> 7.7 | H27: =+ROUND('[3]ROM Temp'!J22,2) -> 8.42 | I27: =+ROUND('[3]ROM Temp'!K22,2) -> 6.67 | J27: =+ROUND('[3]ROM Temp'!L22,2) -> 8.02 | K27: =+ROUND('[3]ROM Temp'!M22,2) -> 0 | L27: =+ROUND('[3]ROM Temp'!N22,2) -> 22.7 | M27: =+ROUND('[3]ROM Temp'!O22,2) -> 14.43 | ... W27: =+ROUND('[3]ROM Temp'!Y22,2) -> 10.39 | X27: =+ROUND('[3]ROM Temp'!AA22,2) -> 23.48 | Y27: =+ROUND('[3]ROM Temp'!AB22,2) -> 17.77 | Z27: =+ROUND('[3]ROM Temp'!AE22,2) -> 7.7 | AA27: =AVERAGEIF(F27:Z27,"<>0") -> 14.206 | AB27: =+MAX(F27:Z27) -> 26.31 | AC27: =+ROUND('[3]ROM Temp'!AD22,2) -> 14 | AD27: =+ROUND('[3]ROM Temp'!Z22,2) -> 3.51 | AE27: =+ROUND('[3]ROM Temp'!AF22,2) -> 21.9 | AF27: =AVERAGEIF(AC27:AE27,"<>0") -> 13.136667 | AG27: =+MAX(AC27:AE27) -> 21.9 | AH27: =+ROUND('[3]ROM Temp'!AC22,2) -> 24.87
A28: =A27+1 -> 18 | B28: Telecommunication Network (Including ICT and ITS) | C28: =+(AA28*2+AB28)/3 -> 21.433651 | D28: =+(AF28*2+AG28)/3*0+(E28*2+C28)/3 -> 29.58455 | E28: =+AH28 -> 33.66 | F28: =+ROUND('[3]ROM Temp'!H23,2) -> 8.92 | G28: =+ROUND('[3]ROM Temp'!I23,2) -> 8.37 | H28: =+ROUND('[3]ROM Temp'!J23,2) -> 13.04 | I28: =+ROUND('[3]ROM Temp'!K23,2) -> 6.76 | J28: =+ROUND('[3]ROM Temp'!L23,2) -> 20.25 | K28: =+ROUND('[3]ROM Temp'!M23,2) -> 24.91 | L28: =+ROUND('[3]ROM Temp'!N23,2) -> 20.85 | M28: =+ROUND('[3]ROM Temp'!O23,2) -> 19.47 | ... W28: =+ROUND('[3]ROM Temp'!Y23,2) -> 7.98 | X28: =+ROUND('[3]ROM Temp'!AA23,2) -> 7.24 | Y28: =+ROUND('[3]ROM Temp'!AB23,2) -> 33.84 | Z28: =+ROUND('[3]ROM Temp'!AE23,2) -> 8.8 | AA28: =AVERAGEIF(F28:Z28,"<>0") -> 15.230476 | AB28: =+MAX(F28:Z28) -> 33.84 | AC28: =+ROUND('[3]ROM Temp'!AD23,2) -> 26 | AD28: =+ROUND('[3]ROM Temp'!Z23,2) -> 3.21 | AE28: =+ROUND('[3]ROM Temp'!AF23,2) -> 21.9 | AF28: =AVERAGEIF(AC28:AE28,"<>0") -> 17.036667 | AG28: =+MAX(AC28:AE28) -> 26 | AH28: =+ROUND('[3]ROM Temp'!AC23,2) -> 33.66
A29: =A28+1 -> 19 | B29: CCTV System | C29: =+(AA29*2+AB29)/3*0+M29 -> 12.56 | D29: =+(AF29*2+AG29)/3 -> 14.58 | E29: =+AH29*0+D29*(E8/D8) -> 38.185714 | F29: =+ROUND('[3]ROM Temp'!H24,2) -> 13.96 | G29: =+ROUND('[3]ROM Temp'!I24,2) -> 12.28 | H29: =+ROUND('[3]ROM Temp'!J24,2) -> 10.72 | I29: =+ROUND('[3]ROM Temp'!K24,2) -> 6.72 | J29: =+ROUND('[3]ROM Temp'!L24,2) -> 0 | K29: =+ROUND('[3]ROM Temp'!M24,2) -> 0 | L29: =+ROUND('[3]ROM Temp'!N24,2) -> 8.59 | M29: =+ROUND('[3]ROM Temp'!O24,2) -> 12.56 | ... W29: =+ROUND('[3]ROM Temp'!Y24,2) -> 6.33 | X29: =+ROUND('[3]ROM Temp'!AA24,2) -> 14.95 | Y29: =+ROUND('[3]ROM Temp'!AB24,2) -> 5.75 | Z29: =+ROUND('[3]ROM Temp'!AE24,2) -> 0 | AA29: =AVERAGEIF(F29:Z29,"<>0") -> 9.3427273 | AB29: =+MAX(F29:Z29) -> 14.95 | AC29: =+ROUND('[3]ROM Temp'!AD24,2) -> 12 | AD29: =+ROUND('[3]ROM Temp'!Z24,2) -> 15.87 | AE29: =+ROUND('[3]ROM Temp'!AF24,2) -> 0 | AF29: =AVERAGEIF(AC29:AE29,"<>0") -> 13.935 | AG29: =+MAX(AC29:AE29) -> 15.87 | AH29: =+ROUND('[3]ROM Temp'!AC24,2) -> 0
A30: =A29+1 -> 20 | B30: Traffic signal | C30: =+(AA30*2+AB30)/3*0+D30*(C8/D8) -> 0.88571429 | D30: =+(AF30*2+AG30)/3 -> 2 | E30: =+AH30*0+D30*(E8/D8) -> 5.2380952 | F30: =+ROUND('[3]ROM Temp'!H25,2) -> 0 | G30: =+ROUND('[3]ROM Temp'!I25,2) -> 0 | H30: =+ROUND('[3]ROM Temp'!J25,2) -> 0 | I30: =+ROUND('[3]ROM Temp'!K25,2) -> 0 | J30: =+ROUND('[3]ROM Temp'!L25,2) -> 0 | K30: =+ROUND('[3]ROM Temp'!M25,2) -> 0 | L30: =+ROUND('[3]ROM Temp'!N25,2) -> 0 | M30: =+ROUND('[3]ROM Temp'!O25,2) -> 0 | ... W30: =+ROUND('[3]ROM Temp'!Y25,2) -> 0 | X30: =+ROUND('[3]ROM Temp'!AA25,2) -> 0 | Y30: =+ROUND('[3]ROM Temp'!AB25,2) -> 0 | Z30: =+ROUND('[3]ROM Temp'!AE25,2) -> 0 | AA30: 0 | AB30: =+MAX(F30:Z30) -> 0 | AC30: =+ROUND('[3]ROM Temp'!AD25,2) -> 2 | AD30: =+ROUND('[3]ROM Temp'!Z25,2) -> 0 | AE30: =+ROUND('[3]ROM Temp'!AF25,2) -> 0 | AF30: =AVERAGEIF(AC30:AE30,"<>0") -> 2 | AG30: =+MAX(AC30:AE30) -> 2 | AH30: =+ROUND('[3]ROM Temp'!AC25,2) -> 0
A31: =A30+1 -> 21 | B31: Soft Landscaping | C31: =+(AA31*2+AB31)/3*0+MAX(F31:Z31) -> 55 | D31: =+(AF31*2+AG31)/3*0+C31*1.1 -> 60.5 | E31: =+AH31*0+C31*1.2 -> 66 | F31: =+ROUND('[3]ROM Temp'!H26,2) -> 19.29 | G31: =+ROUND('[3]ROM Temp'!I26,2) -> 23.49 | H31: =+ROUND('[3]ROM Temp'!J26,2) -> 34.25 | I31: =+ROUND('[3]ROM Temp'!K26,2) -> 21.33 | J31: =+ROUND('[3]ROM Temp'!L26,2) -> 38.01 | K31: =+ROUND('[3]ROM Temp'!M26,2) -> 47.98 | L31: =+ROUND('[3]ROM Temp'!N26,2) -> 21.43 | M31: =+ROUND('[3]ROM Temp'!O26,2) -> 55 | ... W31: =+ROUND('[3]ROM Temp'!Y26,2) -> 0 | X31: =+ROUND('[3]ROM Temp'!AA26,2) -> 0 | Y31: =+ROUND('[3]ROM Temp'!AB26,2) -> 20.67 | Z31: =+ROUND('[3]ROM Temp'!AE26,2) -> 17.53 | AA31: =AVERAGEIF(F31:Z31,"<>0") -> 29.898 | AB31: =+MAX(F31:Z31) -> 55 | AC31: =+ROUND('[3]ROM Temp'!AD26,2) -> 35 | AD31: =+ROUND('[3]ROM Temp'!Z26,2) -> 0 | AE31: =+ROUND('[3]ROM Temp'!AF26,2) -> 0 | AF31: =AVERAGEIF(AC31:AE31,"<>0") -> 35 | AG31: =+MAX(AC31:AE31) -> 35 | AH31: =+ROUND('[3]ROM Temp'!AC26,2) -> 0
A32: =A31+1 -> 22 | B32: Hard Landscaping | C32: =+(AA32*2+AB32)/3*0+MAX(F32:Z32) -> 42.37 | D32: =+(AF32*2+AG32)/3*0+C32*1.1 -> 46.607 | E32: =+AH32*0+C32*1.2 -> 50.844 | F32: =+ROUND('[3]ROM Temp'!H27,2) -> 36.91 | G32: =+ROUND('[3]ROM Temp'!I27,2) -> 26.77 | H32: =+ROUND('[3]ROM Temp'!J27,2) -> 33.93 | I32: =+ROUND('[3]ROM Temp'!K27,2) -> 21.4 | J32: =+ROUND('[3]ROM Temp'!L27,2) -> 39.59 | K32: =+ROUND('[3]ROM Temp'!M27,2) -> 40.52 | L32: =+ROUND('[3]ROM Temp'!N27,2) -> 39.1 | M32: =+ROUND('[3]ROM Temp'!O27,2) -> 42.37 | ... W32: =+ROUND('[3]ROM Temp'!Y27,2) -> 0 | X32: =+ROUND('[3]ROM Temp'!AA27,2) -> 0 | Y32: =+ROUND('[3]ROM Temp'!AB27,2) -> 39.85 | Z32: =+ROUND('[3]ROM Temp'!AE27,2) -> 17.53 | AA32: =AVERAGEIF(F32:Z32,"<>0") -> 33.797 | AB32: =+MAX(F32:Z32) -> 42.37 | AC32: =+ROUND('[3]ROM Temp'!AD27,2) -> 39.68 | AD32: =+ROUND('[3]ROM Temp'!Z27,2) -> 0 | AE32: =+ROUND('[3]ROM Temp'!AF27,2) -> 0 | AF32: =AVERAGEIF(AC32:AE32,"<>0") -> 39.68 | AG32: =+MAX(AC32:AE32) -> 39.68 | AH32: =+ROUND('[3]ROM Temp'!AC27,2) -> 0
A33: =A32+1 -> 23 | B33: ITS Network (Included in Telecommunication Network) | C33: =+(AA33*2+AB33)/3 -> 0 | D33: =+(AF33*2+AG33)/3 -> 0 | E33: =+AH33 -> 0 | F33: =+ROUND('[3]ROM Temp'!H28,2) -> 0 | G33: =+ROUND('[3]ROM Temp'!I28,2) -> 0 | H33: =+ROUND('[3]ROM Temp'!J28,2) -> 0 | I33: =+ROUND('[3]ROM Temp'!K28,2) -> 0 | J33: =+ROUND('[3]ROM Temp'!L28,2) -> 0 | K33: =+ROUND('[3]ROM Temp'!M28,2) -> 0 | L33: =+ROUND('[3]ROM Temp'!N28,2) -> 0 | M33: =+ROUND('[3]ROM Temp'!O28,2) -> 0 | ... W33: =+ROUND('[3]ROM Temp'!Y28,2) -> 0 | X33: =+ROUND('[3]ROM Temp'!AA28,2) -> 0 | Y33: =+ROUND('[3]ROM Temp'!AB28,2) -> 0 | Z33: =+ROUND('[3]ROM Temp'!AE28,2) -> 0 | AA33: 0 | AB33: =+MAX(F33:Z33) -> 0 | AC33: =+ROUND('[3]ROM Temp'!AD28,2) -> 0 | AD33: =+ROUND('[3]ROM Temp'!Z28,2) -> 0 | AE33: =+ROUND('[3]ROM Temp'!AF28,2) -> 0 | AF33: 0 | AG33: =+MAX(AC33:AE33) -> 0 | AH33: =+ROUND('[3]ROM Temp'!AC28,2) -> 0
A34: =A33+1 -> 24 | B34: ICT Network (Telecommunication Network) | C34: =+(AA34*2+AB34)/3 -> 0 | D34: =+(AF34*2+AG34)/3 -> 0 | E34: =+AH34 -> 0 | F34: =+ROUND('[3]ROM Temp'!H29,2) -> 0 | G34: =+ROUND('[3]ROM Temp'!I29,2) -> 0 | H34: =+ROUND('[3]ROM Temp'!J29,2) -> 0 | I34: =+ROUND('[3]ROM Temp'!K29,2) -> 0 | J34: =+ROUND('[3]ROM Temp'!L29,2) -> 0 | K34: =+ROUND('[3]ROM Temp'!M29,2) -> 0 | L34: =+ROUND('[3]ROM Temp'!N29,2) -> 0 | M34: =+ROUND('[3]ROM Temp'!O29,2) -> 0 | ... W34: =+ROUND('[3]ROM Temp'!Y29,2) -> 0 | X34: =+ROUND('[3]ROM Temp'!AA29,2) -> 0 | Y34: =+ROUND('[3]ROM Temp'!AB29,2) -> 0 | Z34: =+ROUND('[3]ROM Temp'!AE29,2) -> 0 | AA34: 0 | AB34: =+MAX(F34:Z34) -> 0 | AC34: =+ROUND('[3]ROM Temp'!AD29,2) -> 0 | AD34: =+ROUND('[3]ROM Temp'!Z29,2) -> 0 | AE34: =+ROUND('[3]ROM Temp'!AF29,2) -> 0 | AF34: 0 | AG34: =+MAX(AC34:AE34) -> 0 | AH34: =+ROUND('[3]ROM Temp'!AC29,2) -> 0
A35: =A34+1 -> 25 | B35: Power Station/Bulk substation & Primary substation (100% primary) | C35: =M35 -> 64.06 | D35: =AF35 -> 89.68 | E35: =D35+(D35-C35) -> 115.3 | F35: =+ROUND('[3]ROM Temp'!H30,2) -> 0 | G35: =+ROUND('[3]ROM Temp'!I30,2) -> 0 | H35: =+ROUND('[3]ROM Temp'!J30,2) -> 0 | I35: =+ROUND('[3]ROM Temp'!K30,2) -> 0 | J35: =+ROUND('[3]ROM Temp'!L30,2) -> 0 | K35: =+ROUND('[3]ROM Temp'!M30,2) -> 0 | L35: =+ROUND('[3]ROM Temp'!N30,2) -> 0 | M35: =+ROUND('[3]ROM Temp'!O30,2) -> 64.06 | ... W35: =+ROUND('[3]ROM Temp'!Y30,2) -> 0 | X35: =+ROUND('[3]ROM Temp'!AA30,2) -> 0 | Y35: =+ROUND('[3]ROM Temp'!AB30,2) -> 0 | Z35: =+ROUND('[3]ROM Temp'!AE30,2) -> 0 | AA35: 0 | AB35: =+MAX(F35:Z35) -> 64.06 | AC35: =+ROUND('[3]ROM Temp'!AD30,2) -> 89.68 | AD35: =+ROUND('[3]ROM Temp'!Z30,2) -> 0 | AE35: =+ROUND('[3]ROM Temp'!AF30,2) -> 0 | AF35: =AVERAGEIF(AC35:AE35,"<>0") -> 89.68 | AG35: =+MAX(AC35:AE35) -> 89.68 | AH35: =+ROUND('[3]ROM Temp'!AC30,2) -> 0
B37: Infra Rate (SAR/Gross Land Area) | C37: =+SUM(C11:C35) -> 538.25581 | D37: =+SUM(D11:D35) -> 719.90501 | E37: =+SUM(E11:E35) -> 931.91554 | F37: =+SUM(F11:F35) -> 207.84 | G37: =+SUM(G11:G35) -> 253.68 | H37: =+SUM(H11:H35) -> 285.27 | I37: =+SUM(I11:I35) -> 212.25 | J37: =+SUM(J11:J35) -> 299.76 | ... AE37: =+SUM(AE11:AE35) -> 358.41 | AH37: =+SUM(AH11:AH35) -> 468.3
D39: =+D37/C37 -> 1.3374775 | E39: =+E37/D37 -> 1.2944979
E40: =+E37/C37 -> 1.7313618
B41: Gross FAR (RCDC) | C41: 0.33-0.60 | D41: 0.6-1.5 | E41: 1.5-4.0

Sheet Building Pivot
A6: Sum of Cost/GFA | B6: Column Labels
B7: Commercial | M7: Commercial Average | N7: Residential | AM7: Residential Average | AN7: Retail | BJ7: Retail Average
B8: Commercial | C8: Commercial | D8: Commercial | E8: Commercial | F8: Commercial | G8: Commercial | H8: Commercial | I8: Commercial | J8: Commercial | K8: Commercial | L8: Commercial Average | N8: Multi Family | O8: Multi Family | P8: Multi Family | Q8: Multi Family | R8: Multi Family | S8: Multi Family | T8: Multi Family | U8: Multi Family | V8: Multi Family | W8: Multi Family Average | X8: Single Family | Y8: Single Family | Z8: Single Family | AA8: Single Family | AB8: Single Family | AC8: Single Family | AD8: Single Family | AE8: Single Family | AF8: Single Family | AG8: Single Family | AH8: Single Family | AI8: Single Family | AJ8: Single Family | AK8: Single Family | AL8: Single Family Average | AN8: Lifestyle Retail | AO8: Lifestyle Retail | AP8: Lifestyle Retail | AQ8: Lifestyle Retail Average | AR8: Mixed Use Retail | AS8: Mixed Use Retail | AT8: Mixed Use Retail | AU8: Mixed Use Retail Average | AV8: Neighbourhood Centre | AW8: Neighbourhood Centre | AX8: Neighbourhood Centre Average | AY8: Outlet Mall | AZ8: Outlet Mall | BA8: Outlet Mall | BB8: Outlet Mall Average | BC8: Regional Mall | BD8: Regional Mall | BE8: Regional Mall | BF8: Regional Mall Average | BG8: District Centre (Community Mall) | BH8: District Centre (Community Mall) | BI8: District Centre (Community Mall) Average
B9: Com-Low-rise | C9: Com-Low-rise | D9: Com-Low-rise Average | E9: Com-Mid-rise | F9: Com-Mid-rise | G9: Com-Mid-rise | H9: Com-Mid-rise Average | I9: Com-High Rise | J9: Com-High Rise | K9: Com-High Rise Average | N9: High Rise | O9: High Rise | P9: High Rise Average | Q9: Low-rise | R9: Low-rise Average | S9: Mid-rise | T9: Mid-rise | U9: Mid-rise | V9: Mid-rise Average | X9: Duplex | Y9: Duplex | Z9: Duplex | AA9: Duplex | AB9: Duplex Average | AC9: Townhouse | AD9: Townhouse | AE9: Townhouse | AF9: Townhouse Average | AG9: Villa | AH9: Villa | AI9: Villa | AJ9: Villa | AK9: Villa Average | AN9: Lifestyle Retail | AO9: Lifestyle Retail | AP9: Lifestyle Retail Average | AR9: Mixed Use Retail | AS9: Mixed Use Retail | AT9: Mixed Use Retail Average | AV9: Neighbourhood Centre | AW9: Neighbourhood Centre Average | AY9: Outlet Mall | AZ9: Outlet Mall | BA9: Outlet Mall Average | BC9: Regional Mall | BD9: Regional Mall | BE9: Regional Mall Average | BG9: District Centre (Community Mall) | BH9: District Centre (Community Mall) Average
A10: Row Labels | B10: PROJECT 1 Low Rise | C10: PROJECT 2 Low Rise | E10: PROJECT 3 Mid Rise | F10: PROJECT 4A Mid Rise | G10: PROJECT 4B Mid Rise | I10: PROJECT 5 High Rise | J10: PROJECT 6 High Rise | N10: MF PROJECT 1 | O10: MF PROJECT 2 | Q10: MF PROJECT 6 | S10: MF PROJECT 3 | T10: MF PROJECT 4 | U10: MF PROJECT 5 | X10: SF PROJECT 5 | Y10: SF PROJECT 6 | Z10: SF PROJECT 7 | AA10: SF PROJECT 8 | AC10: SF PROJECT 10 | AD10: SF PROJECT 11 | AE10: SF PROJECT 9 | AG10: SF PROJECT 1 | AH10: SF PROJECT 2 | AI10: SF PROJECT 3 | AJ10: SF PROJECT 4 | AN10: R PROJECT 7 | AO10: R PROJECT 8 | AR10: R PROJECT 3 | AS10: R PROJECT 4 | AV10: R PROJECT 1 | AY10: R PROJECT 5 | AZ10: R PROJECT 6 | BC10: R PROJECT 10 | BD10: R PROJECT 9 | BG10: R PROJECT 2
A11: Building External Envelope | B11: 1156.329 | C11: 1126.4742 | D11: 1141.4016 | E11: 1141.4016 | F11: 393.55793 | G11: 1141.4016 | H11: 892.12039 | I11: 1014.5703 | J11: 995.62244 | K11: 1005.0964 | L11: 995.62244 | M11: 995.62244 | N11: 409 | O11: 415 | P11: 412 | Q11: 978 | R11: 978 | S11: 683.8 | T11: 954 | U11: 663 | V11: 766.93333 | W11: 683.8 | X11: 857 | Y11: 795 | Z11: 1055 | AA11: 880 | AB11: 896.75 | AC11: 785 | AD11: 631 | AE11: 850 | AF11: 755.33333 | AG11: 752 | AH11: 731 | AI11: 915 | AJ11: 825.1 | AK11: 805.775 | AL11: 825.1 | AM11: 775.22941 | AN11: 1230 | AO11: 976 | AP11: 1103 | AQ11: 1103 | AR11: 991 | AS11: 943.2 | AT11: 967.1 | AU11: 967.1 | AV11: 610 | AW11: 610 | AX11: 610 | AY11: 665 | AZ11: 1196 | BA11: 930.5 | BB11: 930.5 | BC11: 1002.8 | BD11: 947 | BE11: 974.9 | BF11: 974.9 | BG11: 1254 | BH11: 1254 | BI11: 1254 | BJ11: 981.5
A12: Conveying Systems | B12: 94.41744 | C12: 44.454315 | D12: 69.435878 | E12: 227.0209 | F12: 106.80776 | G12: 169.13155 | H12: 167.65341 | I12: 209.91109 | J12: 152.76 | K12: 181.33555 | L12: 143.50044 | M12: 143.50044 | N12: 278 | O12: 276 | P12: 277 | Q12: 53 | R12: 53 | S12: 102 | T12: 160 | U12: 197 | V12: 153 | W12: 177.66667 | X12: 0 | Y12: 0 | Z12: 0 | AA12: 0 | AB12: 0 | AC12: 0 | AD12: 0 | AE12: 0 | AF12: 0 | AG12: 0 | AH12: 0 | AI12: 0 | AJ12: 0 | AK12: 0 | AL12: 0 | AM12: 62.705882 | AN12: 111 | AO12: 0 | AP12: 55.5 | AQ12: 55.5 | AR12: 90 | AS12: 111 | AT12: 100.5 | AU12: 100.5 | AV12: 0 | AW12: 0 | AX12: 0 | AY12: 384 | AZ12: 0 | BA12: 192 | BB12: 192 | BC12: 232 | BD12: 165 | BE12: 198.5 | BF12: 198.5 | BG12: 0 | BH12: 0 | BI12: 0 | BJ12: 109.3
A13: Electrical | B13: 745.45503 | C13: 816.76494 | D13: 781.10999 | E13: 1181.8631 | F13: 714.46314 | G13: 870.11785 | H13: 922.14802 | I13: 1219.1509 | J13: 1568.184 | K13: 1393.6675 | L13: 1016.5713 | M13: 1016.5713 | N13: 1292 | O13: 1303 | P13: 1297.5 | Q13: 1212 | R13: 1212 | S13: 1377 | T13: 1040 | U13: 1376 | V13: 1264.3333 | W13: 1266.6667 | X13: 455 | Y13: 422 | Z13: 560 | AA13: 467 | AB13: 476 | AC13: 417 | AD13: 446.625 | AE13: 451 | AF13: 438.20833 | AG13: 400 | AH13: 388 | AI13: 400 | AJ13: 481 | AK13: 417.25 | AL13: 444.32955 | AM13: 734.56618 | AN13: 768 | AO13: 1091 | AP13: 929.5 | AQ13: 929.5 | AR13: 1231 | AS13: 1480 | AT13: 1355.5 | AU13: 1355.5 | AV13: 1110 | AW13: 1110 | AX13: 1110 | AY13: 753 | AZ13: 1125 | BA13: 939 | BB13: 939 | BC13: 1359 | BD13: 1270 | BE13: 1314.5 | BF13: 1314.5 | BG13: 1115 | BH13: 1115 | BI13: 1115 | BJ13: 1130.2
A14: External Works | B14: 499.47547 | C14: 637.71753 | D14: 568.5965 | E14: 588.42368 | F14: 403.01749 | G14: 436.53237 | H14: 475.99118 | I14: 418.18821 | J14: 943.10328 | K14: 680.64575 | L14: 560.92258 | M14: 560.92258 | N14: 444 | O14: 469 | P14: 456.5 | Q14: 558 | R14: 558 | S14: 563 | T14: 573 | U14: 502 | V14: 546 | W14: 518.16667 | X14: 217 | Y14: 221 | Z14: 191 | AA14: 159 | AB14: 197 | AC14: 218 | AD14: 406 | AE14: 236 | AF14: 286.66667 | AG14: 209 | AH14: 203 | AI14: 218 | AJ14: 223 | AK14: 213.25 | AL14: 227.36364 | AM14: 330 | AN14: 301 | AO14: 303 | AP14: 302 | AQ14: 302 | AR14: 307 | AS14: 375 | AT14: 341 | AU14: 341 | AV14: 243 | AW14: 243 | AX14: 243 | AY14: 344 | AZ14: 364 | BA14: 354 | BB14: 354 | BC14: 470 | BD14: 322 | BE14: 396 | BF14: 396 | BG14: 366 | BH14: 366 | BI14: 366 | BJ14: 339.5
A15: FF&E | B15: 32.948289 | C15: 53.839147 | D15: 43.393718 | E15: 98.128713 | F15: 82.957606 | G15: 129.85718 | H15: 103.64783 | I15: 110.68981 | J15: 170 | K15: 140.34491 | L15: 96.91725 | M15: 96.91725 | N15: 413 | O15: 394 | P15: 403.5 | Q15: 481 | R15: 481 | S15: 232 | T15: 359 | U15: 307 | V15: 299.33333 | W15: 364.33333 | X15: 101 | Y15: 94 | Z15: 125 | AA15: 104 | AB15: 106 | AC15: 93 | AD15: 292 | AE15: 100 | AF15: 161.66667 | AG15: 88 | AH15: 86 | AI15: 295 | AJ15: 287 | AK15: 189 | AL15: 151.36364 | AM15: 226.52941 | AN15: 31 | AO15: 172 | AP15: 101.5 | AQ15: 101.5 | AR15: 394 | AS15: 448 | AT15: 421 | AU15: 421 | AV15: 115 | AW15: 115 | AX15: 115 | AY15: 13 | AZ15: 211 | BA15: 112 | BB15: 112 | BC15: 232 | BD15: 11 | BE15: 121.5 | BF15: 121.5 | BG15: 209 | BH15: 209 | BI15: 209 | BJ15: 183.6
A16: General Requirements | B16: 0 | C16: 0 | D16: 0 | E16: 0 | F16: 0 | G16: 0 | H16: 0 | I16: 0 | J16: 0 | K16: 0 | L16: 0 | M16: 0 | N16: 0 | O16: 0 | P16: 0 | Q16: 0 | R16: 0 | S16: 0 | T16: 0 | U16: 0 | V16: 0 | W16: 0 | X16: 0 | Y16: 0 | Z16: 0 | AA16: 0 | AB16: 0 | AC16: 0 | AD16: 0 | AE16: 0 | AF16: 0 | AG16: 0 | AH16: 0 | AI16: 0 | AJ16: 0 | AK16: 0 | AL16: 0 | AM16: 0 | AN16: 0 | AO16: 0 | AP16: 0 | AQ16: 0 | AR16: 0 | AS16: 0 | AT16: 0 | AU16: 0 | AV16: 0 | AW16: 0 | AX16: 0 | AY16: 0 | AZ16: 0 | BA16: 0 | BB16: 0 | BC16: 0 | BD16: 0 | BE16: 0 | BF16: 0 | BG16: 0 | BH16: 0 | BI16: 0 | BJ16: 0
A17: Internal Finishes | B17: 364.90458 | C17: 474.30868 | D17: 419.60663 | E17: 546.59152 | F17: 200.56366 | G17: 373.57759 | H17: 373.57759 | I17: 507.13993 | J17: 601.25067 | K17: 554.1953 | L17: 438.3338 | M17: 438.3338 | N17: 675 | O17: 605 | P17: 640 | Q17: 1172 | R17: 1172 | S17: 1010 | T17: 1138 | U17: 549 | V17: 899 | W17: 858.16667 | X17: 151 | Y17: 140 | Z17: 186 | AA17: 155 | AB17: 158 | AC17: 139 | AD17: 523 | AE17: 150 | AF17: 270.66667 | AG17: 133 | AH17: 129 | AI17: 500 | AJ17: 496 | AK17: 314.5 | AL17: 245.63636 | AM17: 461.82353 | AN17: 164 | AO17: 317 | AP17: 240.5 | AQ17: 240.5 | AR17: 643 | AS17: 687 | AT17: 665 | AU17: 665 | AV17: 120 | AW17: 120 | AX17: 120 | AY17: 561 | AZ17: 387 | BA17: 474 | BB17: 474 | BC17: 326 | BD17: 292 | BE17: 309 | BF17: 309 | BG17: 383 | BH17: 383 | BI17: 383 | BJ17: 388
A18: Internal Walls and Doors | B18: 189.45266 | C18: 229.36243 | D18: 209.40754 | E18: 140.2757 | F18: 143.80656 | G18: 241.0282 | H18: 175.03682 | I18: 153.63058 | J18: 397.404 | K18: 275.51729 | L18: 213.56573 | M18: 213.56573 | N18: 317 | O18: 540 | P18: 428.5 | Q18: 440 | R18: 440 | S18: 238 | T18: 590 | U18: 196 | V18: 341.33333 | W18: 386.83333 | X18: 284 | Y18: 264 | Z18: 350 | AA18: 292 | AB18: 297.5 | AC18: 262 | AD18: 187 | AE18: 282 | AF18: 243.66667 | AG18: 250 | AH18: 242 | AI18: 239 | AJ18: 221 | AK18: 238 | AL18: 261.18182 | AM18: 305.52941 | AN18: 90 | AO18: 172 | AP18: 131 | AQ18: 131 | AR18: 302 | AS18: 184.44444 | AT18: 243.22222 | AU18: 243.22222 | AV18: 45 | AW18: 45 | AX18: 45 | AY18: 293 | AZ18: 211 | BA18: 252 | BB18: 252 | BC18: 205 | BD18: 133 | BE18: 169 | BF18: 169 | BG18: 209 | BH18: 209 | BI18: 209 | BJ18: 184.44444
A19: Mechanical | B19: 875.6979 | C19: 822.55123 | D19: 849.12457 | E19: 1035.1379 | F19: 806.47367 | G19: 785.48212 | H19: 875.6979 | I19: 1086.0617 | J19: 1252.86 | K19: 1169.4609 | L19: 952.0378 | M19: 952.0378 | N19: 759 | O19: 781 | P19: 770 | Q19: 1421 | R19: 1421 | S19: 968 | T19: 1108 | U19: 1503 | V19: 1193 | W19: 1090 | X19: 543 | Y19: 504 | Z19: 668 | AA19: 557 | AB19: 568 | AC19: 498 | AD19: 556.875 | AE19: 538 | AF19: 530.95833 | AG19: 476 | AH19: 462 | AI19: 756 | AJ19: 489 | AK19: 545.75 | AL19: 549.80682 | AM19: 740.46324 | AN19: 593 | AO19: 746 | AP19: 669.5 | AQ19: 669.5 | AR19: 723 | AS19: 888 | AT19: 805.5 | AU19: 805.5 | AV19: 520 | AW19: 520 | AX19: 520 | AY19: 1179 | AZ19: 844 | BA19: 1011.5 | BB19: 1011.5 | BC19: 994 | BD19: 627 | BE19: 810.5 | BF19: 810.5 | BG19: 836 | BH19: 836 | BI19: 836 | BJ19: 795
A20: Sanitary Fittings | B20: 47.363165 | C20: 36.10156 | D20: 41.732363 | E20: 9.6741862 | F20: 81.630449 | G20: 83.368326 | H20: 58.22432 | I20: 108.919 | J20: 116.28 | K20: 112.5995 | L20: 69.048098 | M20: 69.048098 | N20: 85 | O20: 117 | P20: 101 | Q20: 155 | R20: 155 | S20: 88 | T20: 181 | U20: 68 | V20: 112.33333 | W20: 115.66667 | X20: 66 | Y20: 60 | Z20: 76 | AA20: 63 | AB20: 66.25 | AC20: 60 | AD20: 65 | AE20: 65 | AF20: 63.333333 | AG20: 57 | AH20: 56 | AI20: 119 | AJ20: 73 | AK20: 76.25 | AL20: 69.090909 | AM20: 85.529412 | AN20: 71 | AO20: 57 | AP20: 64 | AQ20: 64 | AR20: 81 | AS20: 64.666667 | AT20: 72.833333 | AU20: 72.833333 | AV20: 25 | AW20: 25 | AX20: 25 | AY20: 44 | AZ20: 70 | BA20: 57 | BB20: 57 | BC20: 113 | BD20: 51 | BE20: 82 | BF20: 82 | BG20: 70 | BH20: 70 | BI20: 70 | BJ20: 64.666667
A21: Services Equipment | B21: 10.29634 | C21: 16.919026 | D21: 13.607683 | E21: 20.960737 | F21: 10.817758 | G21: 19.5 | H21: 17.092831 | I21: 46.700281 | J21: 45 | K21: 45.850141 | L21: 24.313449 | M21: 24.313449 | N21: 51 | O21: 56 | P21: 53.5 | Q21: 94 | R21: 94 | S21: 94 | T21: 94 | U21: 175 | V21: 121 | W21: 94 | X21: 0 | Y21: 0 | Z21: 0 | AA21: 0 | AB21: 0 | AC21: 0 | AD21: 0 | AE21: 0 | AF21: 0 | AG21: 0 | AH21: 0 | AI21: 0 | AJ21: 0 | AK21: 0 | AL21: 0 | AM21: 33.176471 | AN21: 16 | AO21: 0 | AP21: 8 | AQ21: 8 | AR21: 48 | AS21: 133 | AT21: 90.5 | AU21: 90.5 | AV21: 0 | AW21: 0 | AX21: 0 | AY21: 17 | AZ21: 0 | BA21: 8.5 | BB21: 8.5 | BC21: 74 | BD21: 32 | BE21: 53 | BF21: 53 | BG21: 0 | BH21: 0 | BI21: 0 | BJ21: 32
A22: Substructure | B22: 589.9803 | C22: 601.71625 | D22: 595.84827 | E22: 594.86581 | F22: 650 | G22: 572.0189 | H22: 605.62824 | I22: 617.31212 | J22: 545.08 | K22: 581.19606 | L22: 595.85334 | M22: 595.85334 | N22: 373 | O22: 452 | P22: 412.5 | Q22: 294 | R22: 294 | S22: 456 | T22: 314 | U22: 286 | V22: 352 | W22: 362.5 | X22: 220 | Y22: 204 | Z22: 272 | AA22: 226 | AB22: 230.5 | AC22: 201 | AD22: 273 | AE22: 218 | AF22: 230.66667 | AG22: 193 | AH22: 187 | AI22: 379 | AJ22: 506 | AK22: 316.25 | AL22: 261.72727 | AM22: 297.29412 | AN22: 474 | AO22: 402 | AP22: 438 | AQ22: 438 | AR22: 267 | AS22: 513 | AT22: 390 | AU22: 390 | AV22: 660 | AW22: 660 | AX22: 660 | AY22: 431 | AZ22: 577 | BA22: 504 | BB22: 504 | BC22: 901 | BD22: 401 | BE22: 651 | BF22: 651 | BG22: 557 | BH22: 557 | BI22: 557 | BJ22: 518.3
... A24: Grand Total | B24: 5607.6202 | C24: 6301.6264 | D24: 458.04794 | E24: 6776.2036 | F24: 4344.096 | G24: 5884.056 | H24: 436.00912 | I24: 6939.7479 | J24: 8524.5131 | K24: 594.77927 | L24: 487.66883 | M24: 487.66883 | N24: 5988 | O24: 6335 | P24: 473.96154 | Q24: 7625 | R24: 586.53846 | S24: 6733.8 | T24: 7402.8 | U24: 6773 | V24: 536.14359 | W24: 523.81538 | X24: 3324 | Y24: 3103 | Z24: 4014 | AA24: 3345 | AB24: 265.11538 | AC24: 3067 | AD24: 3864.5 | AE24: 3317 | AF24: 262.78205 | AG24: 2935 | AH24: 2850 | AI24: 4583 | AJ24: 4313.1 | AK24: 282.32885 | AL24: 270.73846 | AM24: 360.05973 | AN24: 5321 | AO24: 5356 | AP24: 410.65385 | AQ24: 410.65385 | AR24: 6031 | AS24: 6880.3111 | AT24: 496.58889 | AU24: 496.58889 | AV24: 4298 | AW24: 330.61538 | AX24: 330.61538 | AY24: 6085 | AZ24: 6427 | BA24: 481.23077 | BB24: 481.23077 | BC24: 7386.8 | BD24: 5694 | BE24: 503.10769 | BF24: 503.10769 | BG24: 6462 | BH24: 497.07692 | BI24: 497.07692 | BJ24: 461.08547

Sheet Infra Pivot
A1: Sum of GLA Rate/M2 | B1: Column Labels
B2: High Density | C2: High Density Average | D2: Low Density | R2: Low Density Average | S2: Mid Density | AC2: Mid Density Average | BD2: Grand Total
A3: Row Labels | B3: Project 19 | D3: Project 01 | E3: Project 02 | F3: Project 03 | G3: Project 04 | H3: Project 05 | I3: Project 06 | J3: Project 07 | K3: Project 08 | L3: Project 14 | M3: Project 21 | N3: Project 22 | O3: Project 23 | P3: Project 24 | Q3: Project 25 | S3: Project 09 | T3: Project 10 | U3: Project 11 | V3: Project 12 | W3: Project 13 | X3: Project 15 | Y3: Project 16 | Z3: Project 17 | AA3: Project 18 | AB3: Project 20 | AD3: Project 01 Average | AE3: Project 02 Average | AF3: Project 03 Average | AG3: Project 04 Average | AH3: Project 05 Average | AI3: Project 06 Average | AJ3: Project 07 Average | AK3: Project 08 Average | AL3: Project 09 Average | AM3: Project 10 Average | AN3: Project 11 Average | AO3: Project 12 Average | AP3: Project 13 Average | AQ3: Project 14 Average | AR3: Project 15 Average | AS3: Project 16 Average | AT3: Project 17 Average | AU3: Project 18 Average | AV3: Project 19 Average | AW3: Project 20 Average | AX3: Project 21 Average | AY3: Project 22 Average | AZ3: Project 23 Average | BA3: Project 24 Average | BB3: Project 25 Average | BC3: (blank) Average
A4: Irrigation Pumping Station/Water tank (100% primary) | B4: 0 | C4: 0 | D4: 0 | E4: 0 | F4: 0 | G4: 0 | H4: 0 | I4: 0 | J4: 0 | K4: 0 | L4: 0 | M4: 0 | N4: 0 | O4: 6.5239741 | P4: 7.9248861 | Q4: 0 | R4: 1.0320614 | S4: 0 | T4: 0 | U4: 0 | V4: 0 | W4: 0 | X4: 0 | Y4: 0 | Z4: 0 | AA4: 0 | AB4: 0 | AC4: 0 | AD4: 0 | AE4: 0 | AF4: 0 | AG4: 0 | AH4: 0 | AI4: 0 | AJ4: 0 | AK4: 0 | AL4: 0 | AM4: 0 | AN4: 0 | AO4: 0 | AP4: 0 | AQ4: 0 | AR4: 0 | AS4: 0 | AT4: 0 | AU4: 0 | AV4: 0 | AW4: 0 | AX4: 0 | AY4: 0 | AZ4: 6.5239741 | BA4: 7.9248861 | BB4: 0 | BD4: 14.44886
A5: ITS Network (Included in Telecommunication Network) | B5: 0 | C5: 0 | D5: 0 | E5: 0 | F5: 0 | G5: 0 | H5: 0 | I5: 0 | J5: 0 | K5: 0 | L5: 0 | M5: 0 | N5: 0 | O5: 0 | P5: 0 | Q5: 0 | R5: 0 | S5: 0 | T5: 0 | U5: 0 | V5: 0 | W5: 0 | X5: 0 | Y5: 0 | Z5: 0 | AA5: 0 | AB5: 0 | AC5: 0 | AD5: 0 | AE5: 0 | AF5: 0 | AG5: 0 | AH5: 0 | AI5: 0 | AJ5: 0 | AK5: 0 | AL5: 0 | AM5: 0 | AN5: 0 | AO5: 0 | AP5: 0 | AQ5: 0 | AR5: 0 | AS5: 0 | AT5: 0 | AU5: 0 | AV5: 0 | AW5: 0 | AX5: 0 | AY5: 0 | AZ5: 0 | BA5: 0 | BB5: 0 | BD5: 0
A6: Sewer Treatment Plant/Pumping Station (100% primary) | B6: 0 | C6: 0 | D6: 0 | E6: 0 | F6: 0 | G6: 0 | H6: 21.575249 | I6: 0 | J6: 0 | K6: 0 | L6: 9.3657706 | M6: 0 | N6: 0 | O6: 10.20821 | P6: 7.2044419 | Q6: 0 | R6: 3.4538337 | S6: 0 | T6: 0 | U6: 0 | V6: 0 | W6: 0 | X6: 0 | Y6: 0 | Z6: 0 | AA6: 0 | AB6: 0 | AC6: 0 | AD6: 0 | AE6: 0 | AF6: 0 | AG6: 0 | AH6: 21.575249 | AI6: 0 | AJ6: 0 | AK6: 0 | AL6: 0 | AM6: 0 | AN6: 0 | AO6: 0 | AP6: 0 | AQ6: 9.3657706 | AR6: 0 | AS6: 0 | AT6: 0 | AU6: 0 | AV6: 0 | AW6: 0 | AX6: 0 | AY6: 0 | AZ6: 10.20821 | BA6: 7.2044419 | BB6: 0 | BD6: 48.353672
A7: CCTV System | B7: 15.868763 | C7: 15.868763 | D7: 13.955916 | E7: 12.283663 | F7: 10.72259 | G7: 6.7219669 | H7: 0 | I7: 0 | J7: 8.5898011 | K7: 12.560925 | L7: 0 | M7: 5.7537707 | N7: 0 | O7: 12 | P7: 0 | Q7: 0 | R7: 5.8991881 | S7: 0 | T7: 6.0857337 | U7: 0 | V7: 0 | W7: 4.0054053 | X7: 0 | Y7: 0 | Z7: 0 | AA7: 6.334451 | AB7: 14.949406 | AC7: 3.1374996 | AD7: 13.955916 | AE7: 12.283663 | AF7: 10.72259 | AG7: 6.7219669 | AH7: 0 | AI7: 0 | AJ7: 8.5898011 | AK7: 12.560925 | AL7: 0 | AM7: 6.0857337 | AN7: 0 | AO7: 0 | AP7: 4.0054053 | AQ7: 0 | AR7: 0 | AS7: 0 | AT7: 0 | AU7: 6.334451 | AV7: 15.868763 | AW7: 14.949406 | AX7: 5.7537707 | AY7: 0 | AZ7: 12 | BA7: 0 | BB7: 0 | BD7: 129.83239
A8: Demolition and Site Clearance | B8: 1.653402 | C8: 1.653402 | D8: 0 | E8: 2.5076029 | F8: 2.586115 | G8: 2.6024389 | H8: 3.3563469 | I8: 4.1509863 | J8: 0 | K8: 3.8601588 | L8: 6.2002242 | M8: 8.2935626 | N8: 0.89678911 | O8: 6 | P8: 3.3 | Q8: 4.17 | R8: 3.4231589 | S8: 0 | T8: 4.837823 | U8: 0.41011604 | V8: 0 | W8: 0 | X8: 32.974613 | Y8: 21.834086 | Z8: 0 | AA8: 0.46738067 | AB8: 0.79911219 | AC8: 6.1323131 | AD8: 0 | AE8: 2.5076029 | AF8: 2.586115 | AG8: 2.6024389 | AH8: 3.3563469 | AI8: 4.1509863 | AJ8: 0 | AK8: 3.8601588 | AL8: 0 | AM8: 4.837823 | AN8: 0.41011604 | AO8: 0 | AP8: 0 | AQ8: 6.2002242 | AR8: 32.974613 | AS8: 21.834086 | AT8: 0 | AU8: 0.46738067 | AV8: 1.653402 | AW8: 0.79911219 | AX8: 8.2935626 | AY8: 0.89678911 | AZ8: 6 | BA8: 3.3 | BB8: 4.17 | BD8: 110.90076
A9: Drainage Network | B9: 0 | C9: 0 | D9: 12.49692 | E9: 14.093123 | F9: 18.485646 | G9: 11.653569 | H9: 42.07896 | I9: 41.864714 | J9: 33.059985 | K9: 33.266077 | L9: 0 | M9: 47.417185 | N9: 13.336345 | O9: 35 | P9: 29.7 | Q9: 37.89782 | R9: 26.453596 | S9: 0 | T9: 0 | U9: 0 | V9: 0 | W9: 0 | X9: 0 | Y9: 0 | Z9: 0 | AA9: 0 | AB9: 0 | AC9: 0 | AD9: 12.49692 | AE9: 14.093123 | AF9: 18.485646 | AG9: 11.653569 | AH9: 42.07896 | AI9: 41.864714 | AJ9: 33.059985 | AK9: 33.266077 | AL9: 0 | AM9: 0 | AN9: 0 | AO9: 0 | AP9: 0 | AQ9: 0 | AR9: 0 | AS9: 0 | AT9: 0 | AU9: 0 | AV9: 0 | AW9: 0 | AX9: 47.417185 | AY9: 13.336345 | AZ9: 35 | BA9: 29.7 | BB9: 37.89782 | BD9: 370.35034
A10: Earthworks | B10: 14.308827 | C10: 14.308827 | D10: 4.6916005 | E10: 29.201661 | F10: 28.14884 | G10: 44.475454 | H10: 14.454225 | I10: 15.981857 | J10: 18.115671 | K10: 32.498189 | L10: 23.064497 | M10: 38.486821 | N10: 30.990537 | O10: 35 | P10: 13.2 | Q10: 13.431501 | R10: 24.410061 | S10: 8.801159 | T10: 23.229129 | U10: 1.7856366 | V10: 24.353765 | W10: 23.064497 | X10: 7.3462367 | Y10: 9.2898671 | Z10: 5.9551226 | AA10: 3.0930037 | AB10: 17.62063 | AC10: 12.453905 | AD10: 4.6916005 | AE10: 29.201661 | AF10: 28.14884 | AG10: 44.475454 | AH10: 14.454225 | AI10: 15.981857 | AJ10: 18.115671 | AK10: 32.498189 | AL10: 8.801159 | AM10: 23.229129 | AN10: 1.7856366 | AO10: 24.353765 | AP10: 23.064497 | AQ10: 23.064497 | AR10: 7.3462367 | AS10: 9.2898671 | AT10: 5.9551226 | AU10: 3.0930037 | AV10: 14.308827 | AW10: 17.62063 | AX10: 38.486821 | AY10: 30.990537 | AZ10: 35 | BA10: 13.2 | BB10: 13.431501 | BD10: 480.58873
A11: Electrical Works (HV, LV, MV) | B11: 13.583029 | C11: 13.583029 | D11: 28.764898 | E11: 33.492199 | F11: 31.826443 | G11: 24.271196 | H11: 27.179485 | I11: 25.368528 | J11: 55 | K11: 48 | L11: 35.927785 | M11: 57 | N11: 18.367663 | O11: 40 | P11: 26.549587 | Q11: 54.480207 | R11: 36.159142 | S11: 37.105761 | T11: 22.190112 | U11: 22.190112 | V11: 35.068282 | W11: 22.190112 | X11: 8.405181 | Y11: 8.2314239 | Z11: 59 | AA11: 14.021215 | AB11: 7.1830512 | AC11: 23.558525 | AD11: 28.764898 | AE11: 33.492199 | AF11: 31.826443 | AG11: 24.271196 | AH11: 27.179485 | AI11: 25.368528 | AJ11: 55 | AK11: 48 | AL11: 37.105761 | AM11: 22.190112 | AN11: 22.190112 | AO11: 35.068282 | AP11: 22.190112 | AQ11: 35.927785 | AR11: 8.405181 | AS11: 8.2314239 | AT11: 59 | AU11: 14.021215 | AV11: 13.583029 | AW11: 7.1830512 | AX11: 57 | AY11: 18.367663 | AZ11: 40 | BA11: 26.549587 | BB11: 54.480207 | BD11: 755.39627
A12: Ground Investigation | B12: 0 | C12: 0 | D12: 0.43252171 | E12: 0 | F12: 0 | G12: 0 | H12: 0 | I12: 1.4187627 | J12: 0 | K12: 1.0644885 | L12: 0 | M12: 0 | N12: 0.34386957 | O12: 3 | P12: 0 | Q12: 0.1256783 | R12: 0.45609434 | S12: 0 | T12: 0 | U12: 0 | V12: 0 | W12: 0 | X12: 0 | Y12: 0 | Z12: 0 | AA12: 0 | AB12: 0.05540313 | AC12: 0.005540313 | AD12: 0.43252171 | AE12: 0 | AF12: 0 | AG12: 0 | AH12: 0 | AI12: 1.4187627 | AJ12: 0 | AK12: 1.0644885 | AL12: 0 | AM12: 0 | AN12: 0 | AO12: 0 | AP12: 0 | AQ12: 0 | AR12: 0 | AS12: 0 | AT12: 0 | AU12: 0 | AV12: 0 | AW12: 0.05540313 | AX12: 0 | AY12: 0.34386957 | AZ12: 3 | BA12: 0 | BB12: 0.1256783 | BD12: 6.4407239
A13: Hard Landscaping | B13: 0 | C13: 0 | D13: 36.912689 | E13: 26.771388 | F13: 33.92613 | G13: 21.40473 | H13: 39.587298 | I13: 40.51997 | J13: 39.099386 | K13: 42.370712 | L13: 0 | M13: 39.847667 | N13: 0 | O13: 39.679592 | P13: 17.530217 | Q13: 0 | R13: 26.974984 | S13: 0 | T13: 0 | U13: 0 | V13: 0 | W13: 0 | X13: 0 | Y13: 0 | Z13: 0 | AA13: 0 | AB13: 0 | AC13: 0 | AD13: 36.912689 | AE13: 26.771388 | AF13: 33.92613 | AG13: 21.40473 | AH13: 39.587298 | AI13: 40.51997 | AJ13: 39.099386 | AK13: 42.370712 | AL13: 0 | AM13: 0 | AN13: 0 | AO13: 0 | AP13: 0 | AQ13: 0 | AR13: 0 | AS13: 0 | AT13: 0 | AU13: 0 | AV13: 0 | AW13: 0 | AX13: 39.847667 | AY13: 0 | AZ13: 39.679592 | BA13: 17.530217 | BB13: 0 | BD13: 377.64978
A14: ICT Network (Telecommunication Network) | B14: 0 | C14: 0 | D14: 0 | E14: 0 | F14: 0 | G14: 0 | H14: 0 | I14: 0 | J14: 0 | K14: 0 | L14: 0 | M14: 0 | N14: 0 | O14: 0 | P14: 0 | Q14: 0 | R14: 0 | S14: 0 | T14: 0 | U14: 0 | V14: 0 | W14: 0 | X14: 0 | Y14: 0 | Z14: 0 | AA14: 0 | AB14: 0 | AC14: 0 | AD14: 0 | AE14: 0 | AF14: 0 | AG14: 0 | AH14: 0 | AI14: 0 | AJ14: 0 | AK14: 0 | AL14: 0 | AM14: 0 | AN14: 0 | AO14: 0 | AP14: 0 | AQ14: 0 | AR14: 0 | AS14: 0 | AT14: 0 | AU14: 0 | AV14: 0 | AW14: 0 | AX14: 0 | AY14: 0 | AZ14: 0 | BA14: 0 | BB14: 0 | BD14: 0
A15: Potable Water tank & Pumping Station/tank (100% primary) | B15: 0 | C15: 0 | D15: 0 | E15: 0 | F15: 0 | G15: 0 | H15: 0 | I15: 0 | J15: 0 | K15: 0 | L15: 0 | M15: 0 | N15: 0 | O15: 6.1140081 | P15: 0 | Q15: 0 | R15: 0.43671486 | S15: 0 | T15: 0 | U15: 0 | V15: 0 | W15: 0 | X15: 0 | Y15: 0 | Z15: 0 | AA15: 0 | AB15: 0 | AC15: 0 | AD15: 0 | AE15: 0 | AF15: 0 | AG15: 0 | AH15: 0 | AI15: 0 | AJ15: 0 | AK15: 0 | AL15: 0 | AM15: 0 | AN15: 0 | AO15: 0 | AP15: 0 | AQ15: 0 | AR15: 0 | AS15: 0 | AT15: 0 | AU15: 0 | AV15: 0 | AW15: 0 | AX15: 0 | AY15: 0 | AZ15: 6.1140081 | BA15: 0 | BB15: 0 | BD15: 6.1140081
... A23: Street Lighting Network | B23: 3.5120345 | C23: 3.5120345 | D23: 11.761839 | E23: 7.6962287 | F23: 8.4151455 | G23: 6.6670129 | H23: 8.016259 | I23: 0 | J23: 22.702744 | K23: 14.427255 | L23: 10.374178 | M23: 17.772332 | N23: 4.6097579 | O23: 14 | P23: 7.7 | Q23: 21.903101 | R23: 11.146132 | S23: 10.863412 | T23: 15.470298 | U23: 24.546535 | V23: 13.160645 | W23: 11.752683 | X23: 24.884329 | Y23: 26.310933 | Z23: 4.8068902 | AA23: 10.389103 | AB23: 23.476626 | AC23: 16.566145 | AD23: 11.761839 | AE23: 7.6962287 | AF23: 8.4151455 | AG23: 6.6670129 | AH23: 8.016259 | AI23: 0 | AJ23: 22.702744 | AK23: 14.427255 | AL23: 10.863412 | AM23: 15.470298 | AN23: 24.546535 | AO23: 13.160645 | AP23: 11.752683 | AQ23: 10.374178 | AR23: 24.884329 | AS23: 26.310933 | AT23: 4.8068902 | AU23: 10.389103 | AV23: 3.5120345 | AW23: 23.476626 | AX23: 17.772332 | AY23: 4.6097579 | AZ23: 14 | BA23: 7.7 | BB23: 21.903101 | BD23: 325.21934
A24: Structural Metal Works | B24: 0 | C24: 0 | D24: 0.016932228 | E24: 0 | F24: 0 | G24: 0 | H24: 0 | I24: 1.0215218 | J24: 0 | K24: 0.59711107 | L24: 0 | M24: 0 | N24: 0 | P24: 0 | Q24: 0 | R24: 0.1258127 | S24: 0 | T24: 0 | U24: 0 | V24: 0 | W24: 0 | X24: 0 | Y24: 0 | Z24: 0 | AA24: 0 | AB24: 0 | AC24: 0 | AD24: 0.016932228 | AE24: 0 | AF24: 0 | AG24: 0 | AH24: 0 | AI24: 1.0215218 | AJ24: 0 | AK24: 0.59711107 | AL24: 0 | AM24: 0 | AN24: 0 | AO24: 0 | AP24: 0 | AQ24: 0 | AR24: 0 | AS24: 0 | AT24: 0 | AU24: 0 | AV24: 0 | AW24: 0 | AX24: 0 | AY24: 0 | BA24: 0 | BB24: 0 | BD24: 1.6355651
A25: Telecommunication Network (Including ICT and ITS) | B25: 3.2138511 | C25: 3.2138511 | D25: 8.9188321 | E25: 8.366941 | F25: 13.039531 | G25: 6.7586175 | H25: 20.247165 | I25: 24.911044 | J25: 20.850566 | K25: 19.472265 | L25: 10.396918 | M25: 33.839372 | N25: 6.2390678 | O25: 26 | P25: 8.8 | Q25: 21.90281 | R25: 16.410224 | S25: 23.906535 | T25: 14.321001 | U25: 19.704757 | V25: 9.8651097 | W25: 23.909646 | X25: 11.917829 | Y25: 15.555124 | Z25: 5.2472518 | AA25: 7.9801013 | AB25: 7.2369817 | AC25: 13.964434 | AD25: 8.9188321 | AE25: 8.366941 | AF25: 13.039531 | AG25: 6.7586175 | AH25: 20.247165 | AI25: 24.911044 | AJ25: 20.850566 | AK25: 19.472265 | AL25: 23.906535 | AM25: 14.321001 | AN25: 19.704757 | AO25: 9.8651097 | AP25: 23.909646 | AQ25: 10.396918 | AR25: 11.917829 | AS25: 15.555124 | AT25: 5.2472518 | AU25: 7.9801013 | AV25: 3.2138511 | AW25: 7.2369817 | AX25: 33.839372 | AY25: 6.2390678 | AZ25: 26 | BA25: 8.8 | BB25: 21.90281 | BD25: 372.60132
A26: Traffic signal | B26: 0 | C26: 0 | D26: 0 | E26: 0 | F26: 0 | G26: 0 | H26: 0 | I26: 0 | J26: 0 | K26: 0 | L26: 0 | M26: 0 | N26: 0 | O26: 2 | P26: 0 | Q26: 0 | R26: 0.14285714 | S26: 0 | T26: 0 | U26: 0 | V26: 0 | W26: 0 | X26: 0 | Y26: 0 | Z26: 0 | AA26: 0 | AB26: 0 | AC26: 0 | AD26: 0 | AE26: 0 | AF26: 0 | AG26: 0 | AH26: 0 | AI26: 0 | AJ26: 0 | AK26: 0 | AL26: 0 | AM26: 0 | AN26: 0 | AO26: 0 | AP26: 0 | AQ26: 0 | AR26: 0 | AS26: 0 | AT26: 0 | AU26: 0 | AV26: 0 | AW26: 0 | AX26: 0 | AY26: 0 | AZ26: 2 | BA26: 0 | BB26: 0 | BD26: 2
A27: TSE & Irrigation Network | B27: 6.3616096 | C27: 6.3616096 | D27: 6.0487926 | E27: 9.2568266 | F27: 10.984665 | G27: 7.4453164 | H27: 8.0302366 | I27: 3.6147221 | J27: 9.3570806 | K27: 8.393423 | L27: 7.9188167 | M27: 7.8102687 | N27: 6.6113252 | O27: 11 | P27: 13.2 | Q27: 16.945947 | R27: 9.0441014 | S27: 11.967023 | T27: 34.023706 | U27: 32.661289 | V27: 16.590307 | W27: 48.539209 | X27: 38.142196 | Y27: 45.763223 | Z27: 27.705353 | AA27: 27.705353 | AB27: 7.5719812 | AC27: 29.066964 | AD27: 6.0487926 | AE27: 9.2568266 | AF27: 10.984665 | AG27: 7.4453164 | AH27: 8.0302366 | AI27: 3.6147221 | AJ27: 9.3570806 | AK27: 8.393423 | AL27: 11.967023 | AM27: 34.023706 | AN27: 32.661289 | AO27: 16.590307 | AP27: 48.539209 | AQ27: 7.9188167 | AR27: 38.142196 | AS27: 45.763223 | AT27: 27.705353 | AU27: 27.705353 | AV27: 6.3616096 | AW27: 7.5719812 | AX27: 7.8102687 | AY27: 6.6113252 | AZ27: 11 | BA27: 13.2 | BB27: 16.945947 | BD27: 423.64867
A28: Grand Total | B28: 119.5594 | C28: 4.9816417 | D28: 207.83265 | E28: 253.2698 | F28: 284.87756 | G28: 212.06075 | H28: 299.73209 | I28: 293.45161 | J28: 348.12058 | K28: 369.27507 | L28: 187.54075 | M28: 359.54831 | N28: 130.73529 | O28: 474.768 | P28: 239.93676 | Q28: 346.18053 | R28: 11.962178 | S28: 224.11862 | T28: 215.02877 | U28: 200.45437 | V28: 189.69333 | W28: 289.92785 | X28: 275.91033 | Y28: 281.6405 | Z28: 228.04469 | AA28: 177.44471 | AB28: 214.85625 | AC28: 9.5713309 | AD28: 8.6596936 | AE28: 10.552909 | AF28: 11.869898 | AG28: 8.8358644 | AH28: 12.488837 | AI28: 12.22715 | AJ28: 14.505024 | AK28: 15.386461 | AL28: 9.3382756 | AM28: 8.9595322 | AN28: 8.3522655 | AO28: 7.9038886 | AP28: 12.080327 | AQ28: 7.8141979 | AR28: 11.496264 | AS28: 11.735021 | AT28: 9.501862 | AU28: 7.3935294 | AV28: 4.9816417 | AW28: 8.9523439 | AX28: 14.98118 | AY28: 5.4473039 | AZ28: 20.642087 | BA28: 9.9973649 | BB28: 14.424189 | BD28: 6424.0086
D30: 1 | E30: 2 | F30: 3 | G30: 4 | H30: 5 | I30: 6 | J30: 7 | K30: 8 | L30: 9 | M30: 10 | N30: 11 | O30: 12 | P30: 13 | Q30: 14 | S30: 1 | T30: 2 | U30: 3 | V30: 4 | W30: 5 | X30: 6 | Y30: 7 | Z30: 8 | AA30: 9 | AB30: 10 | AD30: 1 | AE30: 2 | AF30: 3 | AG30: 4 | AH30: 5 | AI30: 6 | AJ30: 7 | AK30: 8 | AL30: 9 | AM30: 10 | AN30: 11 | AO30: 12 | AP30: 13 | AQ30: 14 | AR30: 15 | AS30: 16 | AT30: 17 | AU30: 18 | AV30: 19 | AW30: 20 | AX30: 21 | AY30: 22 | AZ30: 23 | BA30: 24 | BB30: 25

Sheet Example Data Only
B1: Asset Lvl 1 | C1: Asset Lvl 2 | D1: Asset Lvl 3 | E1: Country | F1: City | G1: Developer | H1: Alias Lvl 1 | I1: Alias Lvl 2 | J1: Project Lvl 1 | K1: Project Lvl 2 | L1: Base Date | M1: Contractor | N1: Status | O1: Procurement | P1: Contract Type | Q1: BUA | R1: GIA | S1: GFA | T1: Keys | U1: NRM Lvl 1 | V1: Currency | W1: Total Cost | X1: Cost/BUA | Y1: Cost/GIA | Z1: Cost/GFA | AA1: Cost/Key | AB1: Chart
B3: Single Asset | C3: Villas | E3: UAE | F3: Dubai | G3: Emaar | I3: Project V19.1 | K3: Golf Place Villas (Phase 1) | L3: 2019 | M3: Trojan | N3: Award | O3: Competitive - Traditional | P3: Fixed Price Lump Sum | Q3: 113250.31 | R3: 104555 | S3: 69776 | T3: 158 | U3: Substructure | V3: AED | W3: 27123684 | X3: =W3/Q3 -> 239.50208 | Y3: =W3/R3 -> 259.42025 | Z3: =W3/S3 -> 388.72512 | AA3: =W3/T3 -> 171668.89 | AB3: YES | AC3: =SUM(W3:W15) -> 451204906 | AD3: =W3/AC3 -> 0.060113894
B4: Single Asset | C4: Villas | E4: UAE | F4: Dubai | G4: Emaar | I4: Project V19.1 | K4: Golf Place Villas (Phase 1) | L4: 2019 | M4: Trojan | N4: Award | O4: Competitive - Traditional | P4: Fixed Price Lump Sum | Q4: 113250.31 | R4: 104555 | S4: 69776 | T4: 158 | U4: Superstructure | V4: AED | W4: 57743431 | X4: =W4/Q4 -> 509.87438 | Y4: =W4/R4 -> 552.27805 | Z4: =W4/S4 -> 827.55433 | AA4: =W4/T4 -> 365464.75 | AB4: YES | AD4: =W4/AC3 -> 0.12797607
B5: Single Asset | C5: Villas | E5: UAE | F5: Dubai | G5: Emaar | I5: Project V19.1 | K5: Golf Place Villas (Phase 1) | L5: 2019 | M5: Trojan | N5: Award | O5: Competitive - Traditional | P5: Fixed Price Lump Sum | Q5: 113250.31 | R5: 104555 | S5: 69776 | T5: 158 | U5: Building External Envelope | V5: AED | W5: 83892459 | X5: =W5/Q5 -> 740.77024 | Y5: =W5/R5 -> 802.37635 | Z5: =W5/S5 -> 1202.3111 | AA5: =W5/T5 -> 530964.93 | AB5: YES | AD5: =W5/AC3 -> 0.18592985
B6: Single Asset | C6: Villas | E6: UAE | F6: Dubai | G6: Emaar | I6: Project V19.1 | K6: Golf Place Villas (Phase 1) | L6: 2019 | M6: Trojan | N6: Award | O6: Competitive - Traditional | P6: Fixed Price Lump Sum | Q6: 113250.31 | R6: 104555 | S6: 69776 | T6: 158 | U6: Internal Walls and Doors | V6: AED | W6: 14934994 | X6: =W6/Q6 -> 131.87597 | Y6: =W6/R6 -> 142.84342 | Z6: =W6/S6 -> 214.04199 | AA6: =W6/T6 -> 94525.278 | AB6: YES | AD6: =W6/AC3 -> 0.033100247
B7: Single Asset | C7: Villas | E7: UAE | F7: Dubai | G7: Emaar | I7: Project V19.1 | K7: Golf Place Villas (Phase 1) | L7: 2019 | M7: Trojan | N7: Award | O7: Competitive - Traditional | P7: Fixed Price Lump Sum | Q7: 113250.31 | R7: 104555 | S7: 69776 | T7: 158 | U7: Internal Finishes | V7: AED | W7: 80179291 | X7: =W7/Q7 -> 707.98298 | Y7: =W7/R7 -> 766.86233 | Z7: =W7/S7 -> 1149.0955 | AA7: =W7/T7 -> 507463.87 | AB7: YES | AD7: =W7/AC3 -> 0.1777004
B8: Single Asset | C8: Villas | E8: UAE | F8: Dubai | G8: Emaar | I8: Project V19.1 | K8: Golf Place Villas (Phase 1) | L8: 2019 | M8: Trojan | N8: Award | O8: Competitive - Traditional | P8: Fixed Price Lump Sum | Q8: 113250.31 | R8: 104555 | S8: 69776 | T8: 158 | U8: FF&E | V8: AED | W8: 20817957 | X8: =W8/Q8 -> 183.82252 | Y8: =W8/R8 -> 199.1101 | Z8: =W8/S8 -> 298.35412 | AA8: =W8/T8 -> 131759.22 | AB8: YES | AD8: =W8/AC3 -> 0.046138587
B9: Single Asset | C9: Villas | E9: UAE | F9: Dubai | G9: Emaar | I9: Project V19.1 | K9: Golf Place Villas (Phase 1) | L9: 2019 | M9: Trojan | N9: Award | O9: Competitive - Traditional | P9: Fixed Price Lump Sum | Q9: 113250.31 | R9: 104555 | S9: 69776 | T9: 158 | U9: Sanitary Fittings | V9: AED | W9: 3262311 | X9: =W9/Q9 -> 28.8062 | Y9: =W9/R9 -> 31.201865 | Z9: =W9/S9 -> 46.754056 | AA9: =W9/T9 -> 20647.538 | AB9: YES | AD9: =W9/AC3 -> 0.0072302206
B10: Single Asset | C10: Villas | E10: UAE | F10: Dubai | G10: Emaar | I10: Project V19.1 | K10: Golf Place Villas (Phase 1) | L10: 2019 | M10: Trojan | N10: Award | O10: Competitive - Traditional | P10: Fixed Price Lump Sum | Q10: 113250.31 | R10: 104555 | S10: 69776 | T10: 158 | U10: Services Equipment | V10: AED | W10: 0 | X10: =W10/Q10 -> 0 | Y10: =W10/R10 -> 0 | Z10: =W10/S10 -> 0 | AA10: =W10/T10 -> 0 | AB10: YES | AD10: =W10/AC3 -> 0
B11: Single Asset | C11: Villas | E11: UAE | F11: Dubai | G11: Emaar | I11: Project V19.1 | K11: Golf Place Villas (Phase 1) | L11: 2019 | M11: Trojan | N11: Award | O11: Competitive - Traditional | P11: Fixed Price Lump Sum | Q11: 113250.31 | R11: 104555 | S11: 69776 | T11: 158 | U11: Mechanical | V11: AED | W11: 28963004 | X11: =W11/Q11 -> 255.74327 | Y11: =W11/R11 -> 277.01214 | Z11: =W11/S11 -> 415.08547 | AA11: =W11/T11 -> 183310.15 | AB11: YES | AD11: =W11/AC3 -> 0.064190357
B12: Single Asset | C12: Villas | E12: UAE | F12: Dubai | G12: Emaar | I12: Project V19.1 | K12: Golf Place Villas (Phase 1) | L12: 2019 | M12: Trojan | N12: Award | O12: Competitive - Traditional | P12: Fixed Price Lump Sum | Q12: 113250.31 | R12: 104555 | S12: 69776 | T12: 158 | U12: Electrical | V12: AED | W12: 14909529 | X12: =W12/Q12 -> 131.65111 | Y12: =W12/R12 -> 142.59987 | Z12: =W12/S12 -> 213.67704 | AA12: =W12/T12 -> 94364.108 | AB12: YES | AD12: =W12/AC3 -> 0.03304381
B13: Single Asset | C13: Villas | E13: UAE | F13: Dubai | G13: Emaar | I13: Project V19.1 | K13: Golf Place Villas (Phase 1) | L13: 2019 | M13: Trojan | N13: Award | O13: Competitive - Traditional | P13: Fixed Price Lump Sum | Q13: 113250.31 | R13: 104555 | S13: 69776 | T13: 158 | U13: Conveying Systems | V13: AED | W13: 0 | X13: =W13/Q13 -> 0 | Y13: =W13/R13 -> 0 | Z13: =W13/S13 -> 0 | AA13: =W13/T13 -> 0 | AB13: YES | AD13: =W13/AC3 -> 0
B14: Single Asset | C14: Villas | E14: UAE | F14: Dubai | G14: Emaar | I14: Project V19.1 | K14: Golf Place Villas (Phase 1) | L14: 2019 | M14: Trojan | N14: Award | O14: Competitive - Traditional | P14: Fixed Price Lump Sum | Q14: 113250.31 | R14: 104555 | S14: 69776 | T14: 158 | U14: External Works | V14: AED | W14: 8177680 | X14: =W14/Q14 -> 72.208898 | Y14: =W14/R14 -> 78.214146 | Z14: =W14/S14 -> 117.19904 | AA14: =W14/T14 -> 51757.468 | AB14: YES | AD14: =W14/AC3 -> 0.018124094
B15: Single Asset | C15: Villas | E15: UAE | F15: Dubai | G15: Emaar | I15: Project V19.1 | K15: Golf Place Villas (Phase 1) | L15: 2019 | M15: Trojan | N15: Award | O15: Competitive - Traditional | P15: Fixed Price Lump Sum | Q15: 113250.31 | R15: 104555 | S15: 69776 | T15: 158 | U15: General Requirements | V15: AED | W15: 111200566 | X15: =W15/Q15 -> 981.90077 | Y15: =W15/R15 -> 1063.5605 | Z15: =W15/S15 -> 1593.6793 | AA15: =W15/T15 -> 703801.05 | AB15: YES | AD15: =W15/AC3 -> 0.24645248
B16: Single Asset | C16: Villas | E16: UAE | F16: Dubai | G16: Emaar | I16: Project V21.1 | K16: Al Furjan (P3-V) | L16: 2022 | M16: ASGC | N16: Award | O16: Competitive - Traditional | P16: Fixed Price Lump Sum | Q16: 60504 | R16: 58317 | S16: 49568 | T16: 150 | U16: Substructure | V16: AED | W16: 13291964 | X16: =W16/Q16 -> 219.68736 | Y16: =W16/R16 -> 227.92606 | Z16: =W16/S16 -> 268.15615 | AA16: =W16/T16 -> 88613.093 | AB16: YES | AC16: =SUM(W16:W28) -> 209959928 | AD16: =W16/AC16 -> 0.063307147
B17: Single Asset | C17: Villas | E17: UAE | F17: Dubai | G17: Emaar | I17: Project V21.1 | K17: Al Furjan (P3-V) | L17: 2022 | M17: ASGC | N17: Award | O17: Competitive - Traditional | P17: Fixed Price Lump Sum | Q17: 60504 | R17: 58317 | S17: 49568 | T17: 150 | U17: Superstructure | V17: AED | W17: 25143116 | X17: =W17/Q17 -> 415.56122 | Y17: =W17/R17 -> 431.14557 | Z17: =W17/S17 -> 507.24492 | AA17: =W17/T17 -> 167620.77 | AB17: YES | AD17: =W17/AC16 -> 0.11975197
B18: Single Asset | C18: Villas | E18: UAE | F18: Dubai | G18: Emaar | I18: Project V21.1 | K18: Al Furjan (P3-V) | L18: 2022 | M18: ASGC | N18: Award | O18: Competitive - Traditional | P18: Fixed Price Lump Sum | Q18: 60504 | R18: 58317 | S18: 49568 | T18: 150 | U18: Building External Envelope | V18: AED | W18: 26043300 | X18: =W18/Q18 -> 430.43931 | Y18: =W18/R18 -> 446.58161 | Z18: =W18/S18 -> 525.4055 | AA18: =W18/T18 -> 173622 | AB18: YES | AD18: =W18/AC16 -> 0.12403938
B19: Single Asset | C19: Villas | E19: UAE | F19: Dubai | G19: Emaar | I19: Project V21.1 | K19: Al Furjan (P3-V) | L19: 2022 | M19: ASGC | N19: Award | O19: Competitive - Traditional | P19: Fixed Price Lump Sum | Q19: 60504 | R19: 58317 | S19: 49568 | T19: 150 | U19: Internal Walls and Doors | V19: AED | W19: 10589199 | X19: =W19/Q19 -> 175.01651 | Y19: =W19/R19 -> 181.57997 | Z19: =W19/S19 -> 213.62974 | AA19: =W19/T19 -> 70594.66 | AB19: YES | AD19: =W19/AC16 -> 0.050434381
B20: Single Asset | C20: Villas | E20: UAE | F20: Dubai | G20: Emaar | I20: Project V21.1 | K20: Al Furjan (P3-V) | L20: 2022 | M20: ASGC | N20: Award | O20: Competitive - Traditional | P20: Fixed Price Lump Sum | Q20: 60504 | R20: 58317 | S20: 49568 | T20: 150 | U20: Internal Finishes | V20: AED | W20: 22304299 | X20: =W20/Q20 -> 368.64173 | Y20: =W20/R20 -> 382.4665 | Z20: =W20/S20 -> 449.97375 | AA20: =W20/T20 -> 148695.33 | AB20: YES | AD20: =W20/AC16 -> 0.10623122
B21: Single Asset | C21: Villas | E21: UAE | F21: Dubai | G21: Emaar | I21: Project V21.1 | K21: Al Furjan (P3-V) | L21: 2022 | M21: ASGC | N21: Award | O21: Competitive - Traditional | P21: Fixed Price Lump Sum | Q21: 60504 | R21: 58317 | S21: 49568 | T21: 150 | U21: FF&E | V21: AED | W21: 24542022 | X21: =W21/Q21 -> 405.62644 | Y21: =W21/R21 -> 420.83821 | Z21: =W21/S21 -> 495.11826 | AA21: =W21/T21 -> 163613.48 | AB21: YES | AD21: =W21/AC16 -> 0.11688908
B22: Single Asset | C22: Villas | E22: UAE | F22: Dubai | G22: Emaar | I22: Project V21.1 | K22: Al Furjan (P3-V) | L22: 2022 | M22: ASGC | N22: Award | O22: Competitive - Traditional | P22: Fixed Price Lump Sum | Q22: 60504 | R22: 58317 | S22: 49568 | T22: 150 | U22: Sanitary Fittings | V22: AED | W22: 6803420 | X22: =W22/Q22 -> 112.44579 | Y22: =W22/R22 -> 116.66272 | Z22: =W22/S22 -> 137.25428 | AA22: =W22/T22 -> 45356.133 | AB22: YES | AD22: =W22/AC16 -> 0.032403421
B23: Single Asset | C23: Villas | E23: UAE | F23: Dubai | G23: Emaar | I23: Project V21.1 | K23: Al Furjan (P3-V) | L23: 2022 | M23: ASGC | N23: Award | O23: Competitive - Traditional | P23: Fixed Price Lump Sum | Q23: 60504 | R23: 58317 | S23: 49568 | T23: 150 | U23: Services Equipment | V23: AED | W23: 0 | X23: =W23/Q23 -> 0 | Y23: =W23/R23 -> 0 | Z23: =W23/S23 -> 0 | AA23: =W23/T23 -> 0 | AB23: YES | AD23: =W23/AC16 -> 0
B24: Single Asset | C24: Villas | E24: UAE | F24: Dubai | G24: Emaar | I24: Project V21.1 | K24: Al Furjan (P3-V) | L24: 2022 | M24: ASGC | N24: Award | O24: Competitive - Traditional | P24: Fixed Price Lump Sum | Q24: 60504 | R24: 58317 | S24: 49568 | T24: 150 | U24: Mechanical | V24: AED | W24: 32120642 | X24: =W24/Q24 -> 530.8846 | Y24: =W24/R24 -> 550.7938 | Z24: =W24/S24 -> 648.01166 | AA24: =W24/T24 -> 214137.61 | AB24: YES | AD24: =W24/AC16 -> 0.15298463
B25: Single Asset | C25: Villas | E25: UAE | F25: Dubai | G25: Emaar | I25: Project V21.1 | K25: Al Furjan (P3-V) | L25: 2022 | M25: ASGC | N25: Award | O25: Competitive - Traditional | P25: Fixed Price Lump Sum | Q25: 60504 | R25: 58317 | S25: 49568 | T25: 150 | U25: Electrical | V25: AED | W25: 9312451 | X25: =W25/Q25 -> 153.91463 | Y25: =W25/R25 -> 159.68673 | Z25: =W25/S25 -> 187.87224 | AA25: =W25/T25 -> 62083.007 | AB25: YES | AD25: =W25/AC16 -> 0.044353468
B26: Single Asset | C26: Villas | E26: UAE | F26: Dubai | G26: Emaar | I26: Project V21.1 | K26: Al Furjan (P3-V) | L26: 2022 | M26: ASGC | N26: Award | O26: Competitive - Traditional | P26: Fixed Price Lump Sum | Q26: 60504 | R26: 58317 | S26: 49568 | T26: 150 | U26: Conveying Systems | V26: AED | W26: 0 | X26: =W26/Q26 -> 0 | Y26: =W26/R26 -> 0 | Z26: =W26/S26 -> 0 | AA26: =W26/T26 -> 0 | AB26: YES | AD26: =W26/AC16 -> 0
B27: Single Asset | C27: Villas | E27: UAE | F27: Dubai | G27: Emaar | I27: Project V21.1 | K27: Al Furjan (P3-V) | L27: 2022 | M27: ASGC | N27: Award | O27: Competitive - Traditional | P27: Fixed Price Lump Sum | Q27: 60504 | R27: 58317 | S27: 49568 | T27: 150 | U27: External Works | V27: AED | W27: 20080103 | X27: =W27/Q27 -> 331.88059 | Y27: =W27/R27 -> 344.32675 | Z27: =W27/S27 -> 405.10214 | AA27: =W27/T27 -> 133867.35 | AB27: YES | AD27: =W27/AC16 -> 0.095637788
B28: Single Asset | C28: Villas | E28: UAE | F28: Dubai | G28: Emaar | I28: Project V21.1 | K28: Al Furjan (P3-V) | L28: 2022 | M28: ASGC | N28: Award | O28: Competitive - Traditional | P28: Fixed Price Lump Sum | Q28: 60504 | R28: 58317 | S28: 49568 | T28: 150 | U28: General Requirements | V28: AED | W28: 19729412 | X28: =W28/Q28 -> 326.08442 | Y28: =W28/R28 -> 338.31322 | Z28: =W28/S28 -> 398.02719 | AA28: =W28/T28 -> 131529.41 | AB28: YES | AD28: =W28/AC16 -> 0.093967512
B29: Single Asset | C29: Apartments | E29: UAE | F29: Abu Dhabi | G29: Q-Properties | I29: Project A24.2 | K29: REEM HILLS, Town Plaza | L29: 2024 | M29: Pivot | N29: Award | O29: Competitive - Traditional | P29: Fixed Price Lump Sum | Q29: 313548 | R29: 280221 | S29: 213367 | T29: 984 | U29: Substructure | V29: AED | W29: 145864793 | X29: =W29/Q29 -> 465.20722 | Y29: =W29/R29 -> 520.53484 | Z29: =W29/S29 -> 683.63333 | AA29: =W29/T29 -> 148236.58 | AB29: YES | AC29: =SUM(W29:W41) -> 1214455500 | AD29: =W29/AC29 -> 0.12010715
B30: Single Asset | C30: Apartments | E30: UAE | F30: Abu Dhabi | G30: Q-Properties | I30: Project A24.2 | K30: REEM HILLS, Town Plaza | L30: 2024 | M30: Pivot | N30: Award | O30: Competitive - Traditional | P30: Fixed Price Lump Sum | Q30: 313548 | R30: 280221 | S30: 213367 | T30: 984 | U30: Superstructure | V30: AED | W30: 240984035 | X30: =W30/Q30 -> 768.57143 | Y30: =W30/R30 -> 859.9785 | Z30: =W30/S30 -> 1129.4344 | AA30: =W30/T30 -> 244902.47 | AB30: YES | AD30: =W30/AC29 -> 0.1984297
B31: Single Asset | C31: Apartments | E31: UAE | F31: Abu Dhabi | G31: Q-Properties | I31: Project A24.2 | K31: REEM HILLS, Town Plaza | L31: 2024 | M31: Pivot | N31: Award | O31: Competitive - Traditional | P31: Fixed Price Lump Sum | Q31: 313548 | R31: 280221 | S31: 213367 | T31: 984 | U31: Building External Envelope | V31: AED | W31: 90300523 | X31: =W31/Q31 -> 287.99585 | Y31: =W31/R31 -> 322.24752 | Z31: =W31/S31 -> 423.21691 | AA31: =W31/T31 -> 91768.824 | AB31: YES | AD31: =W31/AC29 -> 0.07435474
B32: Single Asset | C32: Apartments | E32: UAE | F32: Abu Dhabi | G32: Q-Properties | I32: Project A24.2 | K32: REEM HILLS, Town Plaza | L32: 2024 | M32: Pivot | N32: Award | O32: Competitive - Traditional | P32: Fixed Price Lump Sum | Q32: 313548 | R32: 280221 | S32: 213367 | T32: 984 | U32: Internal Walls and Doors | V32: AED | W32: 69924753 | X32: =W32/Q32 -> 223.01132 | Y32: =W32/R32 -> 249.53431 | Z32: =W32/S32 -> 327.72056 | AA32: =W32/T32 -> 71061.741 | AB32: YES | AD32: =W32/AC29 -> 0.05757704
B33: Single Asset | C33: Apartments | E33: UAE | F33: Abu Dhabi | G33: Q-Properties | I33: Project A24.2 | K33: REEM HILLS, Town Plaza | L33: 2024 | M33: Pivot | N33: Award | O33: Competitive - Traditional | P33: Fixed Price Lump Sum | Q33: 313548 | R33: 280221 | S33: 213367 | T33: 984 | U33: Internal Finishes | V33: AED | W33: 132275601 | X33: =W33/Q33 -> 421.86715 | Y33: =W33/R33 -> 472.04029 | Z33: =W33/S33 -> 619.94404 | AA33: =W33/T33 -> 134426.42 | AB33: YES | AD33: =W33/AC29 -> 0.10891762
B34: Single Asset | C34: Apartments | E34: UAE | F34: Abu Dhabi | G34: Q-Properties | I34: Project A24.2 | K34: REEM HILLS, Town Plaza | L34: 2024 | M34: Pivot | N34: Award | O34: Competitive - Traditional | P34: Fixed Price Lump Sum | Q34: 313548 | R34: 280221 | S34: 213367 | T34: 984 | U34: FF&E | V34: AED | W34: 53549754 | X34: =W34/Q34 -> 170.78646 | Y34: =W34/R34 -> 191.09829 | Z34: =W34/S34 -> 250.97486 | AA34: =W34/T34 -> 54420.482 | AB34: YES | AD34: =W34/AC29 -> 0.044093632
B35: Single Asset | C35: Apartments | E35: UAE | F35: Abu Dhabi | G35: Q-Properties | I35: Project A24.2 | K35: REEM HILLS, Town Plaza | L35: 2024 | M35: Pivot | N35: Award | O35: Competitive - Traditional | P35: Fixed Price Lump Sum | Q35: 313548 | R35: 280221 | S35: 213367 | T35: 984 | U35: Sanitary Fittings | V35: AED | W35: 17360086 | X35: =W35/Q35 -> 55.366598 | Y35: =W35/R35 -> 61.95141 | Z35: =W35/S35 -> 81.362563 | AA35: =W35/T35 -> 17642.364 | AB35: YES | AD35: =W35/AC29 -> 0.014294543
B36: Single Asset | C36: Apartments | E36: UAE | F36: Abu Dhabi | G36: Q-Properties | I36: Project A24.2 | K36: REEM HILLS, Town Plaza | L36: 2024 | M36: Pivot | N36: Award | O36: Competitive - Traditional | P36: Fixed Price Lump Sum | Q36: 313548 | R36: 280221 | S36: 213367 | T36: 984 | U36: Services Equipment | V36: AED | W36: 1081588 | X36: =W36/Q36 -> 3.4495133 | Y36: =W36/R36 -> 3.8597678 | Z36: =W36/S36 -> 5.0691438 | AA36: =W36/T36 -> 1099.1748 | AB36: YES | AD36: =W36/AC29 -> 0.000890595
B37: Single Asset | C37: Apartments | E37: UAE | F37: Abu Dhabi | G37: Q-Properties | I37: Project A24.2 | K37: REEM HILLS, Town Plaza | L37: 2024 | M37: Pivot | N37: Award | O37: Competitive - Traditional | P37: Fixed Price Lump Sum | Q37: 313548 | R37: 280221 | S37: 213367 | T37: 984 | U37: Mechanical | V37: AED | W37: 152958790 | X37: =W37/Q37 -> 487.83213 | Y37: =W37/R37 -> 545.85056 | Z37: =W37/S37 -> 716.8812 | AA37: =W37/T37 -> 155445.92 | AB37: YES | AD37: =W37/AC29 -> 0.12594845
B38: Single Asset | C38: Apartments | E38: UAE | F38: Abu Dhabi | G38: Q-Properties | I38: Project A24.2 | K38: REEM HILLS, Town Plaza | L38: 2024 | M38: Pivot | N38: Award | O38: Competitive - Traditional | P38: Fixed Price Lump Sum | Q38: 313548 | R38: 280221 | S38: 213367 | T38: 984 | U38: Electrical | V38: AED | W38: 134749173 | X38: =W38/Q38 -> 429.75612 | Y38: =W38/R38 -> 480.8675 | Z38: =W38/S38 -> 631.53708 | AA38: =W38/T38 -> 136940.22 | AB38: YES | AD38: =W38/AC29 -> 0.11095439
B39: Single Asset | C39: Apartments | E39: UAE | F39: Abu Dhabi | G39: Q-Properties | I39: Project A24.2 | K39: REEM HILLS, Town Plaza | L39: 2024 | M39: Pivot | N39: Award | O39: Competitive - Traditional | P39: Fixed Price Lump Sum | Q39: 313548 | R39: 280221 | S39: 213367 | T39: 984 | U39: Conveying Systems | V39: AED | W39: 11669066 | X39: =W39/Q39 -> 37.216203 | Y39: =W39/R39 -> 41.642368 | Z39: =W39/S39 -> 54.690116 | AA39: =W39/T39 -> 11858.807 | AB39: YES | AD39: =W39/AC29 -> 0.0096084756
B40: Single Asset | C40: Apartments | E40: UAE | F40: Abu Dhabi | G40: Q-Properties | I40: Project A24.2 | K40: REEM HILLS, Town Plaza | L40: 2024 | M40: Pivot | N40: Award | O40: Competitive - Traditional | P40: Fixed Price Lump Sum | Q40: 313548 | R40: 280221 | S40: 213367 | T40: 984 | U40: External Works | V40: AED | W40: 45513407 | X40: =W40/Q40 -> 145.15611 | Y40: =W40/R40 -> 162.41969 | Z40: =W40/S40 -> 213.31043 | AA40: =W40/T40 -> 46253.462 | AB40: YES | AD40: =W40/AC29 -> 0.037476389
B41: Single Asset | C41: Apartments | E41: UAE | F41: Abu Dhabi | G41: Q-Properties | I41: Project A24.2 | K41: REEM HILLS, Town Plaza | L41: 2024 | M41: Pivot | N41: Award | O41: Competitive - Traditional | P41: Fixed Price Lump Sum | Q41: 313548 | R41: 280221 | S41: 213367 | T41: 984 | U41: General Requirements | V41: AED | W41: 118223931 | X41: =W41/Q41 -> 377.0521 | Y41: =W41/R41 -> 421.89533 | Z41: =W41/S41 -> 554.08723 | AA41: =W41/T41 -> 120146.27 | AB41: YES | AD41: =W41/AC29 -> 0.097347273
B42: Single Asset | C42: Apartments | E42: UAE | F42: Dubai | G42: NAKHEEL | I42: Project A24.3 | K42: Como Residences | L42: 2024 | M42: ALEC | N42: Award | O42: Competitive - Traditional | P42: Fixed Price Lump Sum | Q42: 113906 | R42: 108211 | S42: 65631 | T42: 76 | U42: Substructure | V42: AED | W42: 65511236 | X42: =W42/Q42 -> 575.1342 | Y42: =W42/R42 -> 605.40274 | Z42: =W42/S42 -> 998.17519 | AA42: =W42/T42 -> 861989.95 | AB42: YES | AC42: =SUM(W42:W54) -> 1820768104 | AD42: =W42/AC42 -> 0.03598
B43: Single Asset | C43: Apartments | E43: UAE | F43: Dubai | G43: NAKHEEL | I43: Project A24.3 | K43: Como Residences | L43: 2024 | M43: ALEC | N43: Award | O43: Competitive - Traditional | P43: Fixed Price Lump Sum | Q43: 113906 | R43: 108211 | S43: 65631 | T43: 76 | U43: Superstructure | V43: AED | W43: 245734739 | X43: =W43/Q43 -> 2157.3468 | Y43: =W43/R43 -> 2270.885 | Z43: =W43/S43 -> 3744.187 | AA43: =W43/T43 -> 3233351.8 | AB43: YES | AD43: =W43/AC42 -> 0.13496213
B44: Single Asset | C44: Apartments | E44: UAE | F44: Dubai | G44: NAKHEEL | I44: Project A24.3 | K44: Como Residences | L44: 2024 | M44: ALEC | N44: Award | O44: Competitive - Traditional | P44: Fixed Price Lump Sum | Q44: 113906 | R44: 108211 | S44: 65631 | T44: 76 | U44: Building External Envelope | V44: AED | W44: 297566550 | X44: =W44/Q44 -> 2612.387 | Y44: =W44/R44 -> 2749.8734 | Z44: =W44/S44 -> 4533.9329 | AA44: =W44/T44 -> 3915349.3 | AB44: YES | AD44: =W44/AC42 -> 0.16342913
B45: Single Asset | C45: Apartments | E45: UAE | F45: Dubai | G45: NAKHEEL | I45: Project A24.3 | K45: Como Residences | L45: 2024 | M45: ALEC | N45: Award | O45: Competitive - Traditional | P45: Fixed Price Lump Sum | Q45: 113906 | R45: 108211 | S45: 65631 | T45: 76 | U45: Internal Walls and Doors | V45: AED | W45: 77604402 | X45: =W45/Q45 -> 681.30214 | Y45: =W45/R45 -> 717.15816 | Z45: =W45/S45 -> 1182.4352 | AA45: =W45/T45 -> 1021110.6 | AB45: YES | AD45: =W45/AC42 -> 0.042621793
B46: Single Asset | C46: Apartments | E46: UAE | F46: Dubai | G46: NAKHEEL | I46: Project A24.3 | K46: Como Residences | L46: 2024 | M46: ALEC | N46: Award | O46: Competitive - Traditional | P46: Fixed Price Lump Sum | Q46: 113906 | R46: 108211 | S46: 65631 | T46: 76 | U46: Internal Finishes | V46: AED | W46: 226736641 | X46: =W46/Q46 -> 1990.5592 | Y46: =W46/R46 -> 2095.3197 | Z46: =W46/S46 -> 3454.7187 | AA46: =W46/T46 -> 2983376.9 | AB46: YES | AD46: =W46/AC42 -> 0.12452802
B47: Single Asset | C47: Apartments | E47: UAE | F47: Dubai | G47: NAKHEEL | I47: Project A24.3 | K47: Como Residences | L47: 2024 | M47: ALEC | N47: Award | O47: Competitive - Traditional | P47: Fixed Price Lump Sum | Q47: 113906 | R47: 108211 | S47: 65631 | T47: 76 | U47: FF&E | V47: AED | W47: 118189095 | X47: =W47/Q47 -> 1037.602 | Y47: =W47/R47 -> 1092.2096 | Z47: =W47/S47 -> 1800.812 | AA47: =W47/T47 -> 1555119.7 | AB47: YES | AD47: =W47/AC42 -> 0.064911668
B48: Single Asset | C48: Apartments | E48: UAE | F48: Dubai | G48: NAKHEEL | I48: Project A24.3 | K48: Como Residences | L48: 2024 | M48: ALEC | N48: Award | O48: Competitive - Traditional | P48: Fixed Price Lump Sum | Q48: 113906 | R48: 108211 | S48: 65631 | T48: 76 | U48: Sanitary Fittings | V48: AED | W48: 33545811 | X48: =W48/Q48 -> 294.50434 | Y48: =W48/R48 -> 310.00371 | Z48: =W48/S48 -> 511.12753 | AA48: =W48/T48 -> 441392.25 | AB48: YES | AD48: =W48/AC42 -> 0.018423989
B49: Single Asset | C49: Apartments | E49: UAE | F49: Dubai | G49: NAKHEEL | I49: Project A24.3 | K49: Como Residences | L49: 2024 | M49: ALEC | N49: Award | O49: Competitive - Traditional | P49: Fixed Price Lump Sum | Q49: 113906 | R49: 108211 | S49: 65631 | T49: 76 | U49: Services Equipment | V49: AED | W49: 8898048 | X49: =W49/Q49 -> 78.117465 | Y49: =W49/R49 -> 82.228683 | Z49: =W49/S49 -> 135.57691 | AA49: =W49/T49 -> 117079.58 | AB49: YES | AD49: =W49/AC42 -> 0.0048869749
B50: Single Asset | C50: Apartments | E50: UAE | F50: Dubai | G50: NAKHEEL | I50: Project A24.3 | K50: Como Residences | L50: 2024 | M50: ALEC | N50: Award | O50: Competitive - Traditional | P50: Fixed Price Lump Sum | Q50: 113906 | R50: 108211 | S50: 65631 | T50: 76 | U50: Mechanical | V50: AED | W50: 163839288 | X50: =W50/Q50 -> 1438.3728 | Y50: =W50/R50 -> 1514.0724 | Z50: =W50/S50 -> 2496.3704 | AA50: =W50/T50 -> 2155780.1 | AB50: YES | AD50: =W50/AC42 -> 0.089983611
B51: Single Asset | C51: Apartments | E51: UAE | F51: Dubai | G51: NAKHEEL | I51: Project A24.3 | K51: Como Residences | L51: 2024 | M51: ALEC | N51: Award | O51: Competitive - Traditional | P51: Fixed Price Lump Sum | Q51: 113906 | R51: 108211 | S51: 65631 | T51: 76 | U51: Electrical | V51: AED | W51: 148181837 | X51: =W51/Q51 -> 1300.9134 | Y51: =W51/R51 -> 1369.3787 | Z51: =W51/S51 -> 2257.8025 | AA51: =W51/T51 -> 1949761 | AB51: YES | AD51: =W51/AC42 -> 0.081384245
B52: Single Asset | C52: Apartments | E52: UAE | F52: Dubai | G52: NAKHEEL | I52: Project A24.3 | K52: Como Residences | L52: 2024 | M52: ALEC | N52: Award | O52: Competitive - Traditional | P52: Fixed Price Lump Sum | Q52: 113906 | R52: 108211 | S52: 65631 | T52: 76 | U52: Conveying Systems | V52: AED | W52: 33952644 | X52: =W52/Q52 -> 298.07599 | Y52: =W52/R52 -> 313.76333 | Z52: =W52/S52 -> 517.32632 | AA52: =W52/T52 -> 446745.32 | AB52: YES | AD52: =W52/AC42 -> 0.018647429
B53: Single Asset | C53: Apartments | E53: UAE | F53: Dubai | G53: NAKHEEL | I53: Project A24.3 | K53: Como Residences | L53: 2024 | M53: ALEC | N53: Award | O53: Competitive - Traditional | P53: Fixed Price Lump Sum | Q53: 113906 | R53: 108211 | S53: 65631 | T53: 76 | U53: External Works | V53: AED | W53: 115783379 | X53: =W53/Q53 -> 1016.4818 | Y53: =W53/R53 -> 1069.9779 | Z53: =W53/S53 -> 1764.1569 | AA53: =W53/T53 -> 1523465.5 | AB53: YES | AD53: =W53/AC42 -> 0.063590404
B54: Single Asset | C54: Apartments | E54: UAE | F54: Dubai | G54: NAKHEEL | I54: Project A24.3 | K54: Como Residences | L54: 2024 | M54: ALEC | N54: Award | O54: Competitive - Traditional | P54: Fixed Price Lump Sum | Q54: 113906 | R54: 108211 | S54: 65631 | T54: 76 | U54: General Requirements | V54: AED | W54: 285224434 | X54: =W54/Q54 -> 2504.0334 | Y54: =W54/R54 -> 2635.8174 | Z54: =W54/S54 -> 4345.8798 | AA54: =W54/T54 -> 3752953.1 | AB54: YES | AD54: =W54/AC42 -> 0.15665061
A55: NEW | B55: Single Asset | C55: Apartments | E55: UAE | F55: Dubai | G55: TARAF | I55: Project A24.4 | K55: Palm Residences | L55: 2024 | M55: AL ASHRAM | N55: Award | O55: Competitive - Traditional | P55: Fixed Price Lump Sum | Q55: 23646 | R55: 19796 | S55: 10849 | T55: 38 | U55: Substructure | V55: AED | W55: =10088544+13000000 -> 23088544 | X55: =W55/Q55 -> 976.42493 | Y55: =W55/R55 -> 1166.3237 | Z55: =W55/S55 -> 2128.1726 | AA55: =W55/T55 -> 607593.26 | AB55: YES | AC55: =SUM(W55:W67) -> 149314146 | AD55: =W55/AC55 -> 0.15463065
A56: NEW | B56: Single Asset | C56: Apartments | E56: UAE | F56: Dubai | G56: TARAF | I56: Project A24.4 | K56: Palm Residences | L56: 2024 | M56: AL ASHRAM | N56: Award | O56: Competitive - Traditional | P56: Fixed Price Lump Sum | Q56: 23646 | R56: 19796 | S56: 10849 | T56: 38 | U56: Superstructure | V56: AED | W56: 15598171 | X56: =W56/Q56 -> 659.65368 | Y56: =W56/R56 -> 787.9456 | Z56: =W56/S56 -> 1437.752 | AA56: =W56/T56 -> 410478.18 | AB56: YES | AD56: =W56/AC55 -> 0.10446546
A57: NEW | B57: Single Asset | C57: Apartments | E57: UAE | F57: Dubai | G57: TARAF | I57: Project A24.4 | K57: Palm Residences | L57: 2024 | M57: AL ASHRAM | N57: Award | O57: Competitive - Traditional | P57: Fixed Price Lump Sum | Q57: 23646 | R57: 19796 | S57: 10849 | T57: 38 | U57: Building External Envelope | V57: AED | W57: 15833511 | X57: =W57/Q57 -> 669.60632 | Y57: =W57/R57 -> 799.83386 | Z57: =W57/S57 -> 1459.4443 | AA57: =W57/T57 -> 416671.34 | AB57: YES | AD57: =W57/AC55 -> 0.1060416
A58: NEW | B58: Single Asset | C58: Apartments | E58: UAE | F58: Dubai | G58: TARAF | I58: Project A24.4 | K58: Palm Residences | L58: 2024 | M58: AL ASHRAM | N58: Award | O58: Competitive - Traditional | P58: Fixed Price Lump Sum | Q58: 23646 | R58: 19796 | S58: 10849 | T58: 38 | U58: Internal Walls and Doors | V58: AED | W58: 6701885 | X58: =W58/Q58 -> 283.42574 | Y58: =W58/R58 -> 338.54743 | Z58: =W58/S58 -> 617.74219 | AA58: =W58/T58 -> 176365.39 | AB58: YES | AD58: =W58/AC55 -> 0.044884461
A59: NEW | B59: Single Asset | C59: Apartments | E59: UAE | F59: Dubai | G59: TARAF | I59: Project A24.4 | K59: Palm Residences | L59: 2024 | M59: AL ASHRAM | N59: Award | O59: Competitive - Traditional | P59: Fixed Price Lump Sum | Q59: 23646 | R59: 19796 | S59: 10849 | T59: 38 | U59: Internal Finishes | V59: AED | W59: 20746667 | X59: =W59/Q59 -> 877.3859 | Y59: =W59/R59 -> 1048.0232 | Z59: =W59/S59 -> 1912.3115 | AA59: =W59/T59 -> 545964.92 | AB59: YES | AD59: =W59/AC55 -> 0.13894643
A60: NEW | B60: Single Asset | C60: Apartments | E60: UAE | F60: Dubai | G60: TARAF | I60: Project A24.4 | K60: Palm Residences | L60: 2024 | M60: AL ASHRAM | N60: Award | O60: Competitive - Traditional | P60: Fixed Price Lump Sum | Q60: 23646 | R60: 19796 | S60: 10849 | T60: 38 | U60: FF&E | V60: AED | W60: 10065881 | X60: =W60/Q60 -> 425.69065 | Y60: =W60/R60 -> 508.48055 | Z60: =W60/S60 -> 927.81648 | AA60: =W60/T60 -> 264891.61 | AB60: YES | AD60: =W60/AC55 -> 0.067414115
A61: NEW | B61: Single Asset | C61: Apartments | E61: UAE | F61: Dubai | G61: TARAF | I61: Project A24.4 | K61: Palm Residences | L61: 2024 | M61: AL ASHRAM | N61: Award | O61: Competitive - Traditional | P61: Fixed Price Lump Sum | Q61: 23646 | R61: 19796 | S61: 10849 | T61: 38 | U61: Sanitary Fittings | V61: AED | W61: 2524122 | X61: =W61/Q61 -> 106.74626 | Y61: =W61/R61 -> 127.50667 | Z61: =W61/S61 -> 232.65942 | AA61: =W61/T61 -> 66424.263 | AB61: YES | AD61: =W61/AC55 -> 0.016904775
A62: NEW | B62: Single Asset | C62: Apartments | E62: UAE | F62: Dubai | G62: TARAF | I62: Project A24.4 | K62: Palm Residences | L62: 2024 | M62: AL ASHRAM | N62: Award | O62: Competitive - Traditional | P62: Fixed Price Lump Sum | Q62: 23646 | R62: 19796 | S62: 10849 | T62: 38 | U62: Services Equipment | V62: AED | W62: 543045 | X62: =W62/Q62 -> 22.965618 | Y62: =W62/R62 -> 27.432057 | Z62: =W62/S62 -> 50.054844 | AA62: =W62/T62 -> 14290.658 | AB62: YES | AD62: =W62/AC55 -> 0.0036369294
A63: NEW | B63: Single Asset | C63: Apartments | E63: UAE | F63: Dubai | G63: TARAF | I63: Project A24.4 | K63: Palm Residences | L63: 2024 | M63: AL ASHRAM | N63: Award | O63: Competitive - Traditional | P63: Fixed Price Lump Sum | Q63: 23646 | R63: 19796 | S63: 10849 | T63: 38 | U63: Mechanical | V63: AED | W63: 14324357 | X63: =W63/Q63 -> 605.78352 | Y63: =W63/R63 -> 723.59856 | Z63: =W63/S63 -> 1320.3389 | AA63: =W63/T63 -> 376956.76 | AB63: YES | AD63: =W63/AC55 -> 0.09593436
A64: NEW | B64: Single Asset | C64: Apartments | E64: UAE | F64: Dubai | G64: TARAF | I64: Project A24.4 | K64: Palm Residences | L64: 2024 | M64: AL ASHRAM | N64: Award | O64: Competitive - Traditional | P64: Fixed Price Lump Sum | Q64: 23646 | R64: 19796 | S64: 10849 | T64: 38 | U64: Electrical | V64: AED | W64: 12872949 | X64: =W64/Q64 -> 544.40282 | Y64: =W64/R64 -> 650.28031 | Z64: =W64/S64 -> 1186.5563 | AA64: =W64/T64 -> 338761.82 | AB64: YES | AD64: =W64/AC55 -> 0.086213861
A65: NEW | B65: Single Asset | C65: Apartments | E65: UAE | F65: Dubai | G65: TARAF | I65: Project A24.4 | K65: Palm Residences | L65: 2024 | M65: AL ASHRAM | N65: Award | O65: Competitive - Traditional | P65: Fixed Price Lump Sum | Q65: 23646 | R65: 19796 | S65: 10849 | T65: 38 | U65: Conveying Systems | V65: AED | W65: 1943099 | X65: =W65/Q65 -> 82.174533 | Y65: =W65/R65 -> 98.156143 | Z65: =W65/S65 -> 179.10397 | AA65: =W65/T65 -> 51134.184 | AB65: YES | AD65: =W65/AC55 -> 0.013013496
A66: NEW | B66: Single Asset | C66: Apartments | E66: UAE | F66: Dubai | G66: TARAF | I66: Project A24.4 | K66: Palm Residences | L66: 2024 | M66: AL ASHRAM | N66: Award | O66: Competitive - Traditional | P66: Fixed Price Lump Sum | Q66: 23646 | R66: 19796 | S66: 10849 | T66: 38 | U66: External Works | V66: AED | W66: =8664934+110606 -> 8775540 | X66: =W66/Q66 -> 371.12154 | Y66: =W66/R66 -> 443.29865 | Z66: =W66/S66 -> 808.88008 | AA66: =W66/T66 -> 230935.26 | AB66: YES | AD66: =W66/AC55 -> 0.058772328
A67: NEW | B67: Single Asset | C67: Apartments | E67: UAE | F67: Dubai | G67: TARAF | I67: Project A24.4 | K67: Palm Residences | L67: 2024 | M67: AL ASHRAM | N67: Award | O67: Competitive - Traditional | P67: Fixed Price Lump Sum | Q67: 23646 | R67: 19796 | S67: 10849 | T67: 38 | U67: General Requirements | V67: AED | W67: 16296375 | X67: =W67/Q67 -> 689.18105 | Y67: =W67/R67 -> 823.21555 | Z67: =W67/S67 -> 1502.1085 | AA67: =W67/T67 -> 428851.97 | AB67: YES | AD67: =W67/AC55 -> 0.10914153
A68: NEW | B68: Single Asset | C68: Apartments | E68: UAE | F68: Abu Dhabi | G68: NINE YARDS | I68: Project A24.5 | K68: Sea La vie, Yas Towers | L68: 2024 | M68: ZUBLIN | N68: Award | O68: Competitive - Traditional | P68: Fixed Price Lump Sum | Q68: 190388 | R68: 177346 | S68: 112679 | T68: 668 | U68: Substructure | V68: AED | W68: 77484866 | X68: =W68/Q68 -> 406.98398 | Y68: =W68/R68 -> 436.91352 | Z68: =W68/S68 -> 687.66022 | AA68: =W68/T68 -> 115995.31 | AB68: YES | AC68: =SUM(W68:W80) -> 1130144897 | AD68: =W68/AC68 -> 0.068561886
A69: NEW | B69: Single Asset | C69: Apartments | E69: UAE | F69: Abu Dhabi | G69: NINE YARDS | I69: Project A24.5 | K69: Sea La vie, Yas Towers | L69: 2024 | M69: ZUBLIN | N69: Award | O69: Competitive - Traditional | P69: Fixed Price Lump Sum | Q69: 190388 | R69: 177346 | S69: 112679 | T69: 668 | U69: Superstructure | V69: AED | W69: 159733721 | X69: =W69/Q69 -> 838.99049 | Y69: =W69/R69 -> 900.68973 | Z69: =W69/S69 -> 1417.5997 | AA69: =W69/T69 -> 239122.34 | AB69: YES | AD69: =W69/AC68 -> 0.14133915
A70: NEW | B70: Single Asset | C70: Apartments | E70: UAE | F70: Abu Dhabi | G70: NINE YARDS | I70: Project A24.5 | K70: Sea La vie, Yas Towers | L70: 2024 | M70: ZUBLIN | N70: Award | O70: Competitive - Traditional | P70: Fixed Price Lump Sum | Q70: 190388 | R70: 177346 | S70: 112679 | T70: 668 | U70: Building External Envelope | V70: AED | W70: 1.3613124e+08 | X70: =W70/Q70 -> 715.02006 | Y70: =W70/R70 -> 767.60253 | Z70: =W70/S70 -> 1208.1332 | AA70: =W70/T70 -> 203789.28 | AB70: YES | AD70: =W70/AC68 -> 0.12045468
A71: NEW | B71: Single Asset | C71: Apartments | E71: UAE | F71: Abu Dhabi | G71: NINE YARDS | I71: Project A24.5 | K71: Sea La vie, Yas Towers | L71: 2024 | M71: ZUBLIN | N71: Award | O71: Competitive - Traditional | P71: Fixed Price Lump Sum | Q71: 190388 | R71: 177346 | S71: 112679 | T71: 668 | U71: Internal Walls and Doors | V71: AED | W71: 43023987 | X71: =W71/Q71 -> 225.98056 | Y71: =W71/R71 -> 242.59914 | Z71: =W71/S71 -> 381.82791 | AA71: =W71/T71 -> 64407.167 | AB71: YES | AD71: =W71/AC68 -> 0.038069444
A72: NEW | B72: Single Asset | C72: Apartments | E72: UAE | F72: Abu Dhabi | G72: NINE YARDS | I72: Project A24.5 | K72: Sea La vie, Yas Towers | L72: 2024 | M72: ZUBLIN | N72: Award | O72: Competitive - Traditional | P72: Fixed Price Lump Sum | Q72: 190388 | R72: 177346 | S72: 112679 | T72: 668 | U72: Internal Finishes | V72: AED | W72: 126786550 | X72: =W72/Q72 -> 665.93772 | Y72: =W72/R72 -> 714.91068 | Z72: =W72/S72 -> 1125.2012 | AA72: =W72/T72 -> 189800.22 | AB72: YES | AD72: =W72/AC68 -> 0.1121861
A73: NEW | B73: Single Asset | C73: Apartments | E73: UAE | F73: Abu Dhabi | G73: NINE YARDS | I73: Project A24.5 | K73: Sea La vie, Yas Towers | L73: 2024 | M73: ZUBLIN | N73: Award | O73: Competitive - Traditional | P73: Fixed Price Lump Sum | Q73: 190388 | R73: 177346 | S73: 112679 | T73: 668 | U73: FF&E | V73: AED | W73: 61382707 | X73: =W73/Q73 -> 322.40849 | Y73: =W73/R73 -> 346.11836 | Z73: =W73/S73 -> 544.7573 | AA73: =W73/T73 -> 91890.28 | AB73: YES | AD73: =W73/AC68 -> 0.054314015
A74: NEW | B74: Single Asset | C74: Apartments | E74: UAE | F74: Abu Dhabi | G74: NINE YARDS | I74: Project A24.5 | K74: Sea La vie, Yas Towers | L74: 2024 | M74: ZUBLIN | N74: Award | O74: Competitive - Traditional | P74: Fixed Price Lump Sum | Q74: 190388 | R74: 177346 | S74: 112679 | T74: 668 | U74: Sanitary Fittings | V74: AED | W74: 38808124 | X74: =W74/Q74 -> 203.83703 | Y74: =W74/R74 -> 218.82717 | Z74: =W74/S74 -> 344.4131 | AA74: =W74/T74 -> 58095.994 | AB74: YES | AD74: =W74/AC68 -> 0.034339069
A75: NEW | B75: Single Asset | C75: Apartments | E75: UAE | F75: Abu Dhabi | G75: NINE YARDS | I75: Project A24.5 | K75: Sea La vie, Yas Towers | L75: 2024 | M75: ZUBLIN | N75: Award | O75: Competitive - Traditional | P75: Fixed Price Lump Sum | Q75: 190388 | R75: 177346 | S75: 112679 | T75: 668 | U75: Services Equipment | V75: AED | W75: 1067000 | X75: =W75/Q75 -> 5.6043448 | Y75: =W75/R75 -> 6.0164875 | Z75: =W75/S75 -> 9.4693776 | AA75: =W75/T75 -> 1597.3054 | AB75: YES | AD75: =W75/AC68 -> 0.00094412672
A76: NEW | B76: Single Asset | C76: Apartments | E76: UAE | F76: Abu Dhabi | G76: NINE YARDS | I76: Project A24.5 | K76: Sea La vie, Yas Towers | L76: 2024 | M76: ZUBLIN | N76: Award | O76: Competitive - Traditional | P76: Fixed Price Lump Sum | Q76: 190388 | R76: 177346 | S76: 112679 | T76: 668 | U76: Mechanical | V76: AED | W76: 1.4797507e+08 | X76: =W76/Q76 -> 777.22899 | Y76: =W76/R76 -> 834.38631 | Z76: =W76/S76 -> 1313.2445 | AA76: =W76/T76 -> 221519.57 | AB76: YES | AD76: =W76/AC68 -> 0.1309346
A77: NEW | B77: Single Asset | C77: Apartments | E77: UAE | F77: Abu Dhabi | G77: NINE YARDS | I77: Project A24.5 | K77: Sea La vie, Yas Towers | L77: 2024 | M77: ZUBLIN | N77: Award | O77: Competitive - Traditional | P77: Fixed Price Lump Sum | Q77: 190388 | R77: 177346 | S77: 112679 | T77: 668 | U77: Electrical | V77: AED | W77: 1.8266742e+08 | X77: =W77/Q77 -> 959.44816 | Y77: =W77/R77 -> 1030.0058 | Z77: =W77/S77 -> 1621.131 | AA77: =W77/T77 -> 273454.22 | AB77: YES | AD77: =W77/AC68 -> 0.16163186
A78: NEW | B78: Single Asset | C78: Apartments | E78: UAE | F78: Abu Dhabi | G78: NINE YARDS | I78: Project A24.5 | K78: Sea La vie, Yas Towers | L78: 2024 | M78: ZUBLIN | N78: Award | O78: Competitive - Traditional | P78: Fixed Price Lump Sum | Q78: 190388 | R78: 177346 | S78: 112679 | T78: 668 | U78: Conveying Systems | V78: AED | W78: 6389192 | X78: =W78/Q78 -> 33.558796 | Y78: =W78/R78 -> 36.026705 | Z78: =W78/S78 -> 56.702598 | AA78: =W78/T78 -> 9564.6587 | AB78: YES | AD78: =W78/AC68 -> 0.0056534273
A79: NEW | B79: Single Asset | C79: Apartments | E79: UAE | F79: Abu Dhabi | G79: NINE YARDS | I79: Project A24.5 | K79: Sea La vie, Yas Towers | L79: 2024 | M79: ZUBLIN | N79: Award | O79: Competitive - Traditional | P79: Fixed Price Lump Sum | Q79: 190388 | R79: 177346 | S79: 112679 | T79: 668 | U79: External Works | V79: AED | W79: 32986364 | X79: =W79/Q79 -> 173.25863 | Y79: =W79/R79 -> 186.00005 | Z79: =W79/S79 -> 292.74633 | AA79: =W79/T79 -> 49380.784 | AB79: YES | AD79: =W79/AC68 -> 0.02918773
A80: NEW | B80: Single Asset | C80: Apartments | E80: UAE | F80: Abu Dhabi | G80: NINE YARDS | I80: Project A24.5 | K80: Sea La vie, Yas Towers | L80: 2024 | M80: ZUBLIN | N80: Award | O80: Competitive - Traditional | P80: Fixed Price Lump Sum | Q80: 190388 | R80: 177346 | S80: 112679 | T80: 668 | U80: General Requirements | V80: AED | W80: 1.1570866e+08 | X80: =W80/Q80 -> 607.75184 | Y80: =W80/R80 -> 652.44582 | Z80: =W80/S80 -> 1026.8875 | AA80: =W80/T80 -> 173216.55 | AB80: YES | AD80: =W80/AC68 -> 0.10238391
A81: NEW | B81: Single Asset | C81: Apartments | E81: UAE | F81: Dubai | G81: Northacre | I81: Project A24.6 | K81: Ocean House | L81: 2024 | M81: BHATIA | N81: Award | O81: Competitive - Traditional | P81: Fixed Price Lump Sum | Q81: 43888 | R81: 34725 | S81: 25999 | T81: 88 | U81: Substructure | V81: AED | W81: =15800000+20338133 -> 36138133 | X81: =W81/Q81 -> 823.41718 | Y81: =W81/R81 -> 1040.695 | Z81: =W81/S81 -> 1389.9817 | AA81: =W81/T81 -> 410660.6 | AB81: YES | AC81: =SUM(W81:W93) -> 3.98467e+08 | AD81: =W81/AC81 -> 0.090692913
A82: NEW | B82: Single Asset | C82: Apartments | E82: UAE | F82: Dubai | G82: Northacre | I82: Project A24.6 | K82: Ocean House | L82: 2024 | M82: BHATIA | N82: Award | O82: Competitive - Traditional | P82: Fixed Price Lump Sum | Q82: 43888 | R82: 34725 | S82: 25999 | T82: 88 | U82: Superstructure | V82: AED | W82: 38386645 | X82: =W82/Q82 -> 874.65013 | Y82: =W82/R82 -> 1105.4469 | Z82: =W82/S82 -> 1476.4662 | AA82: =W82/T82 -> 436211.88 | AB82: YES | AD82: =W82/AC81 -> 0.096335819
A83: NEW | B83: Single Asset | C83: Apartments | E83: UAE | F83: Dubai | G83: Northacre | I83: Project A24.6 | K83: Ocean House | L83: 2024 | M83: BHATIA | N83: Award | O83: Competitive - Traditional | P83: Fixed Price Lump Sum | Q83: 43888 | R83: 34725 | S83: 25999 | T83: 88 | U83: Building External Envelope | V83: AED | W83: 55126103 | X83: =W83/Q83 -> 1256.0632 | Y83: =W83/R83 -> 1587.5048 | Z83: =W83/S83 -> 2120.3163 | AA83: =W83/T83 -> 626432.99 | AB83: YES | AD83: =W83/AC81 -> 0.13834547
A84: NEW | B84: Single Asset | C84: Apartments | E84: UAE | F84: Dubai | G84: Northacre | I84: Project A24.6 | K84: Ocean House | L84: 2024 | M84: BHATIA | N84: Award | O84: Competitive - Traditional | P84: Fixed Price Lump Sum | Q84: 43888 | R84: 34725 | S84: 25999 | T84: 88 | U84: Internal Walls and Doors | V84: AED | W84: 17936613 | X84: =W84/Q84 -> 408.6906 | Y84: =W84/R84 -> 516.53313 | Z84: =W84/S84 -> 689.89627 | AA84: =W84/T84 -> 203825.15 | AB84: YES | AD84: =W84/AC81 -> 0.045014049
A85: NEW | B85: Single Asset | C85: Apartments | E85: UAE | F85: Dubai | G85: Northacre | I85: Project A24.6 | K85: Ocean House | L85: 2024 | M85: BHATIA | N85: Award | O85: Competitive - Traditional | P85: Fixed Price Lump Sum | Q85: 43888 | R85: 34725 | S85: 25999 | T85: 88 | U85: Internal Finishes | V85: AED | W85: 56538177 | X85: =W85/Q85 -> 1288.2377 | Y85: =W85/R85 -> 1628.1692 | Z85: =W85/S85 -> 2174.6289 | AA85: =W85/T85 -> 642479.28 | AB85: YES | AD85: =W85/AC81 -> 0.14188923
A86: NEW | B86: Single Asset | C86: Apartments | E86: UAE | F86: Dubai | G86: Northacre | I86: Project A24.6 | K86: Ocean House | L86: 2024 | M86: BHATIA | N86: Award | O86: Competitive - Traditional | P86: Fixed Price Lump Sum | Q86: 43888 | R86: 34725 | S86: 25999 | T86: 88 | U86: FF&E | V86: AED | W86: 38176597 | X86: =W86/Q86 -> 869.86413 | Y86: =W86/R86 -> 1099.398 | Z86: =W86/S86 -> 1468.3871 | AA86: =W86/T86 -> 433824.97 | AB86: YES | AD86: =W86/AC81 -> 0.095808679
A87: NEW | B87: Single Asset | C87: Apartments | E87: UAE | F87: Dubai | G87: Northacre | I87: Project A24.6 | K87: Ocean House | L87: 2024 | M87: BHATIA | N87: Award | O87: Competitive - Traditional | P87: Fixed Price Lump Sum | Q87: 43888 | R87: 34725 | S87: 25999 | T87: 88 | U87: Sanitary Fittings | V87: AED | W87: 7066842 | X87: =W87/Q87 -> 161.01991 | Y87: =W87/R87 -> 203.50877 | Z87: =W87/S87 -> 271.81207 | AA87: =W87/T87 -> 80305.023 | AB87: YES | AD87: =W87/AC81 -> 0.017735075
A88: NEW | B88: Single Asset | C88: Apartments | E88: UAE | F88: Dubai | G88: Northacre | I88: Project A24.6 | K88: Ocean House | L88: 2024 | M88: BHATIA | N88: Award | O88: Competitive - Traditional | P88: Fixed Price Lump Sum | Q88: 43888 | R88: 34725 | S88: 25999 | T88: 88 | U88: Services Equipment | V88: AED | W88: 592215 | X88: =W88/Q88 -> 13.49378 | Y88: =W88/R88 -> 17.054428 | Z88: =W88/S88 -> 22.778376 | AA88: =W88/T88 -> 6729.7159 | AB88: YES | AD88: =W88/AC81 -> 0.0014862335
A89: NEW | B89: Single Asset | C89: Apartments | E89: UAE | F89: Dubai | G89: Northacre | I89: Project A24.6 | K89: Ocean House | L89: 2024 | M89: BHATIA | N89: Award | O89: Competitive - Traditional | P89: Fixed Price Lump Sum | Q89: 43888 | R89: 34725 | S89: 25999 | T89: 88 | U89: Mechanical | V89: AED | W89: 30144367 | X89: =W89/Q89 -> 686.84759 | Y89: =W89/R89 -> 868.08832 | Z89: =W89/S89 -> 1159.4433 | AA89: =W89/T89 -> 342549.62 | AB89: YES | AD89: =W89/AC81 -> 0.075650849
A90: NEW | B90: Single Asset | C90: Apartments | E90: UAE | F90: Dubai | G90: Northacre | I90: Project A24.6 | K90: Ocean House | L90: 2024 | M90: BHATIA | N90: Award | O90: Competitive - Traditional | P90: Fixed Price Lump Sum | Q90: 43888 | R90: 34725 | S90: 25999 | T90: 88 | U90: Electrical | V90: AED | W90: 36985780 | X90: =W90/Q90 -> 842.73104 | Y90: =W90/R90 -> 1065.1053 | Z90: =W90/S90 -> 1422.5847 | AA90: =W90/T90 -> 420292.95 | AB90: YES | AD90: =W90/AC81 -> 0.092820183
A91: NEW | B91: Single Asset | C91: Apartments | E91: UAE | F91: Dubai | G91: Northacre | I91: Project A24.6 | K91: Ocean House | L91: 2024 | M91: BHATIA | N91: Award | O91: Competitive - Traditional | P91: Fixed Price Lump Sum | Q91: 43888 | R91: 34725 | S91: 25999 | T91: 88 | U91: Conveying Systems | V91: AED | W91: 2367784 | X91: =W91/Q91 -> 53.950602 | Y91: =W91/R91 -> 68.186724 | Z91: =W91/S91 -> 91.072118 | AA91: =W91/T91 -> 26906.636 | AB91: YES | AD91: =W91/AC81 -> 0.0059422336
A92: NEW | B92: Single Asset | C92: Apartments | E92: UAE | F92: Dubai | G92: Northacre | I92: Project A24.6 | K92: Ocean House | L92: 2024 | M92: BHATIA | N92: Award | O92: Competitive - Traditional | P92: Fixed Price Lump Sum | Q92: 43888 | R92: 34725 | S92: 25999 | T92: 88 | U92: External Works | V92: AED | W92: =33585827+48917 -> 33634744 | X92: =W92/Q92 -> 766.37678 | Y92: =W92/R92 -> 968.60314 | Z92: =W92/S92 -> 1293.6938 | AA92: =W92/T92 -> 382213 | AB92: YES | AD92: =W92/AC81 -> 0.084410363
A93: NEW | B93: Single Asset | C93: Apartments | E93: UAE | F93: Dubai | G93: Northacre | I93: Project A24.6 | K93: Ocean House | L93: 2024 | M93: BHATIA | N93: Award | O93: Competitive - Traditional | P93: Fixed Price Lump Sum | Q93: 43888 | R93: 34725 | S93: 25999 | T93: 88 | U93: General Requirements | V93: AED | W93: 45373000 | X93: =W93/Q93 -> 1033.8361 | Y93: =W93/R93 -> 1306.6379 | Z93: =W93/S93 -> 1745.1825 | AA93: =W93/T93 -> 515602.27 | AB93: YES | AD93: =W93/AC81 -> 0.1138689
B94: Single Asset | C94: Hospitality | E94: UAE | F94: Dubai | G94: Emaar | I94: Project H15.1 | K94: The Address - Sky View | L94: 2015 | M94: ACC | N94: Award | O94: Competitive - Traditional | P94: Fixed Price Lump Sum | Q94: 260111 | R94: 249889 | S94: 163996 | T94: 731 | U94: Substructure | V94: AED | W94: 172621941 | X94: =W94/Q94 -> 663.64722 | Y94: =W94/R94 -> 690.79448 | Z94: =W94/S94 -> 1052.5985 | AA94: =W94/T94 -> 236144.93 | AB94: YES | AC94: =SUM(W94:W106) -> 2263089101 | AD94: =W94/AC94 -> 0.07627713
B95: Single Asset | C95: Hospitality | E95: UAE | F95: Dubai | G95: Emaar | I95: Project H15.1 | K95: The Address - Sky View | L95: 2015 | M95: ACC | N95: Award | O95: Competitive - Traditional | P95: Fixed Price Lump Sum | Q95: 260111 | R95: 249889 | S95: 163996 | T95: 731 | U95: Superstructure | V95: AED | W95: 380532434 | X95: =W95/Q95 -> 1462.9617 | Y95: =W95/R95 -> 1522.8059 | Z95: =W95/S95 -> 2320.3763 | AA95: =W95/T95 -> 520564.21 | AB95: YES | AD95: =W95/AC94 -> 0.16814735
B96: Single Asset | C96: Hospitality | E96: UAE | F96: Dubai | G96: Emaar | I96: Project H15.1 | K96: The Address - Sky View | L96: 2015 | M96: ACC | N96: Award | O96: Competitive - Traditional | P96: Fixed Price Lump Sum | Q96: 260111 | R96: 249889 | S96: 163996 | T96: 731 | U96: Building External Envelope | V96: AED | W96: 258948738 | X96: =W96/Q96 -> 995.53167 | Y96: =W96/R96 -> 1036.255 | Z96: =W96/S96 -> 1578.9942 | AA96: =W96/T96 -> 354239.04 | AB96: YES | AD96: =W96/AC94 -> 0.11442269
B97: Single Asset | C97: Hospitality | E97: UAE | F97: Dubai | G97: Emaar | I97: Project H15.1 | K97: The Address - Sky View | L97: 2015 | M97: ACC | N97: Award | O97: Competitive - Traditional | P97: Fixed Price Lump Sum | Q97: 260111 | R97: 249889 | S97: 163996 | T97: 731 | U97: Internal Walls and Doors | V97: AED | W97: 87253532 | X97: =W97/Q97 -> 335.4473 | Y97: =W97/R97 -> 349.16916 | Z97: =W97/S97 -> 532.04671 | AA97: =W97/T97 -> 119361.88 | AB97: YES | AD97: =W97/AC94 -> 0.038555058
B98: Single Asset | C98: Hospitality | E98: UAE | F98: Dubai | G98: Emaar | I98: Project H15.1 | K98: The Address - Sky View | L98: 2015 | M98: ACC | N98: Award | O98: Competitive - Traditional | P98: Fixed Price Lump Sum | Q98: 260111 | R98: 249889 | S98: 163996 | T98: 731 | U98: Internal Finishes | V98: AED | W98: 229025028 | X98: =W98/Q98 -> 880.48959 | Y98: =W98/R98 -> 916.50704 | Z98: =W98/S98 -> 1396.5281 | AA98: =W98/T98 -> 313303.73 | AB98: YES | AD98: =W98/AC94 -> 0.10120018
B99: Single Asset | C99: Hospitality | E99: UAE | F99: Dubai | G99: Emaar | I99: Project H15.1 | K99: The Address - Sky View | L99: 2015 | M99: ACC | N99: Award | O99: Competitive - Traditional | P99: Fixed Price Lump Sum | Q99: 260111 | R99: 249889 | S99: 163996 | T99: 731 | U99: FF&E | V99: AED | W99: 274374818 | X99: =W99/Q99 -> 1054.8374 | Y99: =W99/R99 -> 1097.9868 | Z99: =W99/S99 -> 1673.058 | AA99: =W99/T99 -> 375341.75 | AB99: YES | AD99: =W99/AC94 -> 0.12123907
B100: Single Asset | C100: Hospitality | E100: UAE | F100: Dubai | G100: Emaar | I100: Project H15.1 | K100: The Address - Sky View | L100: 2015 | M100: ACC | N100: Award | O100: Competitive - Traditional | P100: Fixed Price Lump Sum | Q100: 260111 | R100: 249889 | S100: 163996 | T100: 731 | U100: Sanitary Fittings | V100: AED | W100: 16101294 | X100: =W100/Q100 -> 61.901627 | Y100: =W100/R100 -> 64.433785 | Z100: =W100/S100 -> 98.181017 | AA100: =W100/T100 -> 22026.394 | AB100: YES | AD100: =W100/AC94 -> 0.0071147415
B101: Single Asset | C101: Hospitality | E101: UAE | F101: Dubai | G101: Emaar | I101: Project H15.1 | K101: The Address - Sky View | L101: 2015 | M101: ACC | N101: Award | O101: Competitive - Traditional | P101: Fixed Price Lump Sum | Q101: 260111 | R101: 249889 | S101: 163996 | T101: 731 | U101: Services Equipment | V101: AED | W101: 91821204 | X101: =W101/Q101 -> 353.00777 | Y101: =W101/R101 -> 367.44796 | Z101: =W101/S101 -> 559.89905 | AA101: =W101/T101 -> 125610.4 | AB101: YES | AD101: =W101/AC94 -> 0.040573393
...

Sheet ROSHN Benchmark Data
B1: Asset Lvl 1 (Core Built Assets) | C1: Asset Lvl 1A (Asset Class) | D1: Asset Lvl 1B (Asset Type) | E1: Asset Lvl 2 (Asset Massing) | F1: Asset Lvl 3 (NOT USED) | G1: empty1 | H1: Country | I1: City (Insert Manually) | J1: Developer (Insert Manually) | K1: Alias Lvl 1 (Insert of Required) | L1: Alias Lvl 2 | M1: Project Lvl 1 | N1: Project Lvl 2 | O1: Base Date | P1: Contractor | Q1: Status | R1: Procurement | S1: Contract Type | T1: BUA | U1: GIA | V1: GFA | W1: Keys | X1: NRM Lvl 1 | Y1: Currency | Z1: Total Cost | AA1: Cost/BUA | AB1: Cost/GIA | AC1: Cost/GFA | AD1: Cost/Key | AE1: Chart | AF1: No. of Floors | AG1: Avg Storey Height | AH1: Sustainability Rating (if Known) | AI1: Wall to Floor Ratio
B2: Single Asset | C2: Residential | D2: Single Family | E2: Villa | H2: KSA | I2: Riyadh | J2: ROSHN | K2: SF PROJECT 1 | M2: ROSHN-Sedra | O2: 2023 | Q2: Award | R2: Competitive - Traditional | S2: Fixed Price Lump Sum | V2: =INDEX('[4]3- BENCHMARK - SF'!$D$18:$X$18, MATCH($V$1,'[4]3- BENCHMARK - SF'!$B$18, 0), MATCH($K2,'[4]3- BENCHMARK - SF'!$D$10:$X$10, 0)) -> 332 | X2: Substructure | Y2: SAR | AC2: =INDEX('[4]3- BENCHMARK - SF'!$D$21:$X$33, MATCH($X2,'[4]3- BENCHMARK - SF'!$B$21:$B$33, 0), MATCH($K2,'[4]3- BENCHMARK - SF'!$D$10:$X$10, 0)) -> 193 | AF2: 2-3 Levels | AG2: 5m average
B3: Single Asset | C3: Residential | D3: Single Family | E3: Villa | H3: KSA | I3: Riyadh | J3: ROSHN | K3: SF PROJECT 1 | M3: ROSHN-Sedra | O3: 2023 | Q3: Award | R3: Competitive - Traditional | S3: Fixed Price Lump Sum | V3: =INDEX('[4]3- BENCHMARK - SF'!$D$18:$X$18, MATCH($V$1,'[4]3- BENCHMARK - SF'!$B$18, 0), MATCH($K3,'[4]3- BENCHMARK - SF'!$D$10:$X$10, 0)) -> 332 | X3: Superstructure | Y3: SAR | AC3: =INDEX('[4]3- BENCHMARK - SF'!$D$21:$X$33, MATCH($X3,'[4]3- BENCHMARK - SF'!$B$21:$B$33, 0), MATCH($K3,'[4]3- BENCHMARK - SF'!$D$10:$X$10, 0)) -> 377 | AF3: 2-3 Levels | AG3: 5m average
B4: Single Asset | C4: Residential | D4: Single Family | E4: Villa | H4: KSA | I4: Riyadh | J4: ROSHN | K4: SF PROJECT 1 | M4: ROSHN-Sedra | O4: 2023 | Q4: Award | R4: Competitive - Traditional | S4: Fixed Price Lump Sum | V4: =INDEX('[4]3- BENCHMARK - SF'!$D$18:$X$18, MATCH($V$1,'[4]3- BENCHMARK - SF'!$B$18, 0), MATCH($K4,'[4]3- BENCHMARK - SF'!$D$10:$X$10, 0)) -> 332 | X4: Building External Envelope | Y4: SAR | AC4: =INDEX('[4]3- BENCHMARK - SF'!$D$21:$X$33, MATCH($X4,'[4]3- BENCHMARK - SF'!$B$21:$B$33, 0), MATCH($K4,'[4]3- BENCHMARK - SF'!$D$10:$X$10, 0)) -> 752 | AF4: 2-3 Levels | AG4: 5m average
B5: Single Asset | C5: Residential | D5: Single Family | E5: Villa | H5: KSA | I5: Riyadh | J5: ROSHN | K5: SF PROJECT 1 | M5: ROSHN-Sedra | O5: 2023 | Q5: Award | R5: Competitive - Traditional | S5: Fixed Price Lump Sum | V5: =INDEX('[4]3- BENCHMARK - SF'!$D$18:$X$18, MATCH($V$1,'[4]3- BENCHMARK - SF'!$B$18, 0), MATCH($K5,'[4]3- BENCHMARK - SF'!$D$10:$X$10, 0)) -> 332 | X5: Internal Walls and Doors | Y5: SAR | AC5: =INDEX('[4]3- BENCHMARK - SF'!$D$21:$X$33, MATCH($X5,'[4]3- BENCHMARK - SF'!$B$21:$B$33, 0), MATCH($K5,'[4]3- BENCHMARK - SF'!$D$10:$X$10, 0)) -> 250 | AF5: 2-3 Levels | AG5: 5m average
B6: Single Asset | C6: Residential | D6: Single Family | E6: Villa | H6: KSA | I6: Riyadh | J6: ROSHN | K6: SF PROJECT 1 | M6: ROSHN-Sedra | O6: 2023 | Q6: Award | R6: Competitive - Traditional | S6: Fixed Price Lump Sum | V6: =INDEX('[4]3- BENCHMARK - SF'!$D$18:$X$18, MATCH($V$1,'[4]3- BENCHMARK - SF'!$B$18, 0), MATCH($K6,'[4]3- BENCHMARK - SF'!$D$10:$X$10, 0)) -> 332 | X6: Internal Finishes | Y6: SAR | AC6: =INDEX('[4]3- BENCHMARK - SF'!$D$21:$X$33, MATCH($X6,'[4]3- BENCHMARK - SF'!$B$21:$B$33, 0), MATCH($K6,'[4]3- BENCHMARK - SF'!$D$10:$X$10, 0)) -> 133 | AF6: 2-3 Levels | AG6: 5m average
B7: Single Asset | C7: Residential | D7: Single Family | E7: Villa | H7: KSA | I7: Riyadh | J7: ROSHN | K7: SF PROJECT 1 | M7: ROSHN-Sedra | O7: 2023 | Q7: Award | R7: Competitive - Traditional | S7: Fixed Price Lump Sum | V7: =INDEX('[4]3- BENCHMARK - SF'!$D$18:$X$18, MATCH($V$1,'[4]3- BENCHMARK - SF'!$B$18, 0), MATCH($K7,'[4]3- BENCHMARK - SF'!$D$10:$X$10, 0)) -> 332 | X7: FF&E | Y7: SAR | AC7: =INDEX('[4]3- BENCHMARK - SF'!$D$21:$X$33, MATCH($X7,'[4]3- BENCHMARK - SF'!$B$21:$B$33, 0), MATCH($K7,'[4]3- BENCHMARK - SF'!$D$10:$X$10, 0)) -> 88 | AF7: 2-3 Levels | AG7: 5m average
B8: Single Asset | C8: Residential | D8: Single Family | E8: Villa | H8: KSA | I8: Riyadh | J8: ROSHN | K8: SF PROJECT 1 | M8: ROSHN-Sedra | O8: 2023 | Q8: Award | R8: Competitive - Traditional | S8: Fixed Price Lump Sum | V8: =INDEX('[4]3- BENCHMARK - SF'!$D$18:$X$18, MATCH($V$1,'[4]3- BENCHMARK - SF'!$B$18, 0), MATCH($K8,'[4]3- BENCHMARK - SF'!$D$10:$X$10, 0)) -> 332 | X8: Sanitary Fittings | Y8: SAR | AC8: =INDEX('[4]3- BENCHMARK - SF'!$D$21:$X$33, MATCH($X8,'[4]3- BENCHMARK - SF'!$B$21:$B$33, 0), MATCH($K8,'[4]3- BENCHMARK - SF'!$D$10:$X$10, 0)) -> 57 | AF8: 2-3 Levels | AG8: 5m average
B9: Single Asset | C9: Residential | D9: Single Family | E9: Villa | H9: KSA | I9: Riyadh | J9: ROSHN | K9: SF PROJECT 1 | M9: ROSHN-Sedra | O9: 2023 | Q9: Award | R9: Competitive - Traditional | S9: Fixed Price Lump Sum | V9: =INDEX('[4]3- BENCHMARK - SF'!$D$18:$X$18, MATCH($V$1,'[4]3- BENCHMARK - SF'!$B$18, 0), MATCH($K9,'[4]3- BENCHMARK - SF'!$D$10:$X$10, 0)) -> 332 | X9: Services Equipment | Y9: SAR | AC9: =INDEX('[4]3- BENCHMARK - SF'!$D$21:$X$33, MATCH($X9,'[4]3- BENCHMARK - SF'!$B$21:$B$33, 0), MATCH($K9,'[4]3- BENCHMARK - SF'!$D$10:$X$10, 0)) -> 0 | AF9: 2-3 Levels | AG9: 5m average
B10: Single Asset | C10: Residential | D10: Single Family | E10: Villa | H10: KSA | I10: Riyadh | J10: ROSHN | K10: SF PROJECT 1 | M10: ROSHN-Sedra | O10: 2023 | Q10: Award | R10: Competitive - Traditional | S10: Fixed Price Lump Sum | V10: =INDEX('[4]3- BENCHMARK - SF'!$D$18:$X$18, MATCH($V$1,'[4]3- BENCHMARK - SF'!$B$18, 0), MATCH($K10,'[4]3- BENCHMARK - SF'!$D$10:$X$10, 0)) -> 332 | X10: Mechanical | Y10: SAR | AC10: =INDEX('[4]3- BENCHMARK - SF'!$D$21:$X$33, MATCH($X10,'[4]3- BENCHMARK - SF'!$B$21:$B$33, 0), MATCH($K10,'[4]3- BENCHMARK - SF'!$D$10:$X$10, 0)) -> 476 | AF10: 2-3 Levels | AG10: 5m average
B11: Single Asset | C11: Residential | D11: Single Family | E11: Villa | H11: KSA | I11: Riyadh | J11: ROSHN | K11: SF PROJECT 1 | M11: ROSHN-Sedra | O11: 2023 | Q11: Award | R11: Competitive - Traditional | S11: Fixed Price Lump Sum | V11: =INDEX('[4]3- BENCHMARK - SF'!$D$18:$X$18, MATCH($V$1,'[4]3- BENCHMARK - SF'!$B$18, 0), MATCH($K11,'[4]3- BENCHMARK - SF'!$D$10:$X$10, 0)) -> 332 | X11: Electrical | Y11: SAR | AC11: =INDEX('[4]3- BENCHMARK - SF'!$D$21:$X$33, MATCH($X11,'[4]3- BENCHMARK - SF'!$B$21:$B$33, 0), MATCH($K11,'[4]3- BENCHMARK - SF'!$D$10:$X$10, 0)) -> 400 | AF11: 2-3 Levels | AG11: 5m average
B12: Single Asset | C12: Residential | D12: Single Family | E12: Villa | H12: KSA | I12: Riyadh | J12: ROSHN | K12: SF PROJECT 1 | M12: ROSHN-Sedra | O12: 2023 | Q12: Award | R12: Competitive - Traditional | S12: Fixed Price Lump Sum | V12: =INDEX('[4]3- BENCHMARK - SF'!$D$18:$X$18, MATCH($V$1,'[4]3- BENCHMARK - SF'!$B$18, 0), MATCH($K12,'[4]3- BENCHMARK - SF'!$D$10:$X$10, 0)) -> 332 | X12: Conveying Systems | Y12: SAR | AC12: =INDEX('[4]3- BENCHMARK - SF'!$D$21:$X$33, MATCH($X12,'[4]3- BENCHMARK - SF'!$B$21:$B$33, 0), MATCH($K12,'[4]3- BENCHMARK - SF'!$D$10:$X$10, 0)) -> 0 | AF12: 2-3 Levels | AG12: 5m average
B13: Single Asset | C13: Residential | D13: Single Family | E13: Villa | H13: KSA | I13: Riyadh | J13: ROSHN | K13: SF PROJECT 1 | M13: ROSHN-Sedra | O13: 2023 | Q13: Award | R13: Competitive - Traditional | S13: Fixed Price Lump Sum | V13: =INDEX('[4]3- BENCHMARK - SF'!$D$18:$X$18, MATCH($V$1,'[4]3- BENCHMARK - SF'!$B$18, 0), MATCH($K13,'[4]3- BENCHMARK - SF'!$D$10:$X$10, 0)) -> 332 | X13: External Works | Y13: SAR | AC13: =INDEX('[4]3- BENCHMARK - SF'!$D$21:$X$33, MATCH($X13,'[4]3- BENCHMARK - SF'!$B$21:$B$33, 0), MATCH($K13,'[4]3- BENCHMARK - SF'!$D$10:$X$10, 0)) -> 209 | AF13: 2-3 Levels | AG13: 5m average
... B157: Single Asset | C157: Residential | D157: Single Family | E157: Townhouse | H157: KSA | I157: Jeddah | J157: Developer01 | K157: SF PROJECT 11 | M157: FJ Project01 | O157: 2022 | Q157: Award | R157: Competitive - Traditional | S157: Fixed Price Lump Sum | V157: =INDEX('[4]3- BENCHMARK - SF'!$D$18:$X$18, MATCH($V$1,'[4]3- BENCHMARK - SF'!$B$18, 0), MATCH($K157,'[4]3- BENCHMARK - SF'!$D$10:$X$10, 0)) -> 280 | X157: General Requirements | Y157: SAR | AC157: =INDEX('[4]3- BENCHMARK - SF'!$D$21:$X$33, MATCH($X157,'[4]3- BENCHMARK - SF'!$B$21:$B$33, 0), MATCH($K157,'[4]3- BENCHMARK - SF'!$D$10:$X$10, 0)) -> 0 | AF157: 2-3 Levels | AG157: 5m average
B158: Single Asset | C158: Residential | D158: Multi Family | E158: High Rise | H158: KSA | I158: Jeddah | J158: Developer06 | K158: MF PROJECT 1 | M158: E Project01 | O158: 2019 | Q158: Award | R158: Competitive - Traditional | S158: Fixed Price Lump Sum | V158: =INDEX('[5]3.0 BENCHMARK'!$D$17:$N$17, MATCH($V$1,'[5]3.0 BENCHMARK'!$B$17, 0), MATCH($K158,'[5]3.0 BENCHMARK'!$D$9:$N$9, 0)) -> 68339.32 | X158: Substructure | Y158: SAR | AC158: =INDEX('[5]3.0 BENCHMARK'!$D$20:$N$32, MATCH($X158,'[5]3.0 BENCHMARK'!$B$20:$B$32, 0), MATCH($K158,'[5]3.0 BENCHMARK'!$D$9:$N$9, 0)) -> 373 | AF158: 20 Levels | AG158: 5.5m average
B159: Single Asset | C159: Residential | D159: Multi Family | E159: High Rise | H159: KSA | I159: Jeddah | J159: Developer06 | K159: MF PROJECT 1 | M159: E Project01 | O159: 2019 | Q159: Award | R159: Competitive - Traditional | S159: Fixed Price Lump Sum | V159: =INDEX('[5]3.0 BENCHMARK'!$D$17:$N$17, MATCH($V$1,'[5]3.0 BENCHMARK'!$B$17, 0), MATCH($K159,'[5]3.0 BENCHMARK'!$D$9:$N$9, 0)) -> 68339.32 | X159: Superstructure | Y159: SAR | AC159: =INDEX('[5]3.0 BENCHMARK'!$D$20:$N$32, MATCH($X159,'[5]3.0 BENCHMARK'!$B$20:$B$32, 0), MATCH($K159,'[5]3.0 BENCHMARK'!$D$9:$N$9, 0)) -> 892 | AF159: 20 Levels | AG159: 5.5m average
B160: Single Asset | C160: Residential | D160: Multi Family | E160: High Rise | H160: KSA | I160: Jeddah | J160: Developer06 | K160: MF PROJECT 1 | M160: E Project01 | O160: 2019 | Q160: Award | R160: Competitive - Traditional | S160: Fixed Price Lump Sum | V160: =INDEX('[5]3.0 BENCHMARK'!$D$17:$N$17, MATCH($V$1,'[5]3.0 BENCHMARK'!$B$17, 0), MATCH($K160,'[5]3.0 BENCHMARK'!$D$9:$N$9, 0)) -> 68339.32 | X160: Building External Envelope | Y160: SAR | AC160: =INDEX('[5]3.0 BENCHMARK'!$D$20:$N$32, MATCH($X160,'[5]3.0 BENCHMARK'!$B$20:$B$32, 0), MATCH($K160,'[5]3.0 BENCHMARK'!$D$9:$N$9, 0)) -> 409 | AF160: 20 Levels | AG160: 5.5m average
B161: Single Asset | C161: Residential | D161: Multi Family | E161: High Rise | H161: KSA | I161: Jeddah | J161: Developer06 | K161: MF PROJECT 1 | M161: E Project01 | O161: 2019 | Q161: Award | R161: Competitive - Traditional | S161: Fixed Price Lump Sum | V161: =INDEX('[5]3.0 BENCHMARK'!$D$17:$N$17, MATCH($V$1,'[5]3.0 BENCHMARK'!$B$17, 0), MATCH($K161,'[5]3.0 BENCHMARK'!$D$9:$N$9, 0)) -> 68339.32 | X161: Internal Walls and Doors | Y161: SAR | AC161: =INDEX('[5]3.0 BENCHMARK'!$D$20:$N$32, MATCH($X161,'[5]3.0 BENCHMARK'!$B$20:$B$32, 0), MATCH($K161,'[5]3.0 BENCHMARK'!$D$9:$N$9, 0)) -> 317 | AF161: 20 Levels | AG161: 5.5m average
B162: Single Asset | C162: Residential | D162: Multi Family | E162: High Rise | H162: KSA | I162: Jeddah | J162: Developer06 | K162: MF PROJECT 1 | M162: E Project01 | O162: 2019 | Q162: Award | R162: Competitive - Traditional | S162: Fixed Price Lump Sum | V162: =INDEX('[5]3.0 BENCHMARK'!$D$17:$N$17, MATCH($V$1,'[5]3.0 BENCHMARK'!$B$17, 0), MATCH($K162,'[5]3.0 BENCHMARK'!$D$9:$N$9, 0)) -> 68339.32 | X162: Internal Finishes | Y162: SAR | AC162: =INDEX('[5]3.0 BENCHMARK'!$D$20:$N$32, MATCH($X162,'[5]3.0 BENCHMARK'!$B$20:$B$32, 0), MATCH($K162,'[5]3.0 BENCHMARK'!$D$9:$N$9, 0)) -> 675 | AF162: 20 Levels | AG162: 5.5m average
B163: Single Asset | C163: Residential | D163: Multi Family | E163: High Rise | H163: KSA | I163: Jeddah | J163: Developer06 | K163: MF PROJECT 1 | M163: E Project01 | O163: 2019 | Q163: Award | R163: Competitive - Traditional | S163: Fixed Price Lump Sum | V163: =INDEX('[5]3.0 BENCHMARK'!$D$17:$N$17, MATCH($V$1,'[5]3.0 BENCHMARK'!$B$17, 0), MATCH($K163,'[5]3.0 BENCHMARK'!$D$9:$N$9, 0)) -> 68339.32 | X163: FF&E | Y163: SAR | AC163: =INDEX('[5]3.0 BENCHMARK'!$D$20:$N$32, MATCH($X163,'[5]3.0 BENCHMARK'!$B$20:$B$32, 0), MATCH($K163,'[5]3.0 BENCHMARK'!$D$9:$N$9, 0)) -> 413 | AF163: 20 Levels | AG163: 5.5m average
B164: Single Asset | C164: Residential | D164: Multi Family | E164: High Rise | H164: KSA | I164: Jeddah | J164: Developer06 | K164: MF PROJECT 1 | M164: E Project01 | O164: 2019 | Q164: Award | R164: Competitive - Traditional | S164: Fixed Price Lump Sum | V164: =INDEX('[5]3.0 BENCHMARK'!$D$17:$N$17, MATCH($V$1,'[5]3.0 BENCHMARK'!$B$17, 0), MATCH($K164,'[5]3.0 BENCHMARK'!$D$9:$N$9, 0)) -> 68339.32 | X164: Sanitary Fittings | Y164: SAR | AC164: =INDEX('[5]3.0 BENCHMARK'!$D$20:$N$32, MATCH($X164,'[5]3.0 BENCHMARK'!$B$20:$B$32, 0), MATCH($K164,'[5]3.0 BENCHMARK'!$D$9:$N$9, 0)) -> 85 | AF164: 20 Levels | AG164: 5.5m average
B165: Single Asset | C165: Residential | D165: Multi Family | E165: High Rise | H165: KSA | I165: Jeddah | J165: Developer06 | K165: MF PROJECT 1 | M165: E Project01 | O165: 2019 | Q165: Award | R165: Competitive - Traditional | S165: Fixed Price Lump Sum | V165: =INDEX('[5]3.0 BENCHMARK'!$D$17:$N$17, MATCH($V$1,'[5]3.0 BENCHMARK'!$B$17, 0), MATCH($K165,'[5]3.0 BENCHMARK'!$D$9:$N$9, 0)) -> 68339.32 | X165: Services Equipment | Y165: SAR | AC165: =INDEX('[5]3.0 BENCHMARK'!$D$20:$N$32, MATCH($X165,'[5]3.0 BENCHMARK'!$B$20:$B$32, 0), MATCH($K165,'[5]3.0 BENCHMARK'!$D$9:$N$9, 0)) -> 51 | AF165: 20 Levels | AG165: 5.5m average
B166: Single Asset | C166: Residential | D166: Multi Family | E166: High Rise | H166: KSA | I166: Jeddah | J166: Developer06 | K166: MF PROJECT 1 | M166: E Project01 | O166: 2019 | Q166: Award | R166: Competitive - Traditional | S166: Fixed Price Lump Sum | V166: =INDEX('[5]3.0 BENCHMARK'!$D$17:$N$17, MATCH($V$1,'[5]3.0 BENCHMARK'!$B$17, 0), MATCH($K166,'[5]3.0 BENCHMARK'!$D$9:$N$9, 0)) -> 68339.32 | X166: Mechanical | Y166: SAR | AC166: =INDEX('[5]3.0 BENCHMARK'!$D$20:$N$32, MATCH($X166,'[5]3.0 BENCHMARK'!$B$20:$B$32, 0), MATCH($K166,'[5]3.0 BENCHMARK'!$D$9:$N$9, 0)) -> 759 | AF166: 20 Levels | AG166: 5.5m average
B167: Single Asset | C167: Residential | D167: Multi Family | E167: High Rise | H167: KSA | I167: Jeddah | J167: Developer06 | K167: MF PROJECT 1 | M167: E Project01 | O167: 2019 | Q167: Award | R167: Competitive - Traditional | S167: Fixed Price Lump Sum | V167: =INDEX('[5]3.0 BENCHMARK'!$D$17:$N$17, MATCH($V$1,'[5]3.0 BENCHMARK'!$B$17, 0), MATCH($K167,'[5]3.0 BENCHMARK'!$D$9:$N$9, 0)) -> 68339.32 | X167: Electrical | Y167: SAR | AC167: =INDEX('[5]3.0 BENCHMARK'!$D$20:$N$32, MATCH($X167,'[5]3.0 BENCHMARK'!$B$20:$B$32, 0), MATCH($K167,'[5]3.0 BENCHMARK'!$D$9:$N$9, 0)) -> 1292 | AF167: 20 Levels | AG167: 5.5m average
B168: Single Asset | C168: Residential | D168: Multi Family | E168: High Rise | H168: KSA | I168: Jeddah | J168: Developer06 | K168: MF PROJECT 1 | M168: E Project01 | O168: 2019 | Q168: Award | R168: Competitive - Traditional | S168: Fixed Price Lump Sum | V168: =INDEX('[5]3.0 BENCHMARK'!$D$17:$N$17, MATCH($V$1,'[5]3.0 BENCHMARK'!$B$17, 0), MATCH($K168,'[5]3.0 BENCHMARK'!$D$9:$N$9, 0)) -> 68339.32 | X168: Conveying Systems | Y168: SAR | AC168: =INDEX('[5]3.0 BENCHMARK'!$D$20:$N$32, MATCH($X168,'[5]3.0 BENCHMARK'!$B$20:$B$32, 0), MATCH($K168,'[5]3.0 BENCHMARK'!$D$9:$N$9, 0)) -> 278 | AF168: 20 Levels | AG168: 5.5m average
B169: Single Asset | C169: Residential | D169: Multi Family | E169: High Rise | H169: KSA | I169: Jeddah | J169: Developer06 | K169: MF PROJECT 1 | M169: E Project01 | O169: 2019 | Q169: Award | R169: Competitive - Traditional | S169: Fixed Price Lump Sum | V169: =INDEX('[5]3.0 BENCHMARK'!$D$17:$N$17, MATCH($V$1,'[5]3.0 BENCHMARK'!$B$17, 0), MATCH($K169,'[5]3.0 BENCHMARK'!$D$9:$N$9, 0)) -> 68339.32 | X169: External Works | Y169: SAR | AC169: =INDEX('[5]3.0 BENCHMARK'!$D$20:$N$32, MATCH($X169,'[5]3.0 BENCHMARK'!$B$20:$B$32, 0), MATCH($K169,'[5]3.0 BENCHMARK'!$D$9:$N$9, 0)) -> 444 | AF169: 20 Levels | AG169: 5.5m average
... B235: Single Asset | C235: Residential | D235: Multi Family | E235: Low-rise | H235: KSA | I235: Riyadh | J235: Developer09 | K235: MF PROJECT 6 | M235: DG Project01 | O235: 2023 | Q235: Award | R235: Competitive - Traditional | S235: Fixed Price Lump Sum | V235: =INDEX('[5]3.0 BENCHMARK'!$D$17:$N$17, MATCH($V$1,'[5]3.0 BENCHMARK'!$B$17, 0), MATCH($K235,'[5]3.0 BENCHMARK'!$D$9:$N$9, 0)) -> 29341 | X235: General Requirements | Y235: SAR | AC235: =INDEX('[5]3.0 BENCHMARK'!$D$20:$N$32, MATCH($X235,'[5]3.0 BENCHMARK'!$B$20:$B$32, 0), MATCH($K235,'[5]3.0 BENCHMARK'!$D$9:$N$9, 0)) -> 0 | AF235: 3-4 Levels | AG235: 5.5m average
B236: Single Asset | C236: Retail | D236: Neighbourhood Centre | E236: Neighbourhood Centre | H236: KSA | I236: Riyadh | J236: Developer06 | K236: R PROJECT 1 | M236: MUE Project | O236: 2024 | Q236: Award | R236: Competitive - Traditional | S236: Fixed Price Lump Sum | V236: =+INDEX('[6]3 - BENCHMARK - RT'!$D$22:$V$37,MATCH($K236,'[6]3 - BENCHMARK - RT'!$D$10:$V$10,0),MATCH($V$1,'[6]3 - BENCHMARK - RT'!$B$22,0)) -> 8749 | X236: Substructure | Y236: SAR | AC236: =INDEX('[6]3 - BENCHMARK - RT'!$D$25:$V$37, MATCH($X236,'[6]3 - BENCHMARK - RT'!$B$25:$B$37, 0), MATCH($K236,'[6]3 - BENCHMARK - RT'!$D$10:$V$10, 0)) -> 660 | AF236: 1 Level | AG236: 5.5m average
B237: Single Asset | C237: Retail | D237: Neighbourhood Centre | E237: Neighbourhood Centre | H237: KSA | I237: Riyadh | J237: Developer06 | K237: R PROJECT 1 | M237: MUE Project | O237: 2024 | Q237: Award | R237: Competitive - Traditional | S237: Fixed Price Lump Sum | V237: =+INDEX('[6]3 - BENCHMARK - RT'!$D$22:$V$37,MATCH($K237,'[6]3 - BENCHMARK - RT'!$D$10:$V$10,0),MATCH($V$1,'[6]3 - BENCHMARK - RT'!$B$22,0)) -> 8749 | X237: Superstructure | Y237: SAR | AC237: =INDEX('[6]3 - BENCHMARK - RT'!$D$25:$V$37, MATCH($X237,'[6]3 - BENCHMARK - RT'!$B$25:$B$37, 0), MATCH($K237,'[6]3 - BENCHMARK - RT'!$D$10:$V$10, 0)) -> 850 | AF237: 1 Level | AG237: 5.5m average
B238: Single Asset | C238: Retail | D238: Neighbourhood Centre | E238: Neighbourhood Centre | H238: KSA | I238: Riyadh | J238: Developer06 | K238: R PROJECT 1 | M238: MUE Project | O238: 2024 | Q238: Award | R238: Competitive - Traditional | S238: Fixed Price Lump Sum | V238: =+INDEX('[6]3 - BENCHMARK - RT'!$D$22:$V$37,MATCH($K238,'[6]3 - BENCHMARK - RT'!$D$10:$V$10,0),MATCH($V$1,'[6]3 - BENCHMARK - RT'!$B$22,0)) -> 8749 | X238: Building External Envelope | Y238: SAR | AC238: =INDEX('[6]3 - BENCHMARK - RT'!$D$25:$V$37, MATCH($X238,'[6]3 - BENCHMARK - RT'!$B$25:$B$37, 0), MATCH($K238,'[6]3 - BENCHMARK - RT'!$D$10:$V$10, 0)) -> 610 | AF238: 1 Level | AG238: 5.5m average
B239: Single Asset | C239: Retail | D239: Neighbourhood Centre | E239: Neighbourhood Centre | H239: KSA | I239: Riyadh | J239: Developer06 | K239: R PROJECT 1 | M239: MUE Project | O239: 2024 | Q239: Award | R239: Competitive - Traditional | S239: Fixed Price Lump Sum | V239: =+INDEX('[6]3 - BENCHMARK - RT'!$D$22:$V$37,MATCH($K239,'[6]3 - BENCHMARK - RT'!$D$10:$V$10,0),MATCH($V$1,'[6]3 - BENCHMARK - RT'!$B$22,0)) -> 8749 | X239: Internal Walls and Doors | Y239: SAR | AC239: =INDEX('[6]3 - BENCHMARK - RT'!$D$25:$V$37, MATCH($X239,'[6]3 - BENCHMARK - RT'!$B$25:$B$37, 0), MATCH($K239,'[6]3 - BENCHMARK - RT'!$D$10:$V$10, 0)) -> 45 | AF239: 1 Level | AG239: 5.5m average
B240: Single Asset | C240: Retail | D240: Neighbourhood Centre | E240: Neighbourhood Centre | H240: KSA | I240: Riyadh | J240: Developer06 | K240: R PROJECT 1 | M240: MUE Project | O240: 2024 | Q240: Award | R240: Competitive - Traditional | S240: Fixed Price Lump Sum | V240: =+INDEX('[6]3 - BENCHMARK - RT'!$D$22:$V$37,MATCH($K240,'[6]3 - BENCHMARK - RT'!$D$10:$V$10,0),MATCH($V$1,'[6]3 - BENCHMARK - RT'!$B$22,0)) -> 8749 | X240: Internal Finishes | Y240: SAR | AC240: =INDEX('[6]3 - BENCHMARK - RT'!$D$25:$V$37, MATCH($X240,'[6]3 - BENCHMARK - RT'!$B$25:$B$37, 0), MATCH($K240,'[6]3 - BENCHMARK - RT'!$D$10:$V$10, 0)) -> 120 | AF240: 1 Level | AG240: 5.5m average
B241: Single Asset | C241: Retail | D241: Neighbourhood Centre | E241: Neighbourhood Centre | H241: KSA | I241: Riyadh | J241: Developer06 | K241: R PROJECT 1 | M241: MUE Project | O241: 2024 | Q241: Award | R241: Competitive - Traditional | S241: Fixed Price Lump Sum | V241: =+INDEX('[6]3 - BENCHMARK - RT'!$D$22:$V$37,MATCH($K241,'[6]3 - BENCHMARK - RT'!$D$10:$V$10,0),MATCH($V$1,'[6]3 - BENCHMARK - RT'!$B$22,0)) -> 8749 | X241: FF&E | Y241: SAR | AC241: =INDEX('[6]3 - BENCHMARK - RT'!$D$25:$V$37, MATCH($X241,'[6]3 - BENCHMARK - RT'!$B$25:$B$37, 0), MATCH($K241,'[6]3 - BENCHMARK - RT'!$D$10:$V$10, 0)) -> 115 | AF241: 1 Level | AG241: 5.5m average
B242: Single Asset | C242: Retail | D242: Neighbourhood Centre | E242: Neighbourhood Centre | H242: KSA | I242: Riyadh | J242: Developer06 | K242: R PROJECT 1 | M242: MUE Project | O242: 2024 | Q242: Award | R242: Competitive - Traditional | S242: Fixed Price Lump Sum | V242: =+INDEX('[6]3 - BENCHMARK - RT'!$D$22:$V$37,MATCH($K242,'[6]3 - BENCHMARK - RT'!$D$10:$V$10,0),MATCH($V$1,'[6]3 - BENCHMARK - RT'!$B$22,0)) -> 8749 | X242: Sanitary Fittings | Y242: SAR | AC242: =INDEX('[6]3 - BENCHMARK - RT'!$D$25:$V$37, MATCH($X242,'[6]3 - BENCHMARK - RT'!$B$25:$B$37, 0), MATCH($K242,'[6]3 - BENCHMARK - RT'!$D$10:$V$10, 0)) -> 25 | AF242: 1 Level | AG242: 5.5m average
B243: Single Asset | C243: Retail | D243: Neighbourhood Centre | E243: Neighbourhood Centre | H243: KSA | I243: Riyadh | J243: Developer06 | K243: R PROJECT 1 | M243: MUE Project | O243: 2024 | Q243: Award | R243: Competitive - Traditional | S243: Fixed Price Lump Sum | V243: =+INDEX('[6]3 - BENCHMARK - RT'!$D$22:$V$37,MATCH($K243,'[6]3 - BENCHMARK - RT'!$D$10:$V$10,0),MATCH($V$1,'[6]3 - BENCHMARK - RT'!$B$22,0)) -> 8749 | X243: Services Equipment | Y243: SAR | AC243: =INDEX('[6]3 - BENCHMARK - RT'!$D$25:$V$37, MATCH($X243,'[6]3 - BENCHMARK - RT'!$B$25:$B$37, 0), MATCH($K243,'[6]3 - BENCHMARK - RT'!$D$10:$V$10, 0)) -> 0 | AF243: 1 Level | AG243: 5.5m average
B244: Single Asset | C244: Retail | D244: Neighbourhood Centre | E244: Neighbourhood Centre | H244: KSA | I244: Riyadh | J244: Developer06 | K244: R PROJECT 1 | M244: MUE Project | O244: 2024 | Q244: Award | R244: Competitive - Traditional | S244: Fixed Price Lump Sum | V244: =+INDEX('[6]3 - BENCHMARK - RT'!$D$22:$V$37,MATCH($K244,'[6]3 - BENCHMARK - RT'!$D$10:$V$10,0),MATCH($V$1,'[6]3 - BENCHMARK - RT'!$B$22,0)) -> 8749 | X244: Mechanical | Y244: SAR | AC244: =INDEX('[6]3 - BENCHMARK - RT'!$D$25:$V$37, MATCH($X244,'[6]3 - BENCHMARK - RT'!$B$25:$B$37, 0), MATCH($K244,'[6]3 - BENCHMARK - RT'!$D$10:$V$10, 0)) -> 520 | AF244: 1 Level | AG244: 5.5m average
B245: Single Asset | C245: Retail | D245: Neighbourhood Centre | E245: Neighbourhood Centre | H245: KSA | I245: Riyadh | J245: Developer06 | K245: R PROJECT 1 | M245: MUE Project | O245: 2024 | Q245: Award | R245: Competitive - Traditional | S245: Fixed Price Lump Sum | V245: =+INDEX('[6]3 - BENCHMARK - RT'!$D$22:$V$37,MATCH($K245,'[6]3 - BENCHMARK - RT'!$D$10:$V$10,0),MATCH($V$1,'[6]3 - BENCHMARK - RT'!$B$22,0)) -> 8749 | X245: Electrical | Y245: SAR | AC245: =INDEX('[6]3 - BENCHMARK - RT'!$D$25:$V$37, MATCH($X245,'[6]3 - BENCHMARK - RT'!$B$25:$B$37, 0), MATCH($K245,'[6]3 - BENCHMARK - RT'!$D$10:$V$10, 0)) -> 1110 | AF245: 1 Level | AG245: 5.5m average
B246: Single Asset | C246: Retail | D246: Neighbourhood Centre | E246: Neighbourhood Centre | H246: KSA | I246: Riyadh | J246: Developer06 | K246: R PROJECT 1 | M246: MUE Project | O246: 2024 | Q246: Award | R246: Competitive - Traditional | S246: Fixed Price Lump Sum | V246: =+INDEX('[6]3 - BENCHMARK - RT'!$D$22:$V$37,MATCH($K246,'[6]3 - BENCHMARK - RT'!$D$10:$V$10,0),MATCH($V$1,'[6]3 - BENCHMARK - RT'!$B$22,0)) -> 8749 | X246: Conveying Systems | Y246: SAR | AC246: =INDEX('[6]3 - BENCHMARK - RT'!$D$25:$V$37, MATCH($X246,'[6]3 - BENCHMARK - RT'!$B$25:$B$37, 0), MATCH($K246,'[6]3 - BENCHMARK - RT'!$D$10:$V$10, 0)) -> 0 | AF246: 1 Level | AG246: 5.5m average
B247: Single Asset | C247: Retail | D247: Neighbourhood Centre | E247: Neighbourhood Centre | H247: KSA | I247: Riyadh | J247: Developer06 | K247: R PROJECT 1 | M247: MUE Project | O247: 2024 | Q247: Award | R247: Competitive - Traditional | S247: Fixed Price Lump Sum | V247: =+INDEX('[6]3 - BENCHMARK - RT'!$D$22:$V$37,MATCH($K247,'[6]3 - BENCHMARK - RT'!$D$10:$V$10,0),MATCH($V$1,'[6]3 - BENCHMARK - RT'!$B$22,0)) -> 8749 | X247: External Works | Y247: SAR | AC247: =INDEX('[6]3 - BENCHMARK - RT'!$D$25:$V$37, MATCH($X247,'[6]3 - BENCHMARK - RT'!$B$25:$B$37, 0), MATCH($K247,'[6]3 - BENCHMARK - RT'!$D$10:$V$10, 0)) -> 243 | AF247: 1 Level | AG247: 5.5m average
B248: Single Asset | C248: Retail | D248: Neighbourhood Centre | E248: Neighbourhood Centre | H248: KSA | I248: Riyadh | J248: Developer06 | K248: R PROJECT 1 | M248: MUE Project | O248: 2024 | Q248: Award | R248: Competitive - Traditional | S248: Fixed Price Lump Sum | V248: =INDEX('[6]3 - BENCHMARK - RT'!$D$22:$V$37, MATCH($V$1,'[6]3 - BENCHMARK - RT'!$B$22, 0), MATCH($K248,'[6]3 - BENCHMARK - RT'!$D$10:$V$10, 0)) -> 8749 | X248: General Requirements | Y248: SAR | AC248: =INDEX('[6]3 - BENCHMARK - RT'!$D$25:$V$37, MATCH($X248,'[6]3 - BENCHMARK - RT'!$B$25:$B$37, 0), MATCH($K248,'[6]3 - BENCHMARK - RT'!$D$10:$V$10, 0)) -> 0 | AF248: 1 Level | AG248: 5.5m average
B249: Single Asset | C249: Retail | D249: District Centre (Community Mall) | E249: District Centre (Community Mall) | H249: Qatar | I249: Doha | J249: Developer06 | K249: R PROJECT 2 | M249: MUE Project01 | O249: 2019 | Q249: Award | R249: Competitive - Traditional | S249: Fixed Price Lump Sum | V249: =INDEX('[6]3 - BENCHMARK - RT'!$D$22:$V$37, MATCH($V$1,'[6]3 - BENCHMARK - RT'!$B$22, 0), MATCH($K249,'[6]3 - BENCHMARK - RT'!$D$10:$V$10, 0)) -> 4171.45 | X249: Substructure | Y249: SAR | AC249: =INDEX('[6]3 - BENCHMARK - RT'!$D$25:$V$37, MATCH($X249,'[6]3 - BENCHMARK - RT'!$B$25:$B$37, 0), MATCH($K249,'[6]3 - BENCHMARK - RT'!$D$10:$V$10, 0)) -> 557 | AF249: 1 Level | AG249: 5.5m average
B250: Single Asset | C250: Retail | D250: District Centre (Community Mall) | E250: District Centre (Community Mall) | H250: Qatar | I250: Doha | J250: Developer06 | K250: R PROJECT 2 | M250: MUE Project01 | O250: 2019 | Q250: Award | R250: Competitive - Traditional | S250: Fixed Price Lump Sum | V250: =INDEX('[6]3 - BENCHMARK - RT'!$D$22:$V$37, MATCH($V$1,'[6]3 - BENCHMARK - RT'!$B$22, 0), MATCH($K250,'[6]3 - BENCHMARK - RT'!$D$10:$V$10, 0)) -> 4171.45 | X250: Superstructure | Y250: SAR | AC250: =INDEX('[6]3 - BENCHMARK - RT'!$D$25:$V$37, MATCH($X250,'[6]3 - BENCHMARK - RT'!$B$25:$B$37, 0), MATCH($K250,'[6]3 - BENCHMARK - RT'!$D$10:$V$10, 0)) -> 1463 | AF250: 1 Level | AG250: 5.5m average
B251: Single Asset | C251: Retail | D251: District Centre (Community Mall) | E251: District Centre (Community Mall) | H251: Qatar | I251: Doha | J251: Developer06 | K251: R PROJECT 2 | M251: MUE Project01 | O251: 2019 | Q251: Award | R251: Competitive - Traditional | S251: Fixed Price Lump Sum | V251: =INDEX('[6]3 - BENCHMARK - RT'!$D$22:$V$37, MATCH($V$1,'[6]3 - BENCHMARK - RT'!$B$22, 0), MATCH($K251,'[6]3 - BENCHMARK - RT'!$D$10:$V$10, 0)) -> 4171.45 | X251: Building External Envelope | Y251: SAR | AC251: =INDEX('[6]3 - BENCHMARK - RT'!$D$25:$V$37, MATCH($X251,'[6]3 - BENCHMARK - RT'!$B$25:$B$37, 0), MATCH($K251,'[6]3 - BENCHMARK - RT'!$D$10:$V$10, 0)) -> 1254 | AF251: 1 Level | AG251: 5.5m average
B252: Single Asset | C252: Retail | D252: District Centre (Community Mall) | E252: District Centre (Community Mall) | H252: Qatar | I252: Doha | J252: Developer06 | K252: R PROJECT 2 | M252: MUE Project01 | O252: 2019 | Q252: Award | R252: Competitive - Traditional | S252: Fixed Price Lump Sum | V252: =INDEX('[6]3 - BENCHMARK - RT'!$D$22:$V$37, MATCH($V$1,'[6]3 - BENCHMARK - RT'!$B$22, 0), MATCH($K252,'[6]3 - BENCHMARK - RT'!$D$10:$V$10, 0)) -> 4171.45 | X252: Internal Walls and Doors | Y252: SAR | AC252: =INDEX('[6]3 - BENCHMARK - RT'!$D$25:$V$37, MATCH($X252,'[6]3 - BENCHMARK - RT'!$B$25:$B$37, 0), MATCH($K252,'[6]3 - BENCHMARK - RT'!$D$10:$V$10, 0)) -> 209 | AF252: 1 Level | AG252: 5.5m average
B253: Single Asset | C253: Retail | D253: District Centre (Community Mall) | E253: District Centre (Community Mall) | H253: Qatar | I253: Doha | J253: Developer06 | K253: R PROJECT 2 | M253: MUE Project01 | O253: 2019 | Q253: Award | R253: Competitive - Traditional | S253: Fixed Price Lump Sum | V253: =INDEX('[6]3 - BENCHMARK - RT'!$D$22:$V$37, MATCH($V$1,'[6]3 - BENCHMARK - RT'!$B$22, 0), MATCH($K253,'[6]3 - BENCHMARK - RT'!$D$10:$V$10, 0)) -> 4171.45 | X253: Internal Finishes | Y253: SAR | AC253: =INDEX('[6]3 - BENCHMARK - RT'!$D$25:$V$37, MATCH($X253,'[6]3 - BENCHMARK - RT'!$B$25:$B$37, 0), MATCH($K253,'[6]3 - BENCHMARK - RT'!$D$10:$V$10, 0)) -> 383 | AF253: 1 Level | AG253: 5.5m average
B254: Single Asset | C254: Retail | D254: District Centre (Community Mall) | E254: District Centre (Community Mall) | H254: Qatar | I254: Doha | J254: Developer06 | K254: R PROJECT 2 | M254: MUE Project01 | O254: 2019 | Q254: Award | R254: Competitive - Traditional | S254: Fixed Price Lump Sum | V254: =INDEX('[6]3 - BENCHMARK - RT'!$D$22:$V$37, MATCH($V$1,'[6]3 - BENCHMARK - RT'!$B$22, 0), MATCH($K254,'[6]3 - BENCHMARK - RT'!$D$10:$V$10, 0)) -> 4171.45 | X254: FF&E | Y254: SAR | AC254: =INDEX('[6]3 - BENCHMARK - RT'!$D$25:$V$37, MATCH($X254,'[6]3 - BENCHMARK - RT'!$B$25:$B$37, 0), MATCH($K254,'[6]3 - BENCHMARK - RT'!$D$10:$V$10, 0)) -> 209 | AF254: 1 Level | AG254: 5.5m average
B255: Single Asset | C255: Retail | D255: District Centre (Community Mall) | E255: District Centre (Community Mall) | H255: Qatar | I255: Doha | J255: Developer06 | K255: R PROJECT 2 | M255: MUE Project01 | O255: 2019 | Q255: Award | R255: Competitive - Traditional | S255: Fixed Price Lump Sum | V255: =INDEX('[6]3 - BENCHMARK - RT'!$D$22:$V$37, MATCH($V$1,'[6]3 - BENCHMARK - RT'!$B$22, 0), MATCH($K255,'[6]3 - BENCHMARK - RT'!$D$10:$V$10, 0)) -> 4171.45 | X255: Sanitary Fittings | Y255: SAR | AC255: =INDEX('[6]3 - BENCHMARK - RT'!$D$25:$V$37, MATCH($X255,'[6]3 - BENCHMARK - RT'!$B$25:$B$37, 0), MATCH($K255,'[6]3 - BENCHMARK - RT'!$D$10:$V$10, 0)) -> 70 | AF255: 1 Level | AG255: 5.5m average
B256: Single Asset | C256: Retail | D256: District Centre (Community Mall) | E256: District Centre (Community Mall) | H256: Qatar | I256: Doha | J256: Developer06 | K256: R PROJECT 2 | M256: MUE Project01 | O256: 2019 | Q256: Award | R256: Competitive - Traditional | S256: Fixed Price Lump Sum | V256: =INDEX('[6]3 - BENCHMARK - RT'!$D$22:$V$37, MATCH($V$1,'[6]3 - BENCHMARK - RT'!$B$22, 0), MATCH($K256,'[6]3 - BENCHMARK - RT'!$D$10:$V$10, 0)) -> 4171.45 | X256: Services Equipment | Y256: SAR | AC256: =INDEX('[6]3 - BENCHMARK - RT'!$D$25:$V$37, MATCH($X256,'[6]3 - BENCHMARK - RT'!$B$25:$B$37, 0), MATCH($K256,'[6]3 - BENCHMARK - RT'!$D$10:$V$10, 0)) -> 0 | AF256: 1 Level | AG256: 5.5m average
B257: Single Asset | C257: Retail | D257: District Centre (Community Mall) | E257: District Centre (Community Mall) | H257: Qatar | I257: Doha | J257: Developer06 | K257: R PROJECT 2 | M257: MUE Project01 | O257: 2019 | Q257: Award | R257: Competitive - Traditional | S257: Fixed Price Lump Sum | V257: =INDEX('[6]3 - BENCHMARK - RT'!$D$22:$V$37, MATCH($V$1,'[6]3 - BENCHMARK - RT'!$B$22, 0), MATCH($K257,'[6]3 - BENCHMARK - RT'!$D$10:$V$10, 0)) -> 4171.45 | X257: Mechanical | Y257: SAR | AC257: =INDEX('[6]3 - BENCHMARK - RT'!$D$25:$V$37, MATCH($X257,'[6]3 - BENCHMARK - RT'!$B$25:$B$37, 0), MATCH($K257,'[6]3 - BENCHMARK - RT'!$D$10:$V$10, 0)) -> 836 | AF257: 1 Level | AG257: 5.5m average
B258: Single Asset | C258: Retail | D258: District Centre (Community Mall) | E258: District Centre (Community Mall) | H258: Qatar | I258: Doha | J258: Developer06 | K258: R PROJECT 2 | M258: MUE Project01 | O258: 2019 | Q258: Award | R258: Competitive - Traditional | S258: Fixed Price Lump Sum | V258: =INDEX('[6]3 - BENCHMARK - RT'!$D$22:$V$37, MATCH($V$1,'[6]3 - BENCHMARK - RT'!$B$22, 0), MATCH($K258,'[6]3 - BENCHMARK - RT'!$D$10:$V$10, 0)) -> 4171.45 | X258: Electrical | Y258: SAR | AC258: =INDEX('[6]3 - BENCHMARK - RT'!$D$25:$V$37, MATCH($X258,'[6]3 - BENCHMARK - RT'!$B$25:$B$37, 0), MATCH($K258,'[6]3 - BENCHMARK - RT'!$D$10:$V$10, 0)) -> 1115 | AF258: 1 Level | AG258: 5.5m average
B259: Single Asset | C259: Retail | D259: District Centre (Community Mall) | E259: District Centre (Community Mall) | H259: Qatar | I259: Doha | J259: Developer06 | K259: R PROJECT 2 | M259: MUE Project01 | O259: 2019 | Q259: Award | R259: Competitive - Traditional | S259: Fixed Price Lump Sum | V259: =INDEX('[6]3 - BENCHMARK - RT'!$D$22:$V$37, MATCH($V$1,'[6]3 - BENCHMARK - RT'!$B$22, 0), MATCH($K259,'[6]3 - BENCHMARK - RT'!$D$10:$V$10, 0)) -> 4171.45 | X259: Conveying Systems | Y259: SAR | AC259: =INDEX('[6]3 - BENCHMARK - RT'!$D$25:$V$37, MATCH($X259,'[6]3 - BENCHMARK - RT'!$B$25:$B$37, 0), MATCH($K259,'[6]3 - BENCHMARK - RT'!$D$10:$V$10, 0)) -> 0 | AF259: 1 Level | AG259: 5.5m average
... B365: Single Asset | C365: Retail | D365: Regional Mall | E365: Regional Mall | H365: Qatar | I365: Doha | J365: MBHH | K365: R PROJECT 10 | M365: Regional Mall | O365: 2020 | Q365: Award | R365: Competitive - Traditional | S365: Fixed Price Lump Sum | V365: =INDEX('[6]3 - BENCHMARK - RT'!$D$22:$V$37, MATCH($V$1,'[6]3 - BENCHMARK - RT'!$B$22, 0), MATCH($K365,'[6]3 - BENCHMARK - RT'!$D$10:$V$10, 0)) -> 36650 | X365: General Requirements | Y365: SAR | AC365: =INDEX('[6]3 - BENCHMARK - RT'!$D$25:$V$37, MATCH($X365,'[6]3 - BENCHMARK - RT'!$B$25:$B$37, 0), MATCH($K365,'[6]3 - BENCHMARK - RT'!$D$10:$V$10, 0)) -> 0 | AF365: 4 Levels | AG365: 5.5m average
B366: Single Asset | C366: Commercial | D366: Commercial | E366: Com-Low-rise | H366: KSA | I366: Damman | J366: GCDRC | K366: PROJECT 1 Low Rise | M366: GCDRC | O366: 2023 | Q366: Award | R366: Competitive - Traditional | S366: Fixed Price Lump Sum | V366: =INDEX('[7]BENCHMARK - OFFICE'!$E$22:$Q$36, MATCH($V$1,'[7]BENCHMARK - OFFICE'!$B$22, 0), MATCH($K366,'[7]BENCHMARK - OFFICE'!$E$12:$Q$12, 0)) -> 17400 | X366: Substructure | Y366: SAR | AC366: =INDEX('[7]BENCHMARK - OFFICE'!$E$25:$Q$37, MATCH($X366,'[7]BENCHMARK - OFFICE'!$B$25:$B$37, 0), MATCH($K366,'[7]BENCHMARK - OFFICE'!$E$12:$Q$12, 0)) -> 589.9803 | AF366: 3 Levels | AG366: 4m average
B367: Single Asset | C367: Commercial | D367: Commercial | E367: Com-Low-rise | H367: KSA | I367: Damman | J367: GCDRC | K367: PROJECT 1 Low Rise | M367: GCDRC | O367: 2023 | Q367: Award | R367: Competitive - Traditional | S367: Fixed Price Lump Sum | V367: =INDEX('[7]BENCHMARK - OFFICE'!$E$22:$Q$36, MATCH($V$1,'[7]BENCHMARK - OFFICE'!$B$22, 0), MATCH($K367,'[7]BENCHMARK - OFFICE'!$E$12:$Q$12, 0)) -> 17400 | X367: Superstructure | Y367: SAR | AC367: =INDEX('[7]BENCHMARK - OFFICE'!$E$25:$Q$37, MATCH($X367,'[7]BENCHMARK - OFFICE'!$B$25:$B$37, 0), MATCH($K367,'[7]BENCHMARK - OFFICE'!$E$12:$Q$12, 0)) -> 1001.3 | AF367: 3 Levels | AG367: 4m average
B368: Single Asset | C368: Commercial | D368: Commercial | E368: Com-Low-rise | H368: KSA | I368: Damman | J368: GCDRC | K368: PROJECT 1 Low Rise | M368: GCDRC | O368: 2023 | Q368: Award | R368: Competitive - Traditional | S368: Fixed Price Lump Sum | V368: =INDEX('[7]BENCHMARK - OFFICE'!$E$22:$Q$36, MATCH($V$1,'[7]BENCHMARK - OFFICE'!$B$22, 0), MATCH($K368,'[7]BENCHMARK - OFFICE'!$E$12:$Q$12, 0)) -> 17400 | X368: Building External Envelope | Y368: SAR | AC368: =INDEX('[7]BENCHMARK - OFFICE'!$E$25:$Q$37, MATCH($X368,'[7]BENCHMARK - OFFICE'!$B$25:$B$37, 0), MATCH($K368,'[7]BENCHMARK - OFFICE'!$E$12:$Q$12, 0)) -> 1156.329 | AF368: 3 Levels | AG368: 4m average
B369: Single Asset | C369: Commercial | D369: Commercial | E369: Com-Low-rise | H369: KSA | I369: Damman | J369: GCDRC | K369: PROJECT 1 Low Rise | M369: GCDRC | O369: 2023 | Q369: Award | R369: Competitive - Traditional | S369: Fixed Price Lump Sum | V369: =INDEX('[7]BENCHMARK - OFFICE'!$E$22:$Q$36, MATCH($V$1,'[7]BENCHMARK - OFFICE'!$B$22, 0), MATCH($K369,'[7]BENCHMARK - OFFICE'!$E$12:$Q$12, 0)) -> 17400 | X369: Internal Walls and Doors | Y369: SAR | AC369: =INDEX('[7]BENCHMARK - OFFICE'!$E$25:$Q$37, MATCH($X369,'[7]BENCHMARK - OFFICE'!$B$25:$B$37, 0), MATCH($K369,'[7]BENCHMARK - OFFICE'!$E$12:$Q$12, 0)) -> 189.45266 | AF369: 3 Levels | AG369: 4m average
B370: Single Asset | C370: Commercial | D370: Commercial | E370: Com-Low-rise | H370: KSA | I370: Damman | J370: GCDRC | K370: PROJECT 1 Low Rise | M370: GCDRC | O370: 2023 | Q370: Award | R370: Competitive - Traditional | S370: Fixed Price Lump Sum | V370: =INDEX('[7]BENCHMARK - OFFICE'!$E$22:$Q$36, MATCH($V$1,'[7]BENCHMARK - OFFICE'!$B$22, 0), MATCH($K370,'[7]BENCHMARK - OFFICE'!$E$12:$Q$12, 0)) -> 17400 | X370: Internal Finishes | Y370: SAR | AC370: =INDEX('[7]BENCHMARK - OFFICE'!$E$25:$Q$37, MATCH($X370,'[7]BENCHMARK - OFFICE'!$B$25:$B$37, 0), MATCH($K370,'[7]BENCHMARK - OFFICE'!$E$12:$Q$12, 0)) -> 364.90458 | AF370: 3 Levels | AG370: 4m average
B371: Single Asset | C371: Commercial | D371: Commercial | E371: Com-Low-rise | H371: KSA | I371: Damman | J371: GCDRC | K371: PROJECT 1 Low Rise | M371: GCDRC | O371: 2023 | Q371: Award | R371: Competitive - Traditional | S371: Fixed Price Lump Sum | V371: =INDEX('[7]BENCHMARK - OFFICE'!$E$22:$Q$36, MATCH($V$1,'[7]BENCHMARK - OFFICE'!$B$22, 0), MATCH($K371,'[7]BENCHMARK - OFFICE'!$E$12:$Q$12, 0)) -> 17400 | X371: FF&E | Y371: SAR | AC371: =INDEX('[7]BENCHMARK - OFFICE'!$E$25:$Q$37, MATCH($X371,'[7]BENCHMARK - OFFICE'!$B$25:$B$37, 0), MATCH($K371,'[7]BENCHMARK - OFFICE'!$E$12:$Q$12, 0)) -> 32.948289 | AF371: 3 Levels | AG371: 4m average
B372: Single Asset | C372: Commercial | D372: Commercial | E372: Com-Low-rise | H372: KSA | I372: Damman | J372: GCDRC | K372: PROJECT 1 Low Rise | M372: GCDRC | O372: 2023 | Q372: Award | R372: Competitive - Traditional | S372: Fixed Price Lump Sum | V372: =INDEX('[7]BENCHMARK - OFFICE'!$E$22:$Q$36, MATCH($V$1,'[7]BENCHMARK - OFFICE'!$B$22, 0), MATCH($K372,'[7]BENCHMARK - OFFICE'!$E$12:$Q$12, 0)) -> 17400 | X372: Sanitary Fittings | Y372: SAR | AC372: =INDEX('[7]BENCHMARK - OFFICE'!$E$25:$Q$37, MATCH($X372,'[7]BENCHMARK - OFFICE'!$B$25:$B$37, 0), MATCH($K372,'[7]BENCHMARK - OFFICE'!$E$12:$Q$12, 0)) -> 47.363165 | AF372: 3 Levels | AG372: 4m average
B373: Single Asset | C373: Commercial | D373: Commercial | E373: Com-Low-rise | H373: KSA | I373: Damman | J373: GCDRC | K373: PROJECT 1 Low Rise | M373: GCDRC | O373: 2023 | Q373: Award | R373: Competitive - Traditional | S373: Fixed Price Lump Sum | V373: =INDEX('[7]BENCHMARK - OFFICE'!$E$22:$Q$36, MATCH($V$1,'[7]BENCHMARK - OFFICE'!$B$22, 0), MATCH($K373,'[7]BENCHMARK - OFFICE'!$E$12:$Q$12, 0)) -> 17400 | X373: Services Equipment | Y373: SAR | AC373: =INDEX('[7]BENCHMARK - OFFICE'!$E$25:$Q$37, MATCH($X373,'[7]BENCHMARK - OFFICE'!$B$25:$B$37, 0), MATCH($K373,'[7]BENCHMARK - OFFICE'!$E$12:$Q$12, 0)) -> 10.29634 | AF373: 3 Levels | AG373: 4m average
B374: Single Asset | C374: Commercial | D374: Commercial | E374: Com-Low-rise | H374: KSA | I374: Damman | J374: GCDRC | K374: PROJECT 1 Low Rise | M374: GCDRC | O374: 2023 | Q374: Award | R374: Competitive - Traditional | S374: Fixed Price Lump Sum | V374: =INDEX('[7]BENCHMARK - OFFICE'!$E$22:$Q$36, MATCH($V$1,'[7]BENCHMARK - OFFICE'!$B$22, 0), MATCH($K374,'[7]BENCHMARK - OFFICE'!$E$12:$Q$12, 0)) -> 17400 | X374: Mechanical | Y374: SAR | AC374: =INDEX('[7]BENCHMARK - OFFICE'!$E$25:$Q$37, MATCH($X374,'[7]BENCHMARK - OFFICE'!$B$25:$B$37, 0), MATCH($K374,'[7]BENCHMARK - OFFICE'!$E$12:$Q$12, 0)) -> 875.6979 | AF374: 3 Levels | AG374: 4m average
B375: Single Asset | C375: Commercial | D375: Commercial | E375: Com-Low-rise | H375: KSA | I375: Damman | J375: GCDRC | K375: PROJECT 1 Low Rise | M375: GCDRC | O375: 2023 | Q375: Award | R375: Competitive - Traditional | S375: Fixed Price Lump Sum | V375: =INDEX('[7]BENCHMARK - OFFICE'!$E$22:$Q$36, MATCH($V$1,'[7]BENCHMARK - OFFICE'!$B$22, 0), MATCH($K375,'[7]BENCHMARK - OFFICE'!$E$12:$Q$12, 0)) -> 17400 | X375: Electrical | Y375: SAR | AC375: =INDEX('[7]BENCHMARK - OFFICE'!$E$25:$Q$37, MATCH($X375,'[7]BENCHMARK - OFFICE'!$B$25:$B$37, 0), MATCH($K375,'[7]BENCHMARK - OFFICE'!$E$12:$Q$12, 0)) -> 745.45503 | AF375: 3 Levels | AG375: 4m average
B376: Single Asset | C376: Commercial | D376: Commercial | E376: Com-Low-rise | H376: KSA | I376: Damman | J376: GCDRC | K376: PROJECT 1 Low Rise | M376: GCDRC | O376: 2023 | Q376: Award | R376: Competitive - Traditional | S376: Fixed Price Lump Sum | V376: =INDEX('[7]BENCHMARK - OFFICE'!$E$22:$Q$36, MATCH($V$1,'[7]BENCHMARK - OFFICE'!$B$22, 0), MATCH($K376,'[7]BENCHMARK - OFFICE'!$E$12:$Q$12, 0)) -> 17400 | X376: Conveying Systems | Y376: SAR | AC376: =INDEX('[7]BENCHMARK - OFFICE'!$E$25:$Q$37, MATCH($X376,'[7]BENCHMARK - OFFICE'!$B$25:$B$37, 0), MATCH($K376,'[7]BENCHMARK - OFFICE'!$E$12:$Q$12, 0)) -> 94.41744 | AF376: 3 Levels | AG376: 4m average
B377: Single Asset | C377: Commercial | D377: Commercial | E377: Com-Low-rise | H377: KSA | I377: Damman | J377: GCDRC | K377: PROJECT 1 Low Rise | M377: GCDRC | O377: 2023 | Q377: Award | R377: Competitive - Traditional | S377: Fixed Price Lump Sum | V377: =INDEX('[7]BENCHMARK - OFFICE'!$E$22:$Q$36, MATCH($V$1,'[7]BENCHMARK - OFFICE'!$B$22, 0), MATCH($K377,'[7]BENCHMARK - OFFICE'!$E$12:$Q$12, 0)) -> 17400 | X377: External Works | Y377: SAR | AC377: =INDEX('[7]BENCHMARK - OFFICE'!$E$25:$Q$37, MATCH($X377,'[7]BENCHMARK - OFFICE'!$B$25:$B$37, 0), MATCH($K377,'[7]BENCHMARK - OFFICE'!$E$12:$Q$12, 0)) -> 499.47547 | AF377: 3 Levels | AG377: 4m average
... B456: Single Asset | C456: Commercial | D456: Commercial | E456: Com-High Rise | H456: KSA | I456: Riyadh | J456: Developer05 | K456: PROJECT 6 High Rise | M456: PS3 | O456: 2021 | Q456: Award | R456: Competitive - Traditional | S456: Fixed Price Lump Sum | V456: =INDEX('[7]BENCHMARK - OFFICE'!$E$22:$Q$36, MATCH($V$1,'[7]BENCHMARK - OFFICE'!$B$22, 0), MATCH($K456,'[7]BENCHMARK - OFFICE'!$E$12:$Q$12, 0)) -> 70864 | X456: General Requirements | Y456: SAR | AC456: =INDEX('[7]BENCHMARK - OFFICE'!$E$25:$Q$37, MATCH($X456,'[7]BENCHMARK - OFFICE'!$B$25:$B$37, 0), MATCH($K456,'[7]BENCHMARK - OFFICE'!$E$12:$Q$12, 0)) -> 0 | AF456: 19 Levels | AG456: 4m average
E495: Asset | H495: Country | I495: City | J495: Developer | L495: Alias | N495: Project | O495: Base Date | P495: Contractor | Q495: Status | R495: Procurement | S495: Contract Type | T495: BUA | U495: GIA | V495: GFA | W495: Keys | X495: NRM Lvl 1 | Y495: Currency | Z495: Total Cost | AA495: Cost/BUA | AB495: Cost/GIA | AC495: Cost/GFA | AD495: Cost/Key | AE495: Chart | AF495: No. of Floors | AG495: Avg Storey Height
B496: Single Asset | C496: Residential | D496: Single Family | E496: Villas | H496: UAE | N496: Azalea | O496: 0 | S496: 0 | T496: 0 | U496: 0 | V496: 0 | W496: 0 | X496: 0 | Y496: 0 | Z496: 0 | AA496: 0 | AB496: 0 | AC496: 0 | AD496: 0 | AE496: NO
B497: Mixed Use | C497: Commercial | D497: Multi Family | E497: Villas | H497: KSA | N497: Sidra 3 | O497: 0 | S497: 0 | T497: 0 | U497: 0 | V497: 0 | W497: 0 | X497: 0 | Y497: 0 | Z497: 0 | AA497: 0 | AB497: 0 | AC497: 0 | AD497: 0 | AE497: YES
C498: Retail | D498: Commercial | E498: Villas | H498: Qatar | N498: Club Villas | O498: 0 | S498: 0 | T498: 0 | U498: 0 | V498: 0 | W498: 0 | X498: 0 | Y498: 0 | Z498: 0 | AA498: 0 | AB498: 0 | AC498: 0 | AD498: 0 | AE498: YES
C499: Hospitality | D499: Neighbourhood Centre | E499: Villas | N499: Golf Place Villas (Phase 1) | O499: 0 | S499: 0 | T499: 0 | U499: 0 | V499: 0 | W499: 0 | X499: 0 | Y499: 0 | Z499: 0 | AA499: 0 | AB499: 0 | AC499: 0 | AD499: 0 | AE499: YES
D500: District Centre (Community Mall) | E500: Villas | N500: Al Furjan (P3-V) | O500: 0 | S500: 0 | T500: 0 | U500: 0 | V500: 0 | W500: 0 | X500: 0 | Y500: 0 | Z500: 0 | AA500: 0 | AB500: 0 | AC500: 0 | AD500: 0 | AE500: YES
D501: Mixed Use Retail | E501: Villas | N501: Al Furjan (P5) | O501: 0 | S501: 0 | T501: 0 | U501: 0 | V501: 0 | W501: 0 | X501: 0 | Y501: 0 | Z501: 0 | AA501: 0 | AB501: 0 | AC501: 0 | AD501: 0 | AE501: YES
D502: Outlet Mall | E502: Villas | N502: Golf Place 2 | O502: 0 | S502: 0 | T502: 0 | U502: 0 | V502: 0 | W502: 0 | X502: 0 | Y502: 0 | Z502: 0 | AA502: 0 | AB502: 0 | AC502: 0 | AD502: 0 | AE502: YES
D503: Lifestyle Retail | E503: Villas | N503: Palm Hills Villas | O503: 0 | S503: 0 | T503: 0 | U503: 0 | V503: 0 | W503: 0 | X503: 0 | Y503: 0 | Z503: 0 | AA503: 0 | AB503: 0 | AC503: 0 | AD503: 0 | AE503: YES
D504: Regional Mall | E504: Villas | N504: Majestic Vistas | O504: 0 | S504: 0 | T504: 0 | U504: 0 | V504: 0 | W504: 0 | X504: 0 | Y504: 0 | Z504: 0 | AA504: 0 | AB504: 0 | AC504: 0 | AD504: 0 | AE504: YES
E505: Villas | N505: Elysian Mansions | O505: 0 | S505: 0 | T505: 0 | U505: 0 | V505: 0 | W505: 0 | X505: 0 | Y505: 0 | Z505: 0 | AA505: 0 | AB505: 0 | AC505: 0 | AD505: 0 | AE505: YES
E506: Townhouses | N506: Maple 3 | O506: 0 | S506: 0 | T506: 0 | U506: 0 | V506: 0 | W506: 0 | X506: 0 | Y506: 0 | Z506: 0 | AA506: 0 | AB506: 0 | AC506: 0 | AD506: 0 | AE506: YES
E507: Townhouses | N507: Camelia 1 | O507: 0 | S507: 0 | T507: 0 | U507: 0 | V507: 0 | W507: 0 | X507: 0 | Y507: 0 | Z507: 0 | AA507: 0 | AB507: 0 | AC507: 0 | AD507: 0 | AE507: YES
E508: Townhouses | N508: Camelia 2 | O508: 0 | S508: 0 | T508: 0 | U508: 0 | V508: 0 | W508: 0 | X508: 0 | Y508: 0 | Z508: 0 | AA508: 0 | AB508: 0 | AC508: 0 | AD508: 0 | AE508: YES
E509: Townhouses | N509: Eden (NH01) | O509: 0 | S509: 0 | T509: 0 | U509: 0 | V509: 0 | W509: 0 | X509: 0 | Y509: 0 | Z509: 0 | AA509: 0 | AB509: 0 | AC509: 0 | AD509: 0 | AE509: YES
E510: Townhouses | N510: Al Furjan (P3-T) | O510: 0 | S510: 0 | T510: 0 | U510: 0 | V510: 0 | W510: 0 | X510: 0 | Y510: 0 | Z510: 0 | AA510: 0 | AB510: 0 | AC510: 0 | AD510: 0 | AE510: YES
E511: Townhouses | N511: Nara (NH02) | O511: 0 | S511: 0 | T511: 0 | U511: 0 | V511: 0 | W511: 0 | X511: 0 | Y511: 0 | Z511: 0 | AA511: 0 | AB511: 0 | AC511: 0 | AD511: 0 | AE511: YES
E512: Townhouses | N512: Al Furjan (P14) | O512: 0 | S512: 0 | T512: 0 | U512: 0 | V512: 0 | W512: 0 | X512: 0 | Y512: 0 | Z512: 0 | AA512: 0 | AB512: 0 | AC512: 0 | AD512: 0 | AE512: YES
E513: Townhouses | N513: Al Furjan (P15) | O513: 0 | S513: 0 | T513: 0 | U513: 0 | V513: 0 | W513: 0 | X513: 0 | Y513: 0 | Z513: 0 | AA513: 0 | AB513: 0 | AC513: 0 | AD513: 0 | AE513: YES
E514: Townhouses | N514: Talia (NH03) | O514: 0 | S514: 0 | T514: 0 | U514: 0 | V514: 0 | W514: 0 | X514: 0 | Y514: 0 | Z514: 0 | AA514: 0 | AB514: 0 | AC514: 0 | AD514: 0 | AE514: YES
E515: Townhouses | N515: Orania (NH04) | O515: 0 | S515: 0 | T515: 0 | U515: 0 | V515: 0 | W515: 0 | X515: 0 | Y515: 0 | Z515: 0 | AA515: 0 | AB515: 0 | AC515: 0 | AD515: 0 | AE515: YES
E516: Apartments | N516: Boulevard Heights | O516: 0 | S516: 0 | T516: 0 | U516: 0 | V516: 0 | W516: 0 | X516: 0 | Y516: 0 | Z516: 0 | AA516: 0 | AB516: 0 | AC516: 0 | AD516: 0 | AE516: NO
... E534: Apartments | N534: Como Residences | O534: 0 | S534: 0 | T534: 0 | U534: 0 | V534: 0 | W534: 0 | X534: 0 | Y534: 0 | Z534: 0 | AA534: 0 | AB534: 0 | AC534: 0 | AD534: 0 | AE534: YES
A535: NEW | E535: Apartments | N535: Palm Residences | O535: 0 | S535: 0 | T535: 0 | U535: 0 | V535: 0 | W535: 0 | X535: 0 | Y535: 0 | Z535: 0 | AA535: 0 | AB535: 0 | AC535: 0 | AD535: 0 | AE535: YES
A536: NEW | E536: Apartments | N536: Sea La vie, Yas Towers | O536: 0 | S536: 0 | T536: 0 | U536: 0 | V536: 0 | W536: 0 | X536: 0 | Y536: 0 | Z536: 0 | AA536: 0 | AB536: 0 | AC536: 0 | AD536: 0 | AE536: YES
A537: NEW | E537: Apartments | N537: Ocean House | O537: 0 | S537: 0 | T537: 0 | U537: 0 | V537: 0 | W537: 0 | X537: 0 | Y537: 0 | Z537: 0 | AA537: 0 | AB537: 0 | AC537: 0 | AD537: 0 | AE537: YES
E538: Hospitality | N538: The Address - Sky View | O538: 0 | S538: 0 | T538: 0 | U538: 0 | V538: 0 | W538: 0 | X538: 0 | Y538: 0 | Z538: 0 | AA538: 0 | AB538: 0 | AC538: 0 | AD538: 0 | AE538: YES
E539: Hospitality | N539: Vida Hotel | O539: 0 | S539: 0 | T539: 0 | U539: 0 | V539: 0 | W539: 0 | X539: 0 | Y539: 0 | Z539: 0 | AA539: 0 | AB539: 0 | AC539: 0 | AD539: 0 | AE539: YES
E540: Hospitality | N540: DWD - Plot 05, Hotel | O540: 0 | S540: 0 | T540: 0 | U540: 0 | V540: 0 | W540: 0 | X540: 0 | Y540: 0 | Z540: 0 | AA540: 0 | AB540: 0 | AC540: 0 | AD540: 0 | AE540: YES
E541: Offices | N541: Dubai Hills - Business Park | O541: 0 | S541: 0 | T541: 0 | U541: 0 | V541: 0 | W541: 0 | X541: 0 | Y541: 0 | Z541: 0 | AA541: 0 | AB541: 0 | AC541: 0 | AD541: 0 | AE541: YES
E542: Offices | N542: DWD - Plot 08 | O542: 0 | S542: 0 | T542: 0 | U542: 0 | V542: 0 | W542: 0 | X542: 0 | Y542: 0 | Z542: 0 | AA542: 0 | AB542: 0 | AC542: 0 | AD542: 0 | AE542: YES
E543: Offices | N543: DWD - Plot 09 | O543: 0 | S543: 0 | T543: 0 | U543: 0 | V543: 0 | W543: 0 | X543: 0 | Y543: 0 | Z543: 0 | AA543: 0 | AB543: 0 | AC543: 0 | AD543: 0 | AE543: YES
E544: Offices | N544: Forum Offices | O544: 0 | S544: 0 | T544: 0 | U544: 0 | V544: 0 | W544: 0 | X544: 0 | Y544: 0 | Z544: 0 | AA544: 0 | AB544: 0 | AC544: 0 | AD544: 0 | AE544: YES
E545: Thematic | N545: EXPO 2020, Mobility Pavilion | O545: 0 | S545: 0 | T545: 0 | U545: 0 | V545: 0 | W545: 0 | X545: 0 | Y545: 0 | Z545: 0 | AA545: 0 | AB545: 0 | AC545: 0 | AD545: 0 | AE545: YES
E546: Thematic | N546: EXPO 2020, Sustainability Pavilion | O546: 0 | S546: 0 | T546: 0 | U546: 0 | V546: 0 | W546: 0 | X546: 0 | Y546: 0 | Z546: 0 | AA546: 0 | AB546: 0 | AC546: 0 | AD546: 0 | AE546: YES
...

Sheet Roshan Infra Benchmarking
A1: Asset | B1: Country | C1: City | D1: Area | E1: Alias | F1: Project | G1: Employer | H1: Contractor | I1: Status | J1: Contract | K1: ROW m2 | L1: GLA | M1: GFA (m2) | N1: Element | O1: Total Cost | P1: ROW Rate AED/M2 | Q1: GLA Rate/M2 | R1: GFA Rate | S1: FAR (GFA/GLA) | T1: ROW/GLA | U1: Year | V1: Adjusted Rate/GLA | W1: FAR Code
B2: KSA | C2: Riyadh | D2: Sedra | E2: Project 01 | F2: Sedra 2 | G2: Roshan | H2: TBA | I2: Award | L2: 2900000 | N2: General Items | Q2: =INDEX('[3]ROM Temp'!$H$6:$AB$30, MATCH(N2,'[3]ROM Temp'!$B$6:$B$30, 0), MATCH(E2,'[3]ROM Temp'!$H$4:$AA$4, 0)) -> 0 | V2: =Q2 -> 0
B3: KSA | C3: Riyadh | D3: Sedra | E3: Project 01 | F3: Sedra 2 | G3: Roshan | H3: TBA | I3: Award | L3: 2900000 | N3: Ground Investigation | Q3: =INDEX('[3]ROM Temp'!$H$6:$AB$30, MATCH(N3,'[3]ROM Temp'!$B$6:$B$30, 0), MATCH(E3,'[3]ROM Temp'!$H$4:$AA$4, 0)) -> 0.43252171 | V3: =Q3 -> 0.43252171
B4: KSA | C4: Riyadh | D4: Sedra | E4: Project 01 | F4: Sedra 2 | G4: Roshan | H4: TBA | I4: Award | L4: 2900000 | N4: Demolition and Site Clearance | Q4: =INDEX('[3]ROM Temp'!$H$6:$AB$30, MATCH(N4,'[3]ROM Temp'!$B$6:$B$30, 0), MATCH(E4,'[3]ROM Temp'!$H$4:$AA$4, 0)) -> 0 | V4: =Q4 -> 0
B5: KSA | C5: Riyadh | D5: Sedra | E5: Project 01 | F5: Sedra 2 | G5: Roshan | H5: TBA | I5: Award | L5: 2900000 | N5: Earthworks | Q5: =INDEX('[3]ROM Temp'!$H$6:$AB$30, MATCH(N5,'[3]ROM Temp'!$B$6:$B$30, 0), MATCH(E5,'[3]ROM Temp'!$H$4:$AA$4, 0)) -> 4.6916005 | V5: =Q5 -> 4.6916005
B6: KSA | C6: Riyadh | D6: Sedra | E6: Project 01 | F6: Sedra 2 | G6: Roshan | H6: TBA | I6: Award | L6: 2900000 | N6: Structural Metal Works | Q6: =INDEX('[3]ROM Temp'!$H$6:$AB$30, MATCH(N6,'[3]ROM Temp'!$B$6:$B$30, 0), MATCH(E6,'[3]ROM Temp'!$H$4:$AA$4, 0)) -> 0.016932228 | V6: =Q6 -> 0.016932228
B7: KSA | C7: Riyadh | D7: Sedra | E7: Project 01 | F7: Sedra 2 | G7: Roshan | H7: TBA | I7: Award | L7: 2900000 | N7: Roads and Paving's | Q7: =INDEX('[3]ROM Temp'!$H$6:$AB$30, MATCH(N7,'[3]ROM Temp'!$B$6:$B$30, 0), MATCH(E7,'[3]ROM Temp'!$H$4:$AA$4, 0)) -> 24.865027 | V7: =Q7 -> 24.865027
B8: KSA | C8: Riyadh | D8: Sedra | E8: Project 01 | F8: Sedra 2 | G8: Roshan | H8: TBA | I8: Award | L8: 2900000 | N8: Potable Water Works | Q8: =INDEX('[3]ROM Temp'!$H$6:$AB$30, MATCH(N8,'[3]ROM Temp'!$B$6:$B$30, 0), MATCH(E8,'[3]ROM Temp'!$H$4:$AA$4, 0)) -> 20.090017 | V8: =Q8 -> 20.090017
B9: KSA | C9: Riyadh | D9: Sedra | E9: Project 01 | F9: Sedra 2 | G9: Roshan | H9: TBA | I9: Award | L9: 2900000 | N9: TSE & Irrigation Network | Q9: =INDEX('[3]ROM Temp'!$H$6:$AB$30, MATCH(N9,'[3]ROM Temp'!$B$6:$B$30, 0), MATCH(E9,'[3]ROM Temp'!$H$4:$AA$4, 0)) -> 6.0487926 | V9: =Q9 -> 6.0487926
B10: KSA | C10: Riyadh | D10: Sedra | E10: Project 01 | F10: Sedra 2 | G10: Roshan | H10: TBA | I10: Award | L10: 2900000 | N10: Sewerage Network | Q10: =INDEX('[3]ROM Temp'!$H$6:$AB$30, MATCH(N10,'[3]ROM Temp'!$B$6:$B$30, 0), MATCH(E10,'[3]ROM Temp'!$H$4:$AA$4, 0)) -> 19.585338 | V10: =Q10 -> 19.585338
B11: KSA | C11: Riyadh | D11: Sedra | E11: Project 01 | F11: Sedra 2 | G11: Roshan | H11: TBA | I11: Award | L11: 2900000 | N11: Sewer Treatment Plant/Pumping Station (100% primary) | Q11: =INDEX('[3]ROM Temp'!$H$6:$AB$30, MATCH(N11,'[3]ROM Temp'!$B$6:$B$30, 0), MATCH(E11,'[3]ROM Temp'!$H$4:$AA$4, 0)) -> 0 | V11: =Q11 -> 0
B12: KSA | C12: Riyadh | D12: Sedra | E12: Project 01 | F12: Sedra 2 | G12: Roshan | H12: TBA | I12: Award | L12: 2900000 | N12: Sewerage Lifting Station (100% primary) | Q12: =INDEX('[3]ROM Temp'!$H$6:$AB$30, MATCH(N12,'[3]ROM Temp'!$B$6:$B$30, 0), MATCH(E12,'[3]ROM Temp'!$H$4:$AA$4, 0)) -> 0 | V12: =Q12 -> 0
B13: KSA | C13: Riyadh | D13: Sedra | E13: Project 01 | F13: Sedra 2 | G13: Roshan | H13: TBA | I13: Award | L13: 2900000 | N13: Drainage Network | Q13: =INDEX('[3]ROM Temp'!$H$6:$AB$30, MATCH(N13,'[3]ROM Temp'!$B$6:$B$30, 0), MATCH(E13,'[3]ROM Temp'!$H$4:$AA$4, 0)) -> 12.49692 | V13: =Q13 -> 12.49692
... B28: KSA | C28: Riyadh | D28: Sedra | E28: Project 02 | F28: Sedra 3 | G28: Roshan | H28: TBA | I28: Award | L28: 1821617.1 | N28: Ground Investigation | Q28: =INDEX('[3]ROM Temp'!$H$6:$AB$30, MATCH(N28,'[3]ROM Temp'!$B$6:$B$30, 0), MATCH(E28,'[3]ROM Temp'!$H$4:$AA$4, 0)) -> 0 | V28: =Q28 -> 0
B29: KSA | C29: Riyadh | D29: Sedra | E29: Project 02 | F29: Sedra 3 | G29: Roshan | H29: TBA | I29: Award | L29: 1821617.1 | N29: Demolition and Site Clearance | Q29: =INDEX('[3]ROM Temp'!$H$6:$AB$30, MATCH(N29,'[3]ROM Temp'!$B$6:$B$30, 0), MATCH(E29,'[3]ROM Temp'!$H$4:$AA$4, 0)) -> 2.5076029
B30: KSA | C30: Riyadh | D30: Sedra | E30: Project 02 | F30: Sedra 3 | G30: Roshan | H30: TBA | I30: Award | L30: 1821617.1 | N30: Earthworks | Q30: =INDEX('[3]ROM Temp'!$H$6:$AB$30, MATCH(N30,'[3]ROM Temp'!$B$6:$B$30, 0), MATCH(E30,'[3]ROM Temp'!$H$4:$AA$4, 0)) -> 29.618159
B31: KSA | C31: Riyadh | D31: Sedra | E31: Project 02 | F31: Sedra 3 | G31: Roshan | H31: TBA | I31: Award | L31: 1821617.1 | N31: Structural Metal Works | Q31: =INDEX('[3]ROM Temp'!$H$6:$AB$30, MATCH(N31,'[3]ROM Temp'!$B$6:$B$30, 0), MATCH(E31,'[3]ROM Temp'!$H$4:$AA$4, 0)) -> 0
B32: KSA | C32: Riyadh | D32: Sedra | E32: Project 02 | F32: Sedra 3 | G32: Roshan | H32: TBA | I32: Award | L32: 1821617.1 | N32: Roads and Paving's | Q32: =INDEX('[3]ROM Temp'!$H$6:$AB$30, MATCH(N32,'[3]ROM Temp'!$B$6:$B$30, 0), MATCH(E32,'[3]ROM Temp'!$H$4:$AA$4, 0)) -> 40.8835
B33: KSA | C33: Riyadh | D33: Sedra | E33: Project 02 | F33: Sedra 3 | G33: Roshan | H33: TBA | I33: Award | L33: 1821617.1 | N33: Potable Water Works | Q33: =INDEX('[3]ROM Temp'!$H$6:$AB$30, MATCH(N33,'[3]ROM Temp'!$B$6:$B$30, 0), MATCH(E33,'[3]ROM Temp'!$H$4:$AA$4, 0)) -> 23.184338
B34: KSA | C34: Riyadh | D34: Sedra | E34: Project 02 | F34: Sedra 3 | G34: Roshan | H34: TBA | I34: Award | L34: 1821617.1 | N34: TSE & Irrigation Network | Q34: =INDEX('[3]ROM Temp'!$H$6:$AB$30, MATCH(N34,'[3]ROM Temp'!$B$6:$B$30, 0), MATCH(E34,'[3]ROM Temp'!$H$4:$AA$4, 0)) -> 9.2568266
B35: KSA | C35: Riyadh | D35: Sedra | E35: Project 02 | F35: Sedra 3 | G35: Roshan | H35: TBA | I35: Award | L35: 1821617.1 | N35: Sewerage Network | Q35: =INDEX('[3]ROM Temp'!$H$6:$AB$30, MATCH(N35,'[3]ROM Temp'!$B$6:$B$30, 0), MATCH(E35,'[3]ROM Temp'!$H$4:$AA$4, 0)) -> 22.040863
B36: KSA | C36: Riyadh | D36: Sedra | E36: Project 02 | F36: Sedra 3 | G36: Roshan | H36: TBA | I36: Award | L36: 1821617.1 | N36: Sewer Treatment Plant/Pumping Station (100% primary) | Q36: =INDEX('[3]ROM Temp'!$H$6:$AB$30, MATCH(N36,'[3]ROM Temp'!$B$6:$B$30, 0), MATCH(E36,'[3]ROM Temp'!$H$4:$AA$4, 0)) -> 0
B37: KSA | C37: Riyadh | D37: Sedra | E37: Project 02 | F37: Sedra 3 | G37: Roshan | H37: TBA | I37: Award | L37: 1821617.1 | N37: Sewerage Lifting Station (100% primary) | Q37: =INDEX('[3]ROM Temp'!$H$6:$AB$30, MATCH(N37,'[3]ROM Temp'!$B$6:$B$30, 0), MATCH(E37,'[3]ROM Temp'!$H$4:$AA$4, 0)) -> 0
B38: KSA | C38: Riyadh | D38: Sedra | E38: Project 02 | F38: Sedra 3 | G38: Roshan | H38: TBA | I38: Award | L38: 1821617.1 | N38: Drainage Network | Q38: =INDEX('[3]ROM Temp'!$H$6:$AB$30, MATCH(N38,'[3]ROM Temp'!$B$6:$B$30, 0), MATCH(E38,'[3]ROM Temp'!$H$4:$AA$4, 0)) -> 14.093123
B39: KSA | C39: Riyadh | D39: Sedra | E39: Project 02 | F39: Sedra 3 | G39: Roshan | H39: TBA | I39: Award | L39: 1821617.1 | N39: Potable Water tank & Pumping Station/tank (100% primary) | Q39: =INDEX('[3]ROM Temp'!$H$6:$AB$30, MATCH(N39,'[3]ROM Temp'!$B$6:$B$30, 0), MATCH(E39,'[3]ROM Temp'!$H$4:$AA$4, 0)) -> 0
B40: KSA | C40: Riyadh | D40: Sedra | E40: Project 02 | F40: Sedra 3 | G40: Roshan | H40: TBA | I40: Award | L40: 1821617.1 | N40: Irrigation Pumping Station/Water tank (100% primary) | Q40: =INDEX('[3]ROM Temp'!$H$6:$AB$30, MATCH(N40,'[3]ROM Temp'!$B$6:$B$30, 0), MATCH(E40,'[3]ROM Temp'!$H$4:$AA$4, 0)) -> 0
... B100: KSA | C100: Riyadh | D100: Sedra | E100: Project 04 | F100: Sedra 5 | G100: Roshan | H100: TBA | I100: Award | L100: 1355481.1 | N100: ICT Network (Telecommunication Network) | Q100: =INDEX('[3]ROM Temp'!$H$6:$AB$30, MATCH(N100,'[3]ROM Temp'!$B$6:$B$30, 0), MATCH(E100,'[3]ROM Temp'!$H$4:$AA$4, 0)) -> 0
B101: KSA | C101: Makkah | E101: Project 04 | F101: Makkah Phase 01 | G101: Roshan | H101: TBA | I101: Award | L101: 2577469 | N101: Power Station/Bulk substation & Primary substation (100% primary) | Q101: =INDEX('[3]ROM Temp'!$H$6:$AB$30, MATCH(N101,'[3]ROM Temp'!$B$6:$B$30, 0), MATCH(E101,'[3]ROM Temp'!$H$4:$AA$4, 0)) -> 0
B102: KSA | C102: Makkah | E102: Project 05 | F102: Makkah Phase 01 | G102: Roshan | H102: TBA | I102: Award | L102: 2577469 | N102: General Items | Q102: =INDEX('[3]ROM Temp'!$H$6:$AB$30, MATCH(N102,'[3]ROM Temp'!$B$6:$B$30, 0), MATCH(E102,'[3]ROM Temp'!$H$4:$AA$4, 0)) -> 0
B103: KSA | C103: Makkah | E103: Project 05 | F103: Makkah Phase 01 | G103: Roshan | H103: TBA | I103: Award | L103: 2577469 | N103: Ground Investigation | Q103: =INDEX('[3]ROM Temp'!$H$6:$AB$30, MATCH(N103,'[3]ROM Temp'!$B$6:$B$30, 0), MATCH(E103,'[3]ROM Temp'!$H$4:$AA$4, 0)) -> 0
B104: KSA | C104: Makkah | E104: Project 05 | F104: Makkah Phase 01 | G104: Roshan | H104: TBA | I104: Award | L104: 2577469 | N104: Demolition and Site Clearance | Q104: =INDEX('[3]ROM Temp'!$H$6:$AB$30, MATCH(N104,'[3]ROM Temp'!$B$6:$B$30, 0), MATCH(E104,'[3]ROM Temp'!$H$4:$AA$4, 0)) -> 3.3563469
B105: KSA | C105: Makkah | E105: Project 05 | F105: Makkah Phase 01 | G105: Roshan | H105: TBA | I105: Award | L105: 2577469 | N105: Earthworks | Q105: =INDEX('[3]ROM Temp'!$H$6:$AB$30, MATCH(N105,'[3]ROM Temp'!$B$6:$B$30, 0), MATCH(E105,'[3]ROM Temp'!$H$4:$AA$4, 0)) -> 14.454225
B106: KSA | C106: Makkah | E106: Project 05 | F106: Makkah Phase 01 | G106: Roshan | H106: TBA | I106: Award | L106: 2577469 | N106: Structural Metal Works | Q106: =INDEX('[3]ROM Temp'!$H$6:$AB$30, MATCH(N106,'[3]ROM Temp'!$B$6:$B$30, 0), MATCH(E106,'[3]ROM Temp'!$H$4:$AA$4, 0)) -> 0
B107: KSA | C107: Makkah | E107: Project 05 | F107: Makkah Phase 01 | G107: Roshan | H107: TBA | I107: Award | L107: 2577469 | N107: Roads and Paving's | Q107: =INDEX('[3]ROM Temp'!$H$6:$AB$30, MATCH(N107,'[3]ROM Temp'!$B$6:$B$30, 0), MATCH(E107,'[3]ROM Temp'!$H$4:$AA$4, 0)) -> 40.377372
B108: KSA | C108: Makkah | E108: Project 05 | F108: Makkah Phase 01 | G108: Roshan | H108: TBA | I108: Award | L108: 2577469 | N108: Potable Water Works | Q108: =INDEX('[3]ROM Temp'!$H$6:$AB$30, MATCH(N108,'[3]ROM Temp'!$B$6:$B$30, 0), MATCH(E108,'[3]ROM Temp'!$H$4:$AA$4, 0)) -> 18.215627
B109: KSA | C109: Makkah | E109: Project 05 | F109: Makkah Phase 01 | G109: Roshan | H109: TBA | I109: Award | L109: 2577469 | N109: TSE & Irrigation Network | Q109: =INDEX('[3]ROM Temp'!$H$6:$AB$30, MATCH(N109,'[3]ROM Temp'!$B$6:$B$30, 0), MATCH(E109,'[3]ROM Temp'!$H$4:$AA$4, 0)) -> 8.0302366
B110: KSA | C110: Makkah | E110: Project 05 | F110: Makkah Phase 01 | G110: Roshan | H110: TBA | I110: Award | L110: 2577469 | N110: Sewerage Network | Q110: =INDEX('[3]ROM Temp'!$H$6:$AB$30, MATCH(N110,'[3]ROM Temp'!$B$6:$B$30, 0), MATCH(E110,'[3]ROM Temp'!$H$4:$AA$4, 0)) -> 18.606536
B111: KSA | C111: Makkah | E111: Project 05 | F111: Makkah Phase 01 | G111: Roshan | H111: TBA | I111: Award | L111: 2577469 | N111: Sewer Treatment Plant/Pumping Station (100% primary) | Q111: =INDEX('[3]ROM Temp'!$H$6:$AB$30, MATCH(N111,'[3]ROM Temp'!$B$6:$B$30, 0), MATCH(E111,'[3]ROM Temp'!$H$4:$AA$4, 0)) -> 21.575249
B112: KSA | C112: Makkah | E112: Project 05 | F112: Makkah Phase 01 | G112: Roshan | H112: TBA | I112: Award | L112: 2577469 | N112: Sewerage Lifting Station (100% primary) | Q112: =INDEX('[3]ROM Temp'!$H$6:$AB$30, MATCH(N112,'[3]ROM Temp'!$B$6:$B$30, 0), MATCH(E112,'[3]ROM Temp'!$H$4:$AA$4, 0)) -> 0
... B176: KSA | C176: Riyadh | E176: Project 07 | F176: Riyadh East | G176: Roshan | H176: TBA | I176: Award | L176: 1418268 | N176: Power Station/Bulk substation & Primary substation (100% primary) | Q176: =INDEX('[3]ROM Temp'!$H$6:$AB$30, MATCH(N176,'[3]ROM Temp'!$B$6:$B$30, 0), MATCH(E176,'[3]ROM Temp'!$H$4:$AA$4, 0)) -> 0
B177: KSA | C177: Riyadh | E177: Project 08 | F177: Roshan average and adjusted | G177: Roshan | H177: TBA | I177: Award | N177: General Items | Q177: =INDEX('[3]ROM Temp'!$H$6:$AB$30, MATCH(N177,'[3]ROM Temp'!$B$6:$B$30, 0), MATCH(E177,'[3]ROM Temp'!$H$4:$AA$4, 0)) -> 0
B178: KSA | C178: Riyadh | E178: Project 08 | F178: Roshan average and adjusted | G178: Roshan | H178: TBA | I178: Award | N178: Ground Investigation | Q178: =INDEX('[3]ROM Temp'!$H$6:$AB$30, MATCH(N178,'[3]ROM Temp'!$B$6:$B$30, 0), MATCH(E178,'[3]ROM Temp'!$H$4:$AA$4, 0)) -> 1.0644885
B179: KSA | C179: Riyadh | E179: Project 08 | F179: Roshan average and adjusted | G179: Roshan | H179: TBA | I179: Award | N179: Demolition and Site Clearance | Q179: =INDEX('[3]ROM Temp'!$H$6:$AB$30, MATCH(N179,'[3]ROM Temp'!$B$6:$B$30, 0), MATCH(E179,'[3]ROM Temp'!$H$4:$AA$4, 0)) -> 3.8601588
B180: KSA | C180: Riyadh | E180: Project 08 | F180: Roshan average and adjusted | G180: Roshan | H180: TBA | I180: Award | N180: Earthworks | Q180: =INDEX('[3]ROM Temp'!$H$6:$AB$30, MATCH(N180,'[3]ROM Temp'!$B$6:$B$30, 0), MATCH(E180,'[3]ROM Temp'!$H$4:$AA$4, 0)) -> 32.498189
B181: KSA | C181: Riyadh | E181: Project 08 | F181: Roshan average and adjusted | G181: Roshan | H181: TBA | I181: Award | N181: Structural Metal Works | Q181: =INDEX('[3]ROM Temp'!$H$6:$AB$30, MATCH(N181,'[3]ROM Temp'!$B$6:$B$30, 0), MATCH(E181,'[3]ROM Temp'!$H$4:$AA$4, 0)) -> 0.59711107
B182: KSA | C182: Riyadh | E182: Project 08 | F182: Roshan average and adjusted | G182: Roshan | H182: TBA | I182: Award | N182: Roads and Paving's | Q182: =INDEX('[3]ROM Temp'!$H$6:$AB$30, MATCH(N182,'[3]ROM Temp'!$B$6:$B$30, 0), MATCH(E182,'[3]ROM Temp'!$H$4:$AA$4, 0)) -> 38.314549
